Workbook

Sheet Listas
A1: ID | B1: Corregimiento | C1: Veredas | D1: Area_km2
A2: 1 | B2: Atuncela | C2: Puerto Dagua | D2: 292,13
A3: 2 | B3: Borrero Ayerbe | C3: Km 26, Ambichinte, Pueblo Nuevo, El Vergel, Km 28, Agua Sucia, El Crucero, La Zulia y El Descanso | D3: 204,95
A4: 3 | B4: Cisneros | C4: La Guinea Baja y La Guinea Alta | D4: 79,65
A5: 4 | B5: El Carmen | C5: La Clorinda, Las Tórtolas, Loma Linda, El Galpón y Bahondo | D5: 367,07
A6: 5 | B6: El Danubio | C6: Km 81 y Los Monos | D6: 481,96
A7: 6 | B7: El Limonar | C7: El Chilcal, Monterredondo, Honduras, El Tablazo, Consuegra, La Soledad y Junticas | D7: 322,32
A8: 7 | B8: El Naranjo | C8: La Reina, Peñas Gordas, La Victoria y Galeras | D8: 112,25
A9: 8 | B9: El Palmar | C9: Las Brisas, La Colonia, Centella, Puerto Cosson, Yerbabuena, La Virgen, La Pulida y Palo Alto | D9: 274,05
A10: 9 | B10: El Pinal | C10: Bolivia, Manantiales y El Zapote | D10: 408,85
A11: 10 | B11: El Queremal | C11: Las Camellas, La Rosita, Machado, El Almorzadero, El Tigre, Sendo, Potrerillo y Paraguitas | D11: 979,1
A12: 11 | B12: El Rucio | C12: La Samaria, Vista Hermosa y La Floresta | D12: 276,9
A13: 12 | B13: El Salado | C13: Piedra Pintada, San Antonio, El Aguacate y El Porvenir | D13: 195
A14: 13 | B14: Jiguales | D14: 135,52
A15: 14 | B15: Juntas | C15: La Puerta, San Cristóbal, La Cedrera, La Siria y Sombrerillos | D15: 416,5
A16: 15 | B16: Kilómetro 18 | D16: 60,75
A17: 16 | B17: La Cascada | C17: El Placer, La Mona y El Cauchal | D17: 298,21
A18: 17 | B18: La Elsa | C18: El Engano, Río Blanco, El Digua y Las Curvas | D18: 1.244,6
A19: 18 | B19: Loboguerrero | C19: La Yolomba y La Chapa | D19: 286,8
A20: 19 | B20: Los Alpes | C20: La Garza, Amapola, El Rosal y La Virgen | D20: 234,7
A21: 20 | B21: Los Cristales | C21: Tolda Seca, Vega Grande, Pepitas y El Hormiguero | D21: 538,4
A22: 21 | B22: Providencia | C22: La Esmeralda | D22: 803,7
A23: 22 | B23: San Bernardo | C23: El Jordán, El Jordancito, San Miguel, El Triunfo, El Diviso, Loma Alta, La Tigra, Ben Hur, San Luis y Tocotá | D23: 338,27
A24: 23 | B24: San Vicente | C24: El Pajal y San Joaquín | D24: 457,72
A25: 24 | B25: Santa María | C25: Siempreviva, Cerro Azul y Anegas | D25: 320,41
A26: 25 | B26: Villahermosa | C26: La Esperanza, Las Camelias- K. 95 y Las Delicias | D26: 126,57
A27: 26 | B27: Zabaletas | C27: Carrisales, Bella Vista, El Trapiche y La Velmira | D27: 188,79
A28: 27 | B28: Zelandia | C28: Aguas Lindas | D28: 430

Sheet ABC COSTEO
A1: COSTEO ABC – ACTIVITY BASED COSTING · TRIPLE AAA
A2: Metodología: Kaplan & Cooper (1998) adaptada a transporte PYME colombiano (Mora García, 2008)
A4: DRIVER 1 – COSTOS POR ACTIVIDAD DE VIAJE
A5: Rubro | B5: Monto Mensual | C5: Clasificación | D5: Justificación
A6: Conductor – salario+prest. (2) | B6: 5124456 | C6: Costo Fijo | D6: Personal debe pagarse cada mes
A7: Ayudante – salario+prest. (2) | B7: 4594580 | C7: Costo Fijo | D7: Personal debe pagarse cada mes
A8: Bocato | B8: 58666.67 | C8: Costo Fijo | D8: Minicargador
A9: TOTAL COSTOS FIJOS (Driver 1) | B9: =SUM(B6:B8) -> 9777702.7 | C9: 67.13% del total
A10: ÷ Viajes estimados al mes | B10: =COUNT(Tabla3[N° FACTURA]) -> 240 | D10: Envios en el mes de noviembre
A11: CF POR VIAJE (costo fijo de salir una vez) | B11: =IFERROR(B9/B10,0) -> 40740.428
A13: DRIVER 2 – COSTOS POR KM RECORRIDO (variables con la distancia)
A14: Rubro | B14: Monto Mensual | C14: Clasificación | D14: Justificación
A15: ACPM / Diesel (2 vehículos) | B15: 1893969 | C15: Costo Variable | D15: A mayor km, mayor consumo
A16: Mantenimiento (2 vehículos) | B16: 1000000 | C16: Semi-Variable | D16: Se intensifica con el uso del vehículo
A17: TOTAL COSTOS VARIABLES (Driver 2) | B17: =SUM(B15:B16) -> 2893969 | C17: 32.87% del total | D17: 21% son costos VARIABLES — crecen con los km recorridos
A18: × Km promedio por viaje (solo ida) | B18: =AVERAGE(Tabla3[DISTANCIA (km)]) -> 4.4318197 | D18: Promedio calculado de la base de noviembre
A19: × Factor 2 (vehículo regresa vacío desde destino) | B19: 2
A20: Km totales recorridos al mes | B20: =B10*B18*2 -> 2127.2734
A21: CV POR KM (costo variable por cada km adicional) | B21: =IFERROR(B17/B20,0) -> 1360.4123 | D21: Por cada km extra de distancia, este es el costo adicional
A23: RESUMEN ABC – FÓRMULA DE COSTO POR ENVÍO
A24: Ingrese la distancia del envío (km ida) | B24: 5.5 | D24: ← Ejemplo: Limonar 5.5 km
A25: Peso estimado del envío (kg) | B25: 45 | D25: ← Ferretería: promedio estimado 45 kg
A26: Factor peso (recargo si >50 kg) | B26: =IF(B25>50,1+(B25-50)*0.002,1) -> 1 | D26: Mora García (2008): recargo proporcional al exceso de peso
A27: Número de viajes / transportes | B27: 1
A28: Componente 1 – Costo fijo del viaje | B28: =IFERROR(B9/B10*B27,0) -> 40740.428 | D28: CF/viaje × número de transportes
A29: Componente 2 – Costo variable por km | B29: =B24*2*IFERROR(4787938/B20,0)*B26*B27 -> 24758.133 | D29: CV/km × distancia×2 × factor peso × transportes
A30: COSTO ABC TOTAL DEL ENVÍO | B30: =B28+B29 -> 65498.56 | D30: Kaplan & Cooper: suma de todos los drivers de costo

Sheet Fechas Y ubicaciones
A1: Fecha | B1: Total de envios | C1: Valor | E1: Nombre | F1: Numero de Facturas | G1: Numero de envios | H1: % | I1: Valor envio | J1: Promedio | K1: Distancia (KM) | L1: Distancia total ida y vuelta | N1: Corregimiento | O1: Total de transportes | P1: Valor total de transporte | Q1: Distancia Promedio por corregimiento | R1: Valor promedio de transporte por corregimiento | S1: Valor promedio del costo calculo con ABC | T1: Perdida promedio de margen
A2: 45962 | B2: =COUNTIF(Tabla3[FECHA],Tabla4[[#This Row],[Fecha]]) -> 14 | C2: =SUMIF(Tabla3[FECHA],Tabla4[[#This Row],[Fecha]],Tabla3[VLR. TRANSPORTE]) -> 695000 | E2: Parcelación Pirineos | F2: =COUNTIF(Tabla3[LUGAR ENVÍO],Tabla6[[#This Row],[Nombre]]) -> 0 | G2: =SUMIF(Tabla3[LUGAR ENVÍO],Tabla6[[#This Row],[Nombre]],Tabla3[Numero de Transportes]) -> 0 | H2: =Tabla6[[#This Row],[Numero de Facturas]]/Tabla6[[#Totals],[Numero de Facturas]] -> 0 | I2: =SUMIF(Tabla3[LUGAR ENVÍO],Tabla6[[#This Row],[Nombre]],Tabla3[VLR. TRANSPORTE]) -> 0 | J2: =AVERAGEIF(Tabla3[LUGAR ENVÍO],Tabla6[[#This Row],[Nombre]],Tabla3[VLR. TRANSPORTE]) -> #DIV/0! | K2: =Tabla6[[#This Row],[Distancia total ida y vuelta]]/Tabla6[[#This Row],[Numero de Facturas]] -> #DIV/0! | L2: =SUMIF(Tabla3[LUGAR ENVÍO],Tabla6[[#This Row],[Nombre]],Tabla3[DISTANCIA (km)]) -> 0 | N2: El Carmen | O2: =COUNTIF(Tabla3[Corregimiento],Tabla7[[#This Row],[Corregimiento]]) -> 101 | P2: =SUMIF(Tabla3[Corregimiento],Tabla7[[#This Row],[Corregimiento]],Tabla3[VLR. TRANSPORTE]) -> 5630000 | Q2: =AVERAGEIF(Tabla3[Corregimiento],Tabla7[[#This Row],[Corregimiento]],Tabla3[DISTANCIA (km)]) -> 4.2490918 | R2: =AVERAGEIF(Tabla3[Corregimiento],Tabla7[[#This Row],[Corregimiento]],Tabla3[Valor Tran]) -> 50495.05 | S2: =AVERAGEIF(Tabla8[Corregimiento],Tabla7[[#This Row],[Corregimiento]],Tabla8[Costo Total]) -> 52121.823 | T2: =AVERAGEIF(Tabla8[Corregimiento],Tabla7[[#This Row],[Corregimiento]],Tabla8[Perdida o ganancia de margen]) -> -0.063998881
A3: 45963 | B3: =COUNTIF(Tabla3[FECHA],Tabla4[[#This Row],[Fecha]]) -> 1 | C3: =SUMIF(Tabla3[FECHA],Tabla4[[#This Row],[Fecha]],Tabla3[VLR. TRANSPORTE]) -> 60000 | E3: El Coscorron | F3: =COUNTIF(Tabla3[LUGAR ENVÍO],Tabla6[[#This Row],[Nombre]]) -> 11 | G3: =SUMIF(Tabla3[LUGAR ENVÍO],Tabla6[[#This Row],[Nombre]],Tabla3[Numero de Transportes]) -> 15 | H3: =Tabla6[[#This Row],[Numero de Facturas]]/Tabla6[[#Totals],[Numero de Facturas]] -> 0.15942029 | I3: =SUMIF(Tabla3[LUGAR ENVÍO],Tabla6[[#This Row],[Nombre]],Tabla3[VLR. TRANSPORTE]) -> 985000 | J3: =AVERAGEIF(Tabla3[LUGAR ENVÍO],Tabla6[[#This Row],[Nombre]],Tabla3[VLR. TRANSPORTE]) -> 89545.455 | K3: =Tabla6[[#This Row],[Distancia total ida y vuelta]]/Tabla6[[#This Row],[Numero de Facturas]] -> 2.65 | L3: =SUMIF(Tabla3[LUGAR ENVÍO],Tabla6[[#This Row],[Nombre]],Tabla3[DISTANCIA (km)]) -> 29.15 | N3: Borrero Ayerbe | O3: =COUNTIF(Tabla3[Corregimiento],Tabla7[[#This Row],[Corregimiento]]) -> 90 | P3: =SUMIF(Tabla3[Corregimiento],Tabla7[[#This Row],[Corregimiento]],Tabla3[VLR. TRANSPORTE]) -> 4195000 | Q3: =AVERAGEIF(Tabla3[Corregimiento],Tabla7[[#This Row],[Corregimiento]],Tabla3[DISTANCIA (km)]) -> 2.4517922 | R3: =AVERAGEIF(Tabla3[Corregimiento],Tabla7[[#This Row],[Corregimiento]],Tabla3[Valor Tran]) -> 37222.222 | S3: =AVERAGEIF(Tabla8[Corregimiento],Tabla7[[#This Row],[Corregimiento]],Tabla8[Costo Total]) -> 47463.142 | T3: =AVERAGEIF(Tabla8[Corregimiento],Tabla7[[#This Row],[Corregimiento]],Tabla8[Perdida o ganancia de margen]) -> -0.13028936
A4: 45964 | B4: =COUNTIF(Tabla3[FECHA],Tabla4[[#This Row],[Fecha]]) -> 2 | C4: =SUMIF(Tabla3[FECHA],Tabla4[[#This Row],[Fecha]],Tabla3[VLR. TRANSPORTE]) -> 120000 | E4: Tortolas | F4: =COUNTIF(Tabla3[LUGAR ENVÍO],Tabla6[[#This Row],[Nombre]]) -> 7 | G4: =SUMIF(Tabla3[LUGAR ENVÍO],Tabla6[[#This Row],[Nombre]],Tabla3[Numero de Transportes]) -> 8 | H4: =Tabla6[[#This Row],[Numero de Facturas]]/Tabla6[[#Totals],[Numero de Facturas]] -> 0.10144928 | I4: =SUMIF(Tabla3[LUGAR ENVÍO],Tabla6[[#This Row],[Nombre]],Tabla3[VLR. TRANSPORTE]) -> 580000 | J4: =AVERAGEIF(Tabla3[LUGAR ENVÍO],Tabla6[[#This Row],[Nombre]],Tabla3[VLR. TRANSPORTE]) -> 82857.143 | K4: =Tabla6[[#This Row],[Distancia total ida y vuelta]]/Tabla6[[#This Row],[Numero de Facturas]] -> 5.757 | L4: =SUMIF(Tabla3[LUGAR ENVÍO],Tabla6[[#This Row],[Nombre]],Tabla3[DISTANCIA (km)]) -> 40.299 | N4: El Limonar | O4: =COUNTIF(Tabla3[Corregimiento],Tabla7[[#This Row],[Corregimiento]]) -> 26 | P4: =SUMIF(Tabla3[Corregimiento],Tabla7[[#This Row],[Corregimiento]],Tabla3[VLR. TRANSPORTE]) -> 1745000 | Q4: =AVERAGEIF(Tabla3[Corregimiento],Tabla7[[#This Row],[Corregimiento]],Tabla3[DISTANCIA (km)]) -> 6.2415442 | R4: =AVERAGEIF(Tabla3[Corregimiento],Tabla7[[#This Row],[Corregimiento]],Tabla3[Valor Tran]) -> 51730.769 | S4: =AVERAGEIF(Tabla8[Corregimiento],Tabla7[[#This Row],[Corregimiento]],Tabla8[Costo Total]) -> 57793.765 | T4: =AVERAGEIF(Tabla8[Corregimiento],Tabla7[[#This Row],[Corregimiento]],Tabla8[Perdida o ganancia de margen]) -> -0.14504127
A5: 45965 | B5: =COUNTIF(Tabla3[FECHA],Tabla4[[#This Row],[Fecha]]) -> 4 | C5: =SUMIF(Tabla3[FECHA],Tabla4[[#This Row],[Fecha]],Tabla3[VLR. TRANSPORTE]) -> 190000 | E5: KM 34 | F5: =COUNTIF(Tabla3[LUGAR ENVÍO],Tabla6[[#This Row],[Nombre]]) -> 8 | G5: =SUMIF(Tabla3[LUGAR ENVÍO],Tabla6[[#This Row],[Nombre]],Tabla3[Numero de Transportes]) -> 10 | H5: =Tabla6[[#This Row],[Numero de Facturas]]/Tabla6[[#Totals],[Numero de Facturas]] -> 0.11594203 | I5: =SUMIF(Tabla3[LUGAR ENVÍO],Tabla6[[#This Row],[Nombre]],Tabla3[VLR. TRANSPORTE]) -> 390000 | J5: =AVERAGEIF(Tabla3[LUGAR ENVÍO],Tabla6[[#This Row],[Nombre]],Tabla3[VLR. TRANSPORTE]) -> 48750 | K5: =Tabla6[[#This Row],[Distancia total ida y vuelta]]/Tabla6[[#This Row],[Numero de Facturas]] -> 4.316 | L5: =SUMIF(Tabla3[LUGAR ENVÍO],Tabla6[[#This Row],[Nombre]],Tabla3[DISTANCIA (km)]) -> 34.528 | N5: El Salado | O5: =COUNTIF(Tabla3[Corregimiento],Tabla7[[#This Row],[Corregimiento]]) -> 8 | P5: =SUMIF(Tabla3[Corregimiento],Tabla7[[#This Row],[Corregimiento]],Tabla3[VLR. TRANSPORTE]) -> 560000 | Q5: =AVERAGEIF(Tabla3[Corregimiento],Tabla7[[#This Row],[Corregimiento]],Tabla3[DISTANCIA (km)]) -> 11.97575 | R5: =AVERAGEIF(Tabla3[Corregimiento],Tabla7[[#This Row],[Corregimiento]],Tabla3[Valor Tran]) -> 57500 | S5: =AVERAGEIF(Tabla8[Corregimiento],Tabla7[[#This Row],[Corregimiento]],Tabla8[Costo Total]) -> 73324.343 | T5: =AVERAGEIF(Tabla8[Corregimiento],Tabla7[[#This Row],[Corregimiento]],Tabla8[Perdida o ganancia de margen]) -> -0.18768168
A6: 45966 | B6: =COUNTIF(Tabla3[FECHA],Tabla4[[#This Row],[Fecha]]) -> 9 | C6: =SUMIF(Tabla3[FECHA],Tabla4[[#This Row],[Fecha]],Tabla3[VLR. TRANSPORTE]) -> 495000 | E6: Altos del Carmen | F6: =COUNTIF(Tabla3[LUGAR ENVÍO],Tabla6[[#This Row],[Nombre]]) -> 9 | G6: =SUMIF(Tabla3[LUGAR ENVÍO],Tabla6[[#This Row],[Nombre]],Tabla3[Numero de Transportes]) -> 9 | H6: =Tabla6[[#This Row],[Numero de Facturas]]/Tabla6[[#Totals],[Numero de Facturas]] -> 0.13043478 | I6: =SUMIF(Tabla3[LUGAR ENVÍO],Tabla6[[#This Row],[Nombre]],Tabla3[VLR. TRANSPORTE]) -> 460000 | J6: =AVERAGEIF(Tabla3[LUGAR ENVÍO],Tabla6[[#This Row],[Nombre]],Tabla3[VLR. TRANSPORTE]) -> 51111.111 | K6: =Tabla6[[#This Row],[Distancia total ida y vuelta]]/Tabla6[[#This Row],[Numero de Facturas]] -> 5.464 | L6: =SUMIF(Tabla3[LUGAR ENVÍO],Tabla6[[#This Row],[Nombre]],Tabla3[DISTANCIA (km)]) -> 49.176 | N6: San Bernardo | O6: =COUNTIF(Tabla3[Corregimiento],Tabla7[[#This Row],[Corregimiento]]) -> 7 | P6: =SUMIF(Tabla3[Corregimiento],Tabla7[[#This Row],[Corregimiento]],Tabla3[VLR. TRANSPORTE]) -> 365000 | Q6: =AVERAGEIF(Tabla3[Corregimiento],Tabla7[[#This Row],[Corregimiento]],Tabla3[DISTANCIA (km)]) -> 9.1617143 | R6: =AVERAGEIF(Tabla3[Corregimiento],Tabla7[[#This Row],[Corregimiento]],Tabla3[Valor Tran]) -> 47857.143 | S6: =AVERAGEIF(Tabla8[Corregimiento],Tabla7[[#This Row],[Corregimiento]],Tabla8[Costo Total]) -> 65667.846 | T6: =AVERAGEIF(Tabla8[Corregimiento],Tabla7[[#This Row],[Corregimiento]],Tabla8[Perdida o ganancia de margen]) -> -0.19185042
A7: 45967 | B7: =COUNTIF(Tabla3[FECHA],Tabla4[[#This Row],[Fecha]]) -> 10 | C7: =SUMIF(Tabla3[FECHA],Tabla4[[#This Row],[Fecha]],Tabla3[VLR. TRANSPORTE]) -> 480000 | E7: Parcelacion la Cristalina | F7: =COUNTIF(Tabla3[LUGAR ENVÍO],Tabla6[[#This Row],[Nombre]]) -> 5 | G7: =SUMIF(Tabla3[LUGAR ENVÍO],Tabla6[[#This Row],[Nombre]],Tabla3[Numero de Transportes]) -> 5 | H7: =Tabla6[[#This Row],[Numero de Facturas]]/Tabla6[[#Totals],[Numero de Facturas]] -> 0.072463768 | I7: =SUMIF(Tabla3[LUGAR ENVÍO],Tabla6[[#This Row],[Nombre]],Tabla3[VLR. TRANSPORTE]) -> 270000 | J7: =AVERAGEIF(Tabla3[LUGAR ENVÍO],Tabla6[[#This Row],[Nombre]],Tabla3[VLR. TRANSPORTE]) -> 54000 | K7: =Tabla6[[#This Row],[Distancia total ida y vuelta]]/Tabla6[[#This Row],[Numero de Facturas]] -> 2.71 | L7: =SUMIF(Tabla3[LUGAR ENVÍO],Tabla6[[#This Row],[Nombre]],Tabla3[DISTANCIA (km)]) -> 13.55 | N7: El Queremal | O7: =COUNTIF(Tabla3[Corregimiento],Tabla7[[#This Row],[Corregimiento]]) -> 4 | P7: =SUMIF(Tabla3[Corregimiento],Tabla7[[#This Row],[Corregimiento]],Tabla3[VLR. TRANSPORTE]) -> 221000 | Q7: =AVERAGEIF(Tabla3[Corregimiento],Tabla7[[#This Row],[Corregimiento]],Tabla3[DISTANCIA (km)]) -> 18.542 | R7: =AVERAGEIF(Tabla3[Corregimiento],Tabla7[[#This Row],[Corregimiento]],Tabla3[Valor Tran]) -> 55250 | S7: =AVERAGEIF(Tabla8[Corregimiento],Tabla7[[#This Row],[Corregimiento]],Tabla8[Costo Total]) -> 91189.958 | T7: =AVERAGEIF(Tabla8[Corregimiento],Tabla7[[#This Row],[Corregimiento]],Tabla8[Perdida o ganancia de margen]) -> -0.074418547
A8: 45968 | B8: =COUNTIF(Tabla3[FECHA],Tabla4[[#This Row],[Fecha]]) -> 6 | C8: =SUMIF(Tabla3[FECHA],Tabla4[[#This Row],[Fecha]],Tabla3[VLR. TRANSPORTE]) -> 420000 | E8: Los bomberos | F8: =COUNTIF(Tabla3[LUGAR ENVÍO],Tabla6[[#This Row],[Nombre]]) -> 0 | G8: =SUMIF(Tabla3[LUGAR ENVÍO],Tabla6[[#This Row],[Nombre]],Tabla3[Numero de Transportes]) -> 0 | H8: =Tabla6[[#This Row],[Numero de Facturas]]/Tabla6[[#Totals],[Numero de Facturas]] -> 0 | I8: =SUMIF(Tabla3[LUGAR ENVÍO],Tabla6[[#This Row],[Nombre]],Tabla3[VLR. TRANSPORTE]) -> 0 | J8: =AVERAGEIF(Tabla3[LUGAR ENVÍO],Tabla6[[#This Row],[Nombre]],Tabla3[VLR. TRANSPORTE]) -> #DIV/0! | K8: =Tabla6[[#This Row],[Distancia total ida y vuelta]]/Tabla6[[#This Row],[Numero de Facturas]] -> #DIV/0! | L8: =SUMIF(Tabla3[LUGAR ENVÍO],Tabla6[[#This Row],[Nombre]],Tabla3[DISTANCIA (km)]) -> 0 | N8: El Palmar | O8: =COUNTIF(Tabla3[Corregimiento],Tabla7[[#This Row],[Corregimiento]]) -> 4 | P8: =SUMIF(Tabla3[Corregimiento],Tabla7[[#This Row],[Corregimiento]],Tabla3[VLR. TRANSPORTE]) -> 160000 | Q8: =AVERAGEIF(Tabla3[Corregimiento],Tabla7[[#This Row],[Corregimiento]],Tabla3[DISTANCIA (km)]) -> 4.35775 | R8: =AVERAGEIF(Tabla3[Corregimiento],Tabla7[[#This Row],[Corregimiento]],Tabla3[Valor Tran]) -> 40000 | S8: =AVERAGEIF(Tabla8[Corregimiento],Tabla7[[#This Row],[Corregimiento]],Tabla8[Costo Total]) -> 52078.104 | T8: =AVERAGEIF(Tabla8[Corregimiento],Tabla7[[#This Row],[Corregimiento]],Tabla8[Perdida o ganancia de margen]) -> -0.28020703
A9: 45969 | B9: =COUNTIF(Tabla3[FECHA],Tabla4[[#This Row],[Fecha]]) -> 7 | C9: =SUMIF(Tabla3[FECHA],Tabla4[[#This Row],[Fecha]],Tabla3[VLR. TRANSPORTE]) -> 245000 | E9: El Carmen | F9: =COUNTIF(Tabla3[LUGAR ENVÍO],Tabla6[[#This Row],[Nombre]]) -> 0 | G9: =SUMIF(Tabla3[LUGAR ENVÍO],Tabla6[[#This Row],[Nombre]],Tabla3[Numero de Transportes]) -> 0 | H9: =Tabla6[[#This Row],[Numero de Facturas]]/Tabla6[[#Totals],[Numero de Facturas]] -> 0 | I9: =SUMIF(Tabla3[LUGAR ENVÍO],Tabla6[[#This Row],[Nombre]],Tabla3[VLR. TRANSPORTE]) -> 0 | J9: =AVERAGEIF(Tabla3[LUGAR ENVÍO],Tabla6[[#This Row],[Nombre]],Tabla3[VLR. TRANSPORTE]) -> #DIV/0! | K9: =Tabla6[[#This Row],[Distancia total ida y vuelta]]/Tabla6[[#This Row],[Numero de Facturas]] -> #DIV/0! | L9: =SUMIF(Tabla3[LUGAR ENVÍO],Tabla6[[#This Row],[Nombre]],Tabla3[DISTANCIA (km)]) -> 0 | O9: =SUM(Tabla7[Total de transportes]) -> 240 | T9: =SUBTOTAL(101,Tabla7[Perdida promedio de margen]) -> -0.15335531
A10: 45970 | B10: =COUNTIF(Tabla3[FECHA],Tabla4[[#This Row],[Fecha]]) -> 1 | C10: =SUMIF(Tabla3[FECHA],Tabla4[[#This Row],[Fecha]],Tabla3[VLR. TRANSPORTE]) -> 60000 | E10: San Jose del Salado | F10: =COUNTIF(Tabla3[LUGAR ENVÍO],Tabla6[[#This Row],[Nombre]]) -> 7 | G10: =SUMIF(Tabla3[LUGAR ENVÍO],Tabla6[[#This Row],[Nombre]],Tabla3[Numero de Transportes]) -> 9 | H10: =Tabla6[[#This Row],[Numero de Facturas]]/Tabla6[[#Totals],[Numero de Facturas]] -> 0.10144928 | I10: =SUMIF(Tabla3[LUGAR ENVÍO],Tabla6[[#This Row],[Nombre]],Tabla3[VLR. TRANSPORTE]) -> 500000 | J10: =AVERAGEIF(Tabla3[LUGAR ENVÍO],Tabla6[[#This Row],[Nombre]],Tabla3[VLR. TRANSPORTE]) -> 71428.571 | K10: =Tabla6[[#This Row],[Distancia total ida y vuelta]]/Tabla6[[#This Row],[Numero de Facturas]] -> 13.07 | L10: =SUMIF(Tabla3[LUGAR ENVÍO],Tabla6[[#This Row],[Nombre]],Tabla3[DISTANCIA (km)]) -> 91.49 | O10: =COUNTIF(Tabla3[Corregimiento],Tabla7[[#This Row],[Corregimiento]]) -> 0 | P10: =SUMIF(Tabla3[Corregimiento],Tabla7[[#This Row],[Corregimiento]],Tabla3[VLR. TRANSPORTE]) -> 0 | Q10: =AVERAGEIF(Tabla3[Corregimiento],Tabla7[[#This Row],[Corregimiento]],Tabla3[DISTANCIA (km)]) -> #DIV/0! | R10: =AVERAGEIF(Tabla3[Corregimiento],Tabla7[[#This Row],[Corregimiento]],Tabla3[Valor Tran]) -> #DIV/0! | S10: =AVERAGEIF(Tabla8[Corregimiento],Tabla7[[#This Row],[Corregimiento]],Tabla8[Costo Total]) -> #DIV/0! | T10: =AVERAGEIF(Tabla8[Corregimiento],Tabla7[[#This Row],[Corregimiento]],Tabla8[Perdida o ganancia de margen]) -> #DIV/0!
A11: 45971 | B11: =COUNTIF(Tabla3[FECHA],Tabla4[[#This Row],[Fecha]]) -> 7 | C11: =SUMIF(Tabla3[FECHA],Tabla4[[#This Row],[Fecha]],Tabla3[VLR. TRANSPORTE]) -> 335000 | E11: El Bosque | F11: =COUNTIF(Tabla3[LUGAR ENVÍO],Tabla6[[#This Row],[Nombre]]) -> 0 | G11: =SUMIF(Tabla3[LUGAR ENVÍO],Tabla6[[#This Row],[Nombre]],Tabla3[Numero de Transportes]) -> 0 | H11: =Tabla6[[#This Row],[Numero de Facturas]]/Tabla6[[#Totals],[Numero de Facturas]] -> 0 | I11: =SUMIF(Tabla3[LUGAR ENVÍO],Tabla6[[#This Row],[Nombre]],Tabla3[VLR. TRANSPORTE]) -> 0 | J11: =AVERAGEIF(Tabla3[LUGAR ENVÍO],Tabla6[[#This Row],[Nombre]],Tabla3[VLR. TRANSPORTE]) -> #DIV/0! | K11: =Tabla6[[#This Row],[Distancia total ida y vuelta]]/Tabla6[[#This Row],[Numero de Facturas]] -> #DIV/0! | L11: =SUMIF(Tabla3[LUGAR ENVÍO],Tabla6[[#This Row],[Nombre]],Tabla3[DISTANCIA (km)]) -> 0
A12: 45972 | B12: =COUNTIF(Tabla3[FECHA],Tabla4[[#This Row],[Fecha]]) -> 6 | C12: =SUMIF(Tabla3[FECHA],Tabla4[[#This Row],[Fecha]],Tabla3[VLR. TRANSPORTE]) -> 295000 | E12: Parcelacion San Fernando | F12: =COUNTIF(Tabla3[LUGAR ENVÍO],Tabla6[[#This Row],[Nombre]]) -> 0 | G12: =SUMIF(Tabla3[LUGAR ENVÍO],Tabla6[[#This Row],[Nombre]],Tabla3[Numero de Transportes]) -> 0 | H12: =Tabla6[[#This Row],[Numero de Facturas]]/Tabla6[[#Totals],[Numero de Facturas]] -> 0 | I12: =SUMIF(Tabla3[LUGAR ENVÍO],Tabla6[[#This Row],[Nombre]],Tabla3[VLR. TRANSPORTE]) -> 0 | J12: =AVERAGEIF(Tabla3[LUGAR ENVÍO],Tabla6[[#This Row],[Nombre]],Tabla3[VLR. TRANSPORTE]) -> #DIV/0! | K12: =Tabla6[[#This Row],[Distancia total ida y vuelta]]/Tabla6[[#This Row],[Numero de Facturas]] -> #DIV/0! | L12: =SUMIF(Tabla3[LUGAR ENVÍO],Tabla6[[#This Row],[Nombre]],Tabla3[DISTANCIA (km)]) -> 0
A13: 45973 | B13: =COUNTIF(Tabla3[FECHA],Tabla4[[#This Row],[Fecha]]) -> 7 | C13: =SUMIF(Tabla3[FECHA],Tabla4[[#This Row],[Fecha]],Tabla3[VLR. TRANSPORTE]) -> 480000 | E13: La Zulia 2 | F13: =COUNTIF(Tabla3[LUGAR ENVÍO],Tabla6[[#This Row],[Nombre]]) -> 0 | G13: =SUMIF(Tabla3[LUGAR ENVÍO],Tabla6[[#This Row],[Nombre]],Tabla3[Numero de Transportes]) -> 0 | H13: =Tabla6[[#This Row],[Numero de Facturas]]/Tabla6[[#Totals],[Numero de Facturas]] -> 0 | I13: =SUMIF(Tabla3[LUGAR ENVÍO],Tabla6[[#This Row],[Nombre]],Tabla3[VLR. TRANSPORTE]) -> 0 | J13: =AVERAGEIF(Tabla3[LUGAR ENVÍO],Tabla6[[#This Row],[Nombre]],Tabla3[VLR. TRANSPORTE]) -> #DIV/0! | K13: =Tabla6[[#This Row],[Distancia total ida y vuelta]]/Tabla6[[#This Row],[Numero de Facturas]] -> #DIV/0! | L13: =SUMIF(Tabla3[LUGAR ENVÍO],Tabla6[[#This Row],[Nombre]],Tabla3[DISTANCIA (km)]) -> 0
A14: 45974 | B14: =COUNTIF(Tabla3[FECHA],Tabla4[[#This Row],[Fecha]]) -> 14 | C14: =SUMIF(Tabla3[FECHA],Tabla4[[#This Row],[Fecha]],Tabla3[VLR. TRANSPORTE]) -> 490000 | E14: Chipre | F14: =COUNTIF(Tabla3[LUGAR ENVÍO],Tabla6[[#This Row],[Nombre]]) -> 3 | G14: =SUMIF(Tabla3[LUGAR ENVÍO],Tabla6[[#This Row],[Nombre]],Tabla3[Numero de Transportes]) -> 4 | H14: =Tabla6[[#This Row],[Numero de Facturas]]/Tabla6[[#Totals],[Numero de Facturas]] -> 0.043478261 | I14: =SUMIF(Tabla3[LUGAR ENVÍO],Tabla6[[#This Row],[Nombre]],Tabla3[VLR. TRANSPORTE]) -> 165000 | J14: =AVERAGEIF(Tabla3[LUGAR ENVÍO],Tabla6[[#This Row],[Nombre]],Tabla3[VLR. TRANSPORTE]) -> 55000 | K14: =Tabla6[[#This Row],[Distancia total ida y vuelta]]/Tabla6[[#This Row],[Numero de Facturas]] -> 4.781 | L14: =SUMIF(Tabla3[LUGAR ENVÍO],Tabla6[[#This Row],[Nombre]],Tabla3[DISTANCIA (km)]) -> 14.343
A15: 45975 | B15: =COUNTIF(Tabla3[FECHA],Tabla4[[#This Row],[Fecha]]) -> 4 | C15: =SUMIF(Tabla3[FECHA],Tabla4[[#This Row],[Fecha]],Tabla3[VLR. TRANSPORTE]) -> 165000 | E15: Monteredondo | F15: =COUNTIF(Tabla3[LUGAR ENVÍO],Tabla6[[#This Row],[Nombre]]) -> 5 | G15: =SUMIF(Tabla3[LUGAR ENVÍO],Tabla6[[#This Row],[Nombre]],Tabla3[Numero de Transportes]) -> 6 | H15: =Tabla6[[#This Row],[Numero de Facturas]]/Tabla6[[#Totals],[Numero de Facturas]] -> 0.072463768 | I15: =SUMIF(Tabla3[LUGAR ENVÍO],Tabla6[[#This Row],[Nombre]],Tabla3[VLR. TRANSPORTE]) -> 150000 | J15: =AVERAGEIF(Tabla3[LUGAR ENVÍO],Tabla6[[#This Row],[Nombre]],Tabla3[VLR. TRANSPORTE]) -> 30000 | K15: =Tabla6[[#This Row],[Distancia total ida y vuelta]]/Tabla6[[#This Row],[Numero de Facturas]] -> 0.428 | L15: =SUMIF(Tabla3[LUGAR ENVÍO],Tabla6[[#This Row],[Nombre]],Tabla3[DISTANCIA (km)]) -> 2.14
A16: 45976 | B16: =COUNTIF(Tabla3[FECHA],Tabla4[[#This Row],[Fecha]]) -> 7 | C16: =SUMIF(Tabla3[FECHA],Tabla4[[#This Row],[Fecha]],Tabla3[VLR. TRANSPORTE]) -> 370000 | E16: Agua Sucia | F16: =COUNTIF(Tabla3[LUGAR ENVÍO],Tabla6[[#This Row],[Nombre]]) -> 0 | G16: =SUMIF(Tabla3[LUGAR ENVÍO],Tabla6[[#This Row],[Nombre]],Tabla3[Numero de Transportes]) -> 0 | H16: =Tabla6[[#This Row],[Numero de Facturas]]/Tabla6[[#Totals],[Numero de Facturas]] -> 0 | I16: =SUMIF(Tabla3[LUGAR ENVÍO],Tabla6[[#This Row],[Nombre]],Tabla3[VLR. TRANSPORTE]) -> 0 | J16: =AVERAGEIF(Tabla3[LUGAR ENVÍO],Tabla6[[#This Row],[Nombre]],Tabla3[VLR. TRANSPORTE]) -> #DIV/0! | K16: =Tabla6[[#This Row],[Distancia total ida y vuelta]]/Tabla6[[#This Row],[Numero de Facturas]] -> #DIV/0! | L16: =SUMIF(Tabla3[LUGAR ENVÍO],Tabla6[[#This Row],[Nombre]],Tabla3[DISTANCIA (km)]) -> 0
A17: 45977 | B17: =COUNTIF(Tabla3[FECHA],Tabla4[[#This Row],[Fecha]]) -> 1 | C17: =SUMIF(Tabla3[FECHA],Tabla4[[#This Row],[Fecha]],Tabla3[VLR. TRANSPORTE]) -> 25000 | E17: Tocota | F17: =COUNTIF(Tabla3[LUGAR ENVÍO],Tabla6[[#This Row],[Nombre]]) -> 5 | G17: =SUMIF(Tabla3[LUGAR ENVÍO],Tabla6[[#This Row],[Nombre]],Tabla3[Numero de Transportes]) -> 6 | H17: =Tabla6[[#This Row],[Numero de Facturas]]/Tabla6[[#Totals],[Numero de Facturas]] -> 0.072463768 | I17: =SUMIF(Tabla3[LUGAR ENVÍO],Tabla6[[#This Row],[Nombre]],Tabla3[VLR. TRANSPORTE]) -> 290000 | J17: =AVERAGEIF(Tabla3[LUGAR ENVÍO],Tabla6[[#This Row],[Nombre]],Tabla3[VLR. TRANSPORTE]) -> 58000 | K17: =Tabla6[[#This Row],[Distancia total ida y vuelta]]/Tabla6[[#This Row],[Numero de Facturas]] -> 9.438 | L17: =SUMIF(Tabla3[LUGAR ENVÍO],Tabla6[[#This Row],[Nombre]],Tabla3[DISTANCIA (km)]) -> 47.19
A18: 45978 | B18: =COUNTIF(Tabla3[FECHA],Tabla4[[#This Row],[Fecha]]) -> 7 | C18: =SUMIF(Tabla3[FECHA],Tabla4[[#This Row],[Fecha]],Tabla3[VLR. TRANSPORTE]) -> 550000 | E18: Altos tortolas | F18: =COUNTIF(Tabla3[LUGAR ENVÍO],Tabla6[[#This Row],[Nombre]]) -> 0 | G18: =SUMIF(Tabla3[LUGAR ENVÍO],Tabla6[[#This Row],[Nombre]],Tabla3[Numero de Transportes]) -> 0 | H18: =Tabla6[[#This Row],[Numero de Facturas]]/Tabla6[[#Totals],[Numero de Facturas]] -> 0 | I18: =SUMIF(Tabla3[LUGAR ENVÍO],Tabla6[[#This Row],[Nombre]],Tabla3[VLR. TRANSPORTE]) -> 0 | J18: =AVERAGEIF(Tabla3[LUGAR ENVÍO],Tabla6[[#This Row],[Nombre]],Tabla3[VLR. TRANSPORTE]) -> #DIV/0! | K18: =Tabla6[[#This Row],[Distancia total ida y vuelta]]/Tabla6[[#This Row],[Numero de Facturas]] -> #DIV/0! | L18: =SUMIF(Tabla3[LUGAR ENVÍO],Tabla6[[#This Row],[Nombre]],Tabla3[DISTANCIA (km)]) -> 0
A19: 45979 | B19: =COUNTIF(Tabla3[FECHA],Tabla4[[#This Row],[Fecha]]) -> 6 | C19: =SUMIF(Tabla3[FECHA],Tabla4[[#This Row],[Fecha]],Tabla3[VLR. TRANSPORTE]) -> 535000 | E19: El Carmelo | F19: =COUNTIF(Tabla3[LUGAR ENVÍO],Tabla6[[#This Row],[Nombre]]) -> 0 | G19: =SUMIF(Tabla3[LUGAR ENVÍO],Tabla6[[#This Row],[Nombre]],Tabla3[Numero de Transportes]) -> 0 | H19: =Tabla6[[#This Row],[Numero de Facturas]]/Tabla6[[#Totals],[Numero de Facturas]] -> 0 | I19: =SUMIF(Tabla3[LUGAR ENVÍO],Tabla6[[#This Row],[Nombre]],Tabla3[VLR. TRANSPORTE]) -> 0 | J19: =AVERAGEIF(Tabla3[LUGAR ENVÍO],Tabla6[[#This Row],[Nombre]],Tabla3[VLR. TRANSPORTE]) -> #DIV/0! | K19: =Tabla6[[#This Row],[Distancia total ida y vuelta]]/Tabla6[[#This Row],[Numero de Facturas]] -> #DIV/0! | L19: =SUMIF(Tabla3[LUGAR ENVÍO],Tabla6[[#This Row],[Nombre]],Tabla3[DISTANCIA (km)]) -> 0
A20: 45980 | B20: =COUNTIF(Tabla3[FECHA],Tabla4[[#This Row],[Fecha]]) -> 4 | C20: =SUMIF(Tabla3[FECHA],Tabla4[[#This Row],[Fecha]],Tabla3[VLR. TRANSPORTE]) -> 160000 | E20: KM 40 | F20: =COUNTIF(Tabla3[LUGAR ENVÍO],Tabla6[[#This Row],[Nombre]]) -> 0 | G20: =SUMIF(Tabla3[LUGAR ENVÍO],Tabla6[[#This Row],[Nombre]],Tabla3[Numero de Transportes]) -> 0 | H20: =Tabla6[[#This Row],[Numero de Facturas]]/Tabla6[[#Totals],[Numero de Facturas]] -> 0 | I20: =SUMIF(Tabla3[LUGAR ENVÍO],Tabla6[[#This Row],[Nombre]],Tabla3[VLR. TRANSPORTE]) -> 0 | J20: =AVERAGEIF(Tabla3[LUGAR ENVÍO],Tabla6[[#This Row],[Nombre]],Tabla3[VLR. TRANSPORTE]) -> #DIV/0! | K20: =Tabla6[[#This Row],[Distancia total ida y vuelta]]/Tabla6[[#This Row],[Numero de Facturas]] -> #DIV/0! | L20: =SUMIF(Tabla3[LUGAR ENVÍO],Tabla6[[#This Row],[Nombre]],Tabla3[DISTANCIA (km)]) -> 0
A21: 45981 | B21: =COUNTIF(Tabla3[FECHA],Tabla4[[#This Row],[Fecha]]) -> 13 | C21: =SUMIF(Tabla3[FECHA],Tabla4[[#This Row],[Fecha]],Tabla3[VLR. TRANSPORTE]) -> 625000 | E21: Parcelación Monte Rico | F21: =COUNTIF(Tabla3[LUGAR ENVÍO],Tabla6[[#This Row],[Nombre]]) -> 0 | G21: =SUMIF(Tabla3[LUGAR ENVÍO],Tabla6[[#This Row],[Nombre]],Tabla3[Numero de Transportes]) -> 0 | H21: =Tabla6[[#This Row],[Numero de Facturas]]/Tabla6[[#Totals],[Numero de Facturas]] -> 0 | I21: =SUMIF(Tabla3[LUGAR ENVÍO],Tabla6[[#This Row],[Nombre]],Tabla3[VLR. TRANSPORTE]) -> 0 | J21: =AVERAGEIF(Tabla3[LUGAR ENVÍO],Tabla6[[#This Row],[Nombre]],Tabla3[VLR. TRANSPORTE]) -> #DIV/0! | K21: =Tabla6[[#This Row],[Distancia total ida y vuelta]]/Tabla6[[#This Row],[Numero de Facturas]] -> #DIV/0! | L21: =SUMIF(Tabla3[LUGAR ENVÍO],Tabla6[[#This Row],[Nombre]],Tabla3[DISTANCIA (km)]) -> 0
A22: 45982 | B22: =COUNTIF(Tabla3[FECHA],Tabla4[[#This Row],[Fecha]]) -> 11 | C22: =SUMIF(Tabla3[FECHA],Tabla4[[#This Row],[Fecha]],Tabla3[VLR. TRANSPORTE]) -> 571000 | E22: El Diviso | F22: =COUNTIF(Tabla3[LUGAR ENVÍO],Tabla6[[#This Row],[Nombre]]) -> 0 | G22: =SUMIF(Tabla3[LUGAR ENVÍO],Tabla6[[#This Row],[Nombre]],Tabla3[Numero de Transportes]) -> 0 | H22: =Tabla6[[#This Row],[Numero de Facturas]]/Tabla6[[#Totals],[Numero de Facturas]] -> 0 | I22: =SUMIF(Tabla3[LUGAR ENVÍO],Tabla6[[#This Row],[Nombre]],Tabla3[VLR. TRANSPORTE]) -> 0 | J22: =AVERAGEIF(Tabla3[LUGAR ENVÍO],Tabla6[[#This Row],[Nombre]],Tabla3[VLR. TRANSPORTE]) -> #DIV/0! | K22: =Tabla6[[#This Row],[Distancia total ida y vuelta]]/Tabla6[[#This Row],[Numero de Facturas]] -> #DIV/0! | L22: =SUMIF(Tabla3[LUGAR ENVÍO],Tabla6[[#This Row],[Nombre]],Tabla3[DISTANCIA (km)]) -> 0
... A31: 45991 | B31: =COUNTIF(Tabla3[FECHA],Tabla4[[#This Row],[Fecha]]) -> 4 | C31: =SUMIF(Tabla3[FECHA],Tabla4[[#This Row],[Fecha]],Tabla3[VLR. TRANSPORTE]) -> 160000 | E31: Tierras blancas | F31: =COUNTIF(Tabla3[LUGAR ENVÍO],Tabla6[[#This Row],[Nombre]]) -> 0 | G31: =SUMIF(Tabla3[LUGAR ENVÍO],Tabla6[[#This Row],[Nombre]],Tabla3[Numero de Transportes]) -> 0 | H31: =Tabla6[[#This Row],[Numero de Facturas]]/Tabla6[[#Totals],[Numero de Facturas]] -> 0 | I31: =SUMIF(Tabla3[LUGAR ENVÍO],Tabla6[[#This Row],[Nombre]],Tabla3[VLR. TRANSPORTE]) -> 0 | J31: =AVERAGEIF(Tabla3[LUGAR ENVÍO],Tabla6[[#This Row],[Nombre]],Tabla3[VLR. TRANSPORTE]) -> #DIV/0! | K31: =Tabla6[[#This Row],[Distancia total ida y vuelta]]/Tabla6[[#This Row],[Numero de Facturas]] -> #DIV/0! | L31: =SUMIF(Tabla3[LUGAR ENVÍO],Tabla6[[#This Row],[Nombre]],Tabla3[DISTANCIA (km)]) -> 0
B32: =SUBTOTAL(109,Tabla4[Total de envios]) -> 216 | C32: =SUBTOTAL(109,Tabla4[Valor]) -> 11466000 | E32: Pa la chingada | F32: =COUNTIF(Tabla3[LUGAR ENVÍO],Tabla6[[#This Row],[Nombre]]) -> 0 | G32: =SUMIF(Tabla3[LUGAR ENVÍO],Tabla6[[#This Row],[Nombre]],Tabla3[Numero de Transportes]) -> 0 | H32: =Tabla6[[#This Row],[Numero de Facturas]]/Tabla6[[#Totals],[Numero de Facturas]] -> 0 | I32: =SUMIF(Tabla3[LUGAR ENVÍO],Tabla6[[#This Row],[Nombre]],Tabla3[VLR. TRANSPORTE]) -> 0 | J32: =AVERAGEIF(Tabla3[LUGAR ENVÍO],Tabla6[[#This Row],[Nombre]],Tabla3[VLR. TRANSPORTE]) -> #DIV/0! | K32: =Tabla6[[#This Row],[Distancia total ida y vuelta]]/Tabla6[[#This Row],[Numero de Facturas]] -> #DIV/0! | L32: =SUMIF(Tabla3[LUGAR ENVÍO],Tabla6[[#This Row],[Nombre]],Tabla3[DISTANCIA (km)]) -> 0
E33: Cositas ricas | F33: =COUNTIF(Tabla3[LUGAR ENVÍO],Tabla6[[#This Row],[Nombre]]) -> 0 | G33: =SUMIF(Tabla3[LUGAR ENVÍO],Tabla6[[#This Row],[Nombre]],Tabla3[Numero de Transportes]) -> 0 | H33: =Tabla6[[#This Row],[Numero de Facturas]]/Tabla6[[#Totals],[Numero de Facturas]] -> 0 | I33: =SUMIF(Tabla3[LUGAR ENVÍO],Tabla6[[#This Row],[Nombre]],Tabla3[VLR. TRANSPORTE]) -> 0 | J33: =AVERAGEIF(Tabla3[LUGAR ENVÍO],Tabla6[[#This Row],[Nombre]],Tabla3[VLR. TRANSPORTE]) -> #DIV/0! | K33: =Tabla6[[#This Row],[Distancia total ida y vuelta]]/Tabla6[[#This Row],[Numero de Facturas]] -> #DIV/0! | L33: =SUMIF(Tabla3[LUGAR ENVÍO],Tabla6[[#This Row],[Nombre]],Tabla3[DISTANCIA (km)]) -> 0
E34: KM 25 | F34: =COUNTIF(Tabla3[LUGAR ENVÍO],Tabla6[[#This Row],[Nombre]]) -> 2 | G34: =SUMIF(Tabla3[LUGAR ENVÍO],Tabla6[[#This Row],[Nombre]],Tabla3[Numero de Transportes]) -> 2 | H34: =Tabla6[[#This Row],[Numero de Facturas]]/Tabla6[[#Totals],[Numero de Facturas]] -> 0.028985507 | I34: =SUMIF(Tabla3[LUGAR ENVÍO],Tabla6[[#This Row],[Nombre]],Tabla3[VLR. TRANSPORTE]) -> 110000 | J34: =AVERAGEIF(Tabla3[LUGAR ENVÍO],Tabla6[[#This Row],[Nombre]],Tabla3[VLR. TRANSPORTE]) -> 55000 | K34: =Tabla6[[#This Row],[Distancia total ida y vuelta]]/Tabla6[[#This Row],[Numero de Facturas]] -> 6.46658 | L34: =SUMIF(Tabla3[LUGAR ENVÍO],Tabla6[[#This Row],[Nombre]],Tabla3[DISTANCIA (km)]) -> 12.93316
E35: El Queremal | F35: =COUNTIF(Tabla3[LUGAR ENVÍO],Tabla6[[#This Row],[Nombre]]) -> 4 | G35: =SUMIF(Tabla3[LUGAR ENVÍO],Tabla6[[#This Row],[Nombre]],Tabla3[Numero de Transportes]) -> 4 | H35: =Tabla6[[#This Row],[Numero de Facturas]]/Tabla6[[#Totals],[Numero de Facturas]] -> 0.057971014 | I35: =SUMIF(Tabla3[LUGAR ENVÍO],Tabla6[[#This Row],[Nombre]],Tabla3[VLR. TRANSPORTE]) -> 221000 | J35: =AVERAGEIF(Tabla3[LUGAR ENVÍO],Tabla6[[#This Row],[Nombre]],Tabla3[VLR. TRANSPORTE]) -> 55250 | K35: =Tabla6[[#This Row],[Distancia total ida y vuelta]]/Tabla6[[#This Row],[Numero de Facturas]] -> 18.542 | L35: =SUMIF(Tabla3[LUGAR ENVÍO],Tabla6[[#This Row],[Nombre]],Tabla3[DISTANCIA (km)]) -> 74.168
F36: =SUBTOTAL(109,Tabla6[Numero de Facturas]) -> 69 | G36: =SUBTOTAL(109,Tabla6[Numero de envios]) -> 81 | I36: =SUBTOTAL(109,Tabla6[Valor envio]) -> 4271000 | K36: =SUBTOTAL(101,Tabla6[Distancia (KM)]) -> #DIV/0! | L36: =SUBTOTAL(101,Tabla6[Distancia total ida y vuelta]) -> 12.522564
E38: Nombre | F38: Numero de Facturas | G38: Numero de envios | H38: % | I38: Valor envio | J38: Promedio | K38: Distancia (KM)
E39: Parcelación Pirineos | F39: 8 | G39: 8 | H39: 0.0777 | I39: 350000 | J39: 43750 | K39: 2.66
E40: El Coscorron | F40: 7 | G40: 9 | H40: 0.068 | I40: 560000 | J40: 80000 | K40: 2.65
E41: Tortolas | F41: 7 | G41: 8 | H41: 0.068 | I41: 580000 | J41: 82857.14 | K41: 4.935
E42: KM 34 | F42: 7 | G42: 9 | H42: 0.068 | I42: 310000 | J42: 44285.71 | K42: 3.699
E43: Altos del Carmen | F43: 9 | G43: 9 | H43: 0.0874 | I43: 460000 | J43: 51111.11 | K43: 3.643
E44: Parcelacion la Cristalina | F44: 5 | G44: 5 | H44: 0.0485 | I44: 236000 | J44: 47200 | K44: 2.71
E45: Los bomberos | F45: 4 | G45: 5 | H45: 0.0388 | I45: 145000 | J45: 36250 | K45: 2.092
E46: El Carmen | F46: 4 | G46: 4 | H46: 0.0388 | I46: 170000 | J46: 42500 | K46: 4.201
E47: San Jose del Salado | F47: 6 | G47: 7 | H47: 0.0583 | I47: 380000 | J47: 63333.33 | K47: 8.714
E48: El Bosque | F48: 3 | G48: 3 | H48: 0.0291 | I48: 180000 | J48: 60000 | K48: 4.443
E49: Parcelacion San Fernando | F49: 3 | G49: 3 | H49: 0.0291 | I49: 160000 | J49: 53333.33 | K49: 7.6
E50: La Zulia 2 | F50: 3 | G50: 3 | H50: 0.0291 | I50: 85000 | J50: 28333.33 | K50: 1.665
... E72: El Queremal | F72: 1 | G72: 1 | H72: 0.0097 | I72: 80000 | J72: 80000 | K72: 18.54

Sheet Base de datos
A1: N° FACTURA | B1: FECHA | C1: TIPO FACTURA | D1: CLIENTE | E1: LUGAR ENVÍO | F1: ID | G1: Corregimiento | H1: DISTANCIA (km) | I1: Valor del transporte/KM | J1: PESO EST. (kg) | K1: Numero de Transportes | L1: VLR. TRANSPORTE | M1: Valor Tran | N1: VLR. TOTAL FACT. | O1: VLR. PRODUCTOS | P1: Local/Tercero (1/0) | Q1: FORMA PAGO
A2: 58563 | B2: 45978 | C2: sai | D2: Elizabeth Perlaza | E2: Villahermosa | F2: 6 | G2: =_xlfn.XLOOKUP(Tabla3[[#This Row],[ID]],Tabla2[ID],Tabla2[Corregimiento],"NA") -> El Limonar | H2: =_xlfn.XLOOKUP(Tabla3[[#This Row],[LUGAR ENVÍO]],Tabla9[[Nombre ]],Tabla9[Distancia],"NA") -> 6.788 | I2: =Tabla3[[#This Row],[Valor Tran]]/(Tabla3[[#This Row],[DISTANCIA (km)]]*2) -> 7365.9399 | K2: 2 | L2: 200000 | M2: =Tabla3[[#This Row],[VLR. TRANSPORTE]]/Tabla3[[#This Row],[Numero de Transportes]] -> 100000 | N2: 1044500 | O2: =Tabla3[[#This Row],[VLR. TOTAL FACT.]]-Tabla3[[#This Row],[VLR. TRANSPORTE]] -> 844500 | P2: 1 | Q2: Multiples
A3: 58646 | B3: 45983 | C3: sai | D3: jhon alex | E3: Villahermosa | F3: 6 | G3: =_xlfn.XLOOKUP(Tabla3[[#This Row],[ID]],Tabla2[ID],Tabla2[Corregimiento],"NA") -> El Limonar | H3: =_xlfn.XLOOKUP(Tabla3[[#This Row],[LUGAR ENVÍO]],Tabla9[[Nombre ]],Tabla9[Distancia],"NA") -> 6.788 | I3: =Tabla3[[#This Row],[Valor Tran]]/(Tabla3[[#This Row],[DISTANCIA (km)]]*2) -> 3682.9699 | K3: 1 | L3: 50000 | M3: =Tabla3[[#This Row],[VLR. TRANSPORTE]]/Tabla3[[#This Row],[Numero de Transportes]] -> 50000 | N3: 4067000 | O3: =Tabla3[[#This Row],[VLR. TOTAL FACT.]]-Tabla3[[#This Row],[VLR. TRANSPORTE]] -> 4017000 | P3: 1 | Q3: efectivo
A4: 47037 | B4: 45969 | C4: sai | D4: NA | E4: Villa saman | F4: 2 | G4: =_xlfn.XLOOKUP(Tabla3[[#This Row],[ID]],Tabla2[ID],Tabla2[Corregimiento],"NA") -> Borrero Ayerbe | H4: =_xlfn.XLOOKUP(Tabla3[[#This Row],[LUGAR ENVÍO]],Tabla9[[Nombre ]],Tabla9[Distancia],"NA") -> 2.059 | I4: =Tabla3[[#This Row],[Valor Tran]]/(Tabla3[[#This Row],[DISTANCIA (km)]]*2) -> 6070.9082 | K4: 1 | L4: 25000 | M4: =Tabla3[[#This Row],[VLR. TRANSPORTE]]/Tabla3[[#This Row],[Numero de Transportes]] -> 25000 | N4: 175000 | O4: =Tabla3[[#This Row],[VLR. TOTAL FACT.]]-Tabla3[[#This Row],[VLR. TRANSPORTE]] -> 150000 | P4: 0 | Q4: transferencia
A5: 58690 | B5: 45993 | C5: sai | D5: Carlos Torres | E5: Villa saman | F5: 2 | G5: =_xlfn.XLOOKUP(Tabla3[[#This Row],[ID]],Tabla2[ID],Tabla2[Corregimiento],"NA") -> Borrero Ayerbe | H5: =_xlfn.XLOOKUP(Tabla3[[#This Row],[LUGAR ENVÍO]],Tabla9[[Nombre ]],Tabla9[Distancia],"NA") -> 2.059 | I5: =Tabla3[[#This Row],[Valor Tran]]/(Tabla3[[#This Row],[DISTANCIA (km)]]*2) -> 4856.7266 | K5: 2 | L5: 40000 | M5: =Tabla3[[#This Row],[VLR. TRANSPORTE]]/Tabla3[[#This Row],[Numero de Transportes]] -> 20000 | N5: 387000 | O5: =Tabla3[[#This Row],[VLR. TOTAL FACT.]]-Tabla3[[#This Row],[VLR. TRANSPORTE]] -> 347000 | P5: 1 | Q5: efectivo
A6: 58823 | B6: 46000 | C6: manual | D6: miriam gomez | E6: Villa saman | F6: 2 | G6: =_xlfn.XLOOKUP(Tabla3[[#This Row],[ID]],Tabla2[ID],Tabla2[Corregimiento],"NA") -> Borrero Ayerbe | H6: =_xlfn.XLOOKUP(Tabla3[[#This Row],[LUGAR ENVÍO]],Tabla9[[Nombre ]],Tabla9[Distancia],"NA") -> 2.059 | I6: =Tabla3[[#This Row],[Valor Tran]]/(Tabla3[[#This Row],[DISTANCIA (km)]]*2) -> 3642.5449 | K6: 1 | L6: 15000 | M6: =Tabla3[[#This Row],[VLR. TRANSPORTE]]/Tabla3[[#This Row],[Numero de Transportes]] -> 15000 | N6: 2954000 | O6: =Tabla3[[#This Row],[VLR. TOTAL FACT.]]-Tabla3[[#This Row],[VLR. TRANSPORTE]] -> 2939000 | P6: 1 | Q6: efectivo
A7: 46418 | B7: 45962 | C7: sai | D7: katherine | E7: Villa emilia | F7: 4 | G7: =_xlfn.XLOOKUP(Tabla3[[#This Row],[ID]],Tabla2[ID],Tabla2[Corregimiento],"NA") -> El Carmen | H7: =_xlfn.XLOOKUP(Tabla3[[#This Row],[LUGAR ENVÍO]],Tabla9[[Nombre ]],Tabla9[Distancia],"NA") -> 3.449 | I7: =Tabla3[[#This Row],[Valor Tran]]/(Tabla3[[#This Row],[DISTANCIA (km)]]*2) -> 5798.7823 | K7: 1 | L7: 40000 | M7: =Tabla3[[#This Row],[VLR. TRANSPORTE]]/Tabla3[[#This Row],[Numero de Transportes]] -> 40000 | N7: 233000 | O7: =Tabla3[[#This Row],[VLR. TOTAL FACT.]]-Tabla3[[#This Row],[VLR. TRANSPORTE]] -> 193000 | P7: 0 | Q7: transferencia
A8: 48240 | B8: 2025-11-20 | C8: sai | D8: Amparo Rodriguez | E8: villa del toro | F8: 4 | G8: =_xlfn.XLOOKUP(Tabla3[[#This Row],[ID]],Tabla2[ID],Tabla2[Corregimiento],"NA") -> El Carmen | H8: =_xlfn.XLOOKUP(Tabla3[[#This Row],[LUGAR ENVÍO]],Tabla9[[Nombre ]],Tabla9[Distancia],"NA") -> 2.279762 | I8: =Tabla3[[#This Row],[Valor Tran]]/(Tabla3[[#This Row],[DISTANCIA (km)]]*2) -> 8772.8456 | K8: 1 | L8: 40000 | M8: 40000 | N8: 410500 | O8: =Tabla3[[#This Row],[VLR. TOTAL FACT.]]-Tabla3[[#This Row],[VLR. TRANSPORTE]] -> 370500 | P8: 1 | Q8: tarjeta
A9: 48122 | B9: 2025-11-12 | C9: sai | D9: Oscar Narvaez | E9: villa del toro | F9: 4 | G9: =_xlfn.XLOOKUP(Tabla3[[#This Row],[ID]],Tabla2[ID],Tabla2[Corregimiento],"NA") -> El Carmen | H9: =_xlfn.XLOOKUP(Tabla3[[#This Row],[LUGAR ENVÍO]],Tabla9[[Nombre ]],Tabla9[Distancia],"NA") -> 2.279762 | I9: =Tabla3[[#This Row],[Valor Tran]]/(Tabla3[[#This Row],[DISTANCIA (km)]]*2) -> 8772.8456 | K9: 1 | L9: 40000 | M9: 40000 | N9: 412700 | O9: =Tabla3[[#This Row],[VLR. TOTAL FACT.]]-Tabla3[[#This Row],[VLR. TRANSPORTE]] -> 372700 | P9: 1 | Q9: transferencia
A10: 55590 | B10: 2025-11-13 | C10: sai | D10: Olga Patricia | E10: villa del toro | F10: 4 | G10: =_xlfn.XLOOKUP(Tabla3[[#This Row],[ID]],Tabla2[ID],Tabla2[Corregimiento],"NA") -> El Carmen | H10: =_xlfn.XLOOKUP(Tabla3[[#This Row],[LUGAR ENVÍO]],Tabla9[[Nombre ]],Tabla9[Distancia],"NA") -> 2.279762 | I10: =Tabla3[[#This Row],[Valor Tran]]/(Tabla3[[#This Row],[DISTANCIA (km)]]*2) -> 8772.8456 | K10: 1 | L10: 40000 | M10: 40000 | N10: 437200 | O10: =Tabla3[[#This Row],[VLR. TOTAL FACT.]]-Tabla3[[#This Row],[VLR. TRANSPORTE]] -> 397200 | P10: 1 | Q10: efectivo
A11: 49737 | B11: 2025-11-26 | C11: sai | D11: Tania Duque | E11: villa del toro | F11: 4 | G11: =_xlfn.XLOOKUP(Tabla3[[#This Row],[ID]],Tabla2[ID],Tabla2[Corregimiento],"NA") -> El Carmen | H11: =_xlfn.XLOOKUP(Tabla3[[#This Row],[LUGAR ENVÍO]],Tabla9[[Nombre ]],Tabla9[Distancia],"NA") -> 2.279762 | I11: =Tabla3[[#This Row],[Valor Tran]]/(Tabla3[[#This Row],[DISTANCIA (km)]]*2) -> 9869.4513 | K11: 1 | L11: 45000 | M11: 45000 | N11: 443600 | O11: =Tabla3[[#This Row],[VLR. TOTAL FACT.]]-Tabla3[[#This Row],[VLR. TRANSPORTE]] -> 398600 | P11: 1 | Q11: tarjeta
A12: 47087 | B12: 45966 | C12: sai | D12: isabel castaño | E12: villa del toro | F12: 4 | G12: =_xlfn.XLOOKUP(Tabla3[[#This Row],[ID]],Tabla2[ID],Tabla2[Corregimiento],"NA") -> El Carmen | H12: =_xlfn.XLOOKUP(Tabla3[[#This Row],[LUGAR ENVÍO]],Tabla9[[Nombre ]],Tabla9[Distancia],"NA") -> 2.279762 | I12: =Tabla3[[#This Row],[Valor Tran]]/(Tabla3[[#This Row],[DISTANCIA (km)]]*2) -> 8772.8456 | K12: 1 | L12: 40000 | M12: =Tabla3[[#This Row],[VLR. TRANSPORTE]]/Tabla3[[#This Row],[Numero de Transportes]] -> 40000 | N12: 450100 | O12: =Tabla3[[#This Row],[VLR. TOTAL FACT.]]-Tabla3[[#This Row],[VLR. TRANSPORTE]] -> 410100 | P12: 1 | Q12: tarjeta
A13: 34670 | B13: 2025-11-11 | C13: manual | D13: Esperanza Ortega | E13: villa del toro | F13: 4 | G13: =_xlfn.XLOOKUP(Tabla3[[#This Row],[ID]],Tabla2[ID],Tabla2[Corregimiento],"NA") -> El Carmen | H13: =_xlfn.XLOOKUP(Tabla3[[#This Row],[LUGAR ENVÍO]],Tabla9[[Nombre ]],Tabla9[Distancia],"NA") -> 2.279762 | I13: =Tabla3[[#This Row],[Valor Tran]]/(Tabla3[[#This Row],[DISTANCIA (km)]]*2) -> 8772.8456 | K13: 1 | L13: 40000 | M13: 40000 | N13: 479900 | O13: =Tabla3[[#This Row],[VLR. TOTAL FACT.]]-Tabla3[[#This Row],[VLR. TRANSPORTE]] -> 439900 | P13: 1 | Q13: efectivo
A14: 30518 | B14: 45974 | C14: manual | D14: martha rosero | E14: Tortolas | F14: 4 | G14: =_xlfn.XLOOKUP(Tabla3[[#This Row],[ID]],Tabla2[ID],Tabla2[Corregimiento],"NA") -> El Carmen | H14: =_xlfn.XLOOKUP(Tabla3[[#This Row],[LUGAR ENVÍO]],Tabla9[[Nombre ]],Tabla9[Distancia],"NA") -> 5.757 | I14: =Tabla3[[#This Row],[Valor Tran]]/(Tabla3[[#This Row],[DISTANCIA (km)]]*2) -> 3474.0316 | K14: 1 | L14: 40000 | M14: =Tabla3[[#This Row],[VLR. TRANSPORTE]]/Tabla3[[#This Row],[Numero de Transportes]] -> 40000 | N14: 192000 | O14: =Tabla3[[#This Row],[VLR. TOTAL FACT.]]-Tabla3[[#This Row],[VLR. TRANSPORTE]] -> 152000 | P14: 0 | Q14: efectivo
A15: 58924 | B15: 45980 | C15: sai | D15: Martha Rosero | E15: Tortolas | F15: 4 | G15: =_xlfn.XLOOKUP(Tabla3[[#This Row],[ID]],Tabla2[ID],Tabla2[Corregimiento],"NA") -> El Carmen | H15: =_xlfn.XLOOKUP(Tabla3[[#This Row],[LUGAR ENVÍO]],Tabla9[[Nombre ]],Tabla9[Distancia],"NA") -> 5.757 | I15: =Tabla3[[#This Row],[Valor Tran]]/(Tabla3[[#This Row],[DISTANCIA (km)]]*2) -> 4342.5395 | K15: 1 | L15: 50000 | M15: =Tabla3[[#This Row],[VLR. TRANSPORTE]]/Tabla3[[#This Row],[Numero de Transportes]] -> 50000 | N15: 242000 | O15: =Tabla3[[#This Row],[VLR. TOTAL FACT.]]-Tabla3[[#This Row],[VLR. TRANSPORTE]] -> 192000 | P15: 0 | Q15: efectivo
A16: 48280 | B16: 45982 | C16: sai | D16: julio daza | E16: Tortolas | F16: 4 | G16: =_xlfn.XLOOKUP(Tabla3[[#This Row],[ID]],Tabla2[ID],Tabla2[Corregimiento],"NA") -> El Carmen | H16: =_xlfn.XLOOKUP(Tabla3[[#This Row],[LUGAR ENVÍO]],Tabla9[[Nombre ]],Tabla9[Distancia],"NA") -> 5.757 | I16: =Tabla3[[#This Row],[Valor Tran]]/(Tabla3[[#This Row],[DISTANCIA (km)]]*2) -> 2605.5237 | K16: 1 | L16: 30000 | M16: =Tabla3[[#This Row],[VLR. TRANSPORTE]]/Tabla3[[#This Row],[Numero de Transportes]] -> 30000 | N16: 575700 | O16: =Tabla3[[#This Row],[VLR. TOTAL FACT.]]-Tabla3[[#This Row],[VLR. TRANSPORTE]] -> 545700 | P16: 0 | Q16: transferencia
A17: 58571 | B17: 45989 | C17: sai | D17: Julio Daza | E17: Tortolas | F17: 4 | G17: =_xlfn.XLOOKUP(Tabla3[[#This Row],[ID]],Tabla2[ID],Tabla2[Corregimiento],"NA") -> El Carmen | H17: =_xlfn.XLOOKUP(Tabla3[[#This Row],[LUGAR ENVÍO]],Tabla9[[Nombre ]],Tabla9[Distancia],"NA") -> 5.757 | I17: =Tabla3[[#This Row],[Valor Tran]]/(Tabla3[[#This Row],[DISTANCIA (km)]]*2) -> 5211.0474 | K17: 1 | L17: 60000 | M17: =Tabla3[[#This Row],[VLR. TRANSPORTE]]/Tabla3[[#This Row],[Numero de Transportes]] -> 60000 | N17: 1045000 | O17: =Tabla3[[#This Row],[VLR. TOTAL FACT.]]-Tabla3[[#This Row],[VLR. TRANSPORTE]] -> 985000 | P17: 1 | Q17: Transferencia
A18: 51291 | B18: 2025-11-07 | C18: manual | D18: Ferney Bernal | E18: Tortolas | F18: 4 | G18: =_xlfn.XLOOKUP(Tabla3[[#This Row],[ID]],Tabla2[ID],Tabla2[Corregimiento],"NA") -> El Carmen | H18: =_xlfn.XLOOKUP(Tabla3[[#This Row],[LUGAR ENVÍO]],Tabla9[[Nombre ]],Tabla9[Distancia],"NA") -> 5.757 | I18: =Tabla3[[#This Row],[Valor Tran]]/(Tabla3[[#This Row],[DISTANCIA (km)]]*2) -> 6948.0632 | K18: 1 | L18: 80000 | M18: 80000 | N18: 1245200 | O18: =Tabla3[[#This Row],[VLR. TOTAL FACT.]]-Tabla3[[#This Row],[VLR. TRANSPORTE]] -> 1165200 | P18: 1 | Q18: tarjeta
A19: 59047 | B19: 45989 | C19: sai | D19: Martha Rosero | E19: Tortolas | F19: 4 | G19: =_xlfn.XLOOKUP(Tabla3[[#This Row],[ID]],Tabla2[ID],Tabla2[Corregimiento],"NA") -> El Carmen | H19: =_xlfn.XLOOKUP(Tabla3[[#This Row],[LUGAR ENVÍO]],Tabla9[[Nombre ]],Tabla9[Distancia],"NA") -> 5.757 | I19: =Tabla3[[#This Row],[Valor Tran]]/(Tabla3[[#This Row],[DISTANCIA (km)]]*2) -> 13896.126 | K19: 1 | L19: 160000 | M19: =Tabla3[[#This Row],[VLR. TRANSPORTE]]/Tabla3[[#This Row],[Numero de Transportes]] -> 160000 | N19: 1704900 | O19: =Tabla3[[#This Row],[VLR. TOTAL FACT.]]-Tabla3[[#This Row],[VLR. TRANSPORTE]] -> 1544900 | P19: 1 | Q19: efectivo
A20: 46906 | B20: 45966 | C20: sai | D20: martha rosero | E20: Tortolas | F20: 4 | G20: =_xlfn.XLOOKUP(Tabla3[[#This Row],[ID]],Tabla2[ID],Tabla2[Corregimiento],"NA") -> El Carmen | H20: =_xlfn.XLOOKUP(Tabla3[[#This Row],[LUGAR ENVÍO]],Tabla9[[Nombre ]],Tabla9[Distancia],"NA") -> 5.757 | I20: =Tabla3[[#This Row],[Valor Tran]]/(Tabla3[[#This Row],[DISTANCIA (km)]]*2) -> 6948.0632 | K20: 2 | L20: 160000 | M20: =Tabla3[[#This Row],[VLR. TRANSPORTE]]/Tabla3[[#This Row],[Numero de Transportes]] -> 80000 | N20: 1915000 | O20: =Tabla3[[#This Row],[VLR. TOTAL FACT.]]-Tabla3[[#This Row],[VLR. TRANSPORTE]] -> 1755000 | P20: 1 | Q20: transferencia
A21: 46903 | B21: 45967 | C21: sai | D21: eduardo olaus | E21: Tocota | F21: 22 | G21: =_xlfn.XLOOKUP(Tabla3[[#This Row],[ID]],Tabla2[ID],Tabla2[Corregimiento],"NA") -> San Bernardo | H21: =_xlfn.XLOOKUP(Tabla3[[#This Row],[LUGAR ENVÍO]],Tabla9[[Nombre ]],Tabla9[Distancia],"NA") -> 9.438 | I21: =Tabla3[[#This Row],[Valor Tran]]/(Tabla3[[#This Row],[DISTANCIA (km)]]*2) -> 2648.8663 | K21: 1 | L21: 50000 | M21: =Tabla3[[#This Row],[VLR. TRANSPORTE]]/Tabla3[[#This Row],[Numero de Transportes]] -> 50000 | N21: 428000 | O21: =Tabla3[[#This Row],[VLR. TOTAL FACT.]]-Tabla3[[#This Row],[VLR. TRANSPORTE]] -> 378000 | P21: 0 | Q21: transferencia
A22: 30503 | B22: 45973 | C22: sai | D22: Guerardo Hernandez | E22: Tocota | F22: 22 | G22: =_xlfn.XLOOKUP(Tabla3[[#This Row],[ID]],Tabla2[ID],Tabla2[Corregimiento],"NA") -> San Bernardo | H22: =_xlfn.XLOOKUP(Tabla3[[#This Row],[LUGAR ENVÍO]],Tabla9[[Nombre ]],Tabla9[Distancia],"NA") -> 9.438 | I22: =Tabla3[[#This Row],[Valor Tran]]/(Tabla3[[#This Row],[DISTANCIA (km)]]*2) -> 3178.6395 | K22: 1 | L22: 60000 | M22: =Tabla3[[#This Row],[VLR. TRANSPORTE]]/Tabla3[[#This Row],[Numero de Transportes]] -> 60000 | N22: 750000 | O22: =Tabla3[[#This Row],[VLR. TOTAL FACT.]]-Tabla3[[#This Row],[VLR. TRANSPORTE]] -> 690000 | P22: 0 | Q22: Transferencia
A23: 58870 | B23: 45985 | C23: sai | D23: diego zuluaga | E23: Tocota | F23: 22 | G23: =_xlfn.XLOOKUP(Tabla3[[#This Row],[ID]],Tabla2[ID],Tabla2[Corregimiento],"NA") -> San Bernardo | H23: =_xlfn.XLOOKUP(Tabla3[[#This Row],[LUGAR ENVÍO]],Tabla9[[Nombre ]],Tabla9[Distancia],"NA") -> 9.438 | I23: =Tabla3[[#This Row],[Valor Tran]]/(Tabla3[[#This Row],[DISTANCIA (km)]]*2) -> 1589.3198 | K23: 2 | L23: 60000 | M23: =Tabla3[[#This Row],[VLR. TRANSPORTE]]/Tabla3[[#This Row],[Numero de Transportes]] -> 30000 | N23: 829000 | O23: =Tabla3[[#This Row],[VLR. TOTAL FACT.]]-Tabla3[[#This Row],[VLR. TRANSPORTE]] -> 769000 | P23: 1 | Q23: tarjeta
A24: 57102 | B24: 45989 | C24: sai | D24: Jose Murillo | E24: Tocota | F24: 22 | G24: =_xlfn.XLOOKUP(Tabla3[[#This Row],[ID]],Tabla2[ID],Tabla2[Corregimiento],"NA") -> San Bernardo | H24: =_xlfn.XLOOKUP(Tabla3[[#This Row],[LUGAR ENVÍO]],Tabla9[[Nombre ]],Tabla9[Distancia],"NA") -> 9.438 | I24: =Tabla3[[#This Row],[Valor Tran]]/(Tabla3[[#This Row],[DISTANCIA (km)]]*2) -> 3178.6395 | K24: 1 | L24: 60000 | M24: =Tabla3[[#This Row],[VLR. TRANSPORTE]]/Tabla3[[#This Row],[Numero de Transportes]] -> 60000 | N24: 1186000 | O24: =Tabla3[[#This Row],[VLR. TOTAL FACT.]]-Tabla3[[#This Row],[VLR. TRANSPORTE]] -> 1126000 | P24: 0 | Q24: efectivo
A25: 30560 | B25: 45979 | C25: sai | D25: NA | E25: Tocota | F25: 22 | G25: =_xlfn.XLOOKUP(Tabla3[[#This Row],[ID]],Tabla2[ID],Tabla2[Corregimiento],"NA") -> San Bernardo | H25: =_xlfn.XLOOKUP(Tabla3[[#This Row],[LUGAR ENVÍO]],Tabla9[[Nombre ]],Tabla9[Distancia],"NA") -> 9.438 | I25: =Tabla3[[#This Row],[Valor Tran]]/(Tabla3[[#This Row],[DISTANCIA (km)]]*2) -> 3178.6395 | K25: 1 | L25: 60000 | M25: =Tabla3[[#This Row],[VLR. TRANSPORTE]]/Tabla3[[#This Row],[Numero de Transportes]] -> 60000 | N25: 1479500 | O25: =Tabla3[[#This Row],[VLR. TOTAL FACT.]]-Tabla3[[#This Row],[VLR. TRANSPORTE]] -> 1419500 | P25: 0 | Q25: Tarjeta
A26: 58552 | B26: 45977 | C26: manual | D26: jose correa | E26: Tierras blancas | F26: 2 | G26: =_xlfn.XLOOKUP(Tabla3[[#This Row],[ID]],Tabla2[ID],Tabla2[Corregimiento],"NA") -> Borrero Ayerbe | H26: =_xlfn.XLOOKUP(Tabla3[[#This Row],[LUGAR ENVÍO]],Tabla9[[Nombre ]],Tabla9[Distancia],"NA") -> 0.449 | I26: =Tabla3[[#This Row],[Valor Tran]]/(Tabla3[[#This Row],[DISTANCIA (km)]]*2) -> 27839.644 | K26: 1 | L26: 25000 | M26: =Tabla3[[#This Row],[VLR. TRANSPORTE]]/Tabla3[[#This Row],[Numero de Transportes]] -> 25000 | N26: 590000 | O26: =Tabla3[[#This Row],[VLR. TOTAL FACT.]]-Tabla3[[#This Row],[VLR. TRANSPORTE]] -> 565000 | P26: 1 | Q26: efectivo
A27: 58977 | B27: 2025-11-21 | C27: sai | D27: Maria Del Carmen | E27: Tierras blancas | F27: 2 | G27: =_xlfn.XLOOKUP(Tabla3[[#This Row],[ID]],Tabla2[ID],Tabla2[Corregimiento],"NA") -> Borrero Ayerbe | H27: =_xlfn.XLOOKUP(Tabla3[[#This Row],[LUGAR ENVÍO]],Tabla9[[Nombre ]],Tabla9[Distancia],"NA") -> 0.449 | I27: =Tabla3[[#This Row],[Valor Tran]]/(Tabla3[[#This Row],[DISTANCIA (km)]]*2) -> 33407.572 | K27: 1 | L27: 30000 | M27: 30000 | N27: 627100 | O27: =Tabla3[[#This Row],[VLR. TOTAL FACT.]]-Tabla3[[#This Row],[VLR. TRANSPORTE]] -> 597100 | P27: 1 | Q27: efectivo
A28: 58706 | B28: 45984 | C28: sai | D28: sergio bautista | E28: Tierras blancas | F28: 2 | G28: =_xlfn.XLOOKUP(Tabla3[[#This Row],[ID]],Tabla2[ID],Tabla2[Corregimiento],"NA") -> Borrero Ayerbe | H28: =_xlfn.XLOOKUP(Tabla3[[#This Row],[LUGAR ENVÍO]],Tabla9[[Nombre ]],Tabla9[Distancia],"NA") -> 0.449 | I28: =Tabla3[[#This Row],[Valor Tran]]/(Tabla3[[#This Row],[DISTANCIA (km)]]*2) -> 55679.287 | K28: 3 | L28: 150000 | M28: =Tabla3[[#This Row],[VLR. TRANSPORTE]]/Tabla3[[#This Row],[Numero de Transportes]] -> 50000 | N28: 1342000 | O28: =Tabla3[[#This Row],[VLR. TOTAL FACT.]]-Tabla3[[#This Row],[VLR. TRANSPORTE]] -> 1192000 | P28: 1 | Q28: tarjeta
A29: 46572 | B29: 2025-11-17 | C29: sai | D29: Sandra Palomino | E29: San miguel | F29: 2 | G29: =_xlfn.XLOOKUP(Tabla3[[#This Row],[ID]],Tabla2[ID],Tabla2[Corregimiento],"NA") -> Borrero Ayerbe | H29: =_xlfn.XLOOKUP(Tabla3[[#This Row],[LUGAR ENVÍO]],Tabla9[[Nombre ]],Tabla9[Distancia],"NA") -> 2.269 | I29: =Tabla3[[#This Row],[Valor Tran]]/(Tabla3[[#This Row],[DISTANCIA (km)]]*2) -> 15425.297 | K29: 1 | L29: 70000 | M29: 70000 | N29: 441600 | O29: =Tabla3[[#This Row],[VLR. TOTAL FACT.]]-Tabla3[[#This Row],[VLR. TRANSPORTE]] -> 371600 | P29: 1 | Q29: efectivo
A30: 51992 | B30: 2025-11-17 | C30: sai | D30: Mario Duran | E30: San miguel | F30: 2 | G30: =_xlfn.XLOOKUP(Tabla3[[#This Row],[ID]],Tabla2[ID],Tabla2[Corregimiento],"NA") -> Borrero Ayerbe | H30: =_xlfn.XLOOKUP(Tabla3[[#This Row],[LUGAR ENVÍO]],Tabla9[[Nombre ]],Tabla9[Distancia],"NA") -> 2.269 | I30: =Tabla3[[#This Row],[Valor Tran]]/(Tabla3[[#This Row],[DISTANCIA (km)]]*2) -> 17628.911 | K30: 1 | L30: 80000 | M30: 80000 | N30: 491200 | O30: =Tabla3[[#This Row],[VLR. TOTAL FACT.]]-Tabla3[[#This Row],[VLR. TRANSPORTE]] -> 411200 | P30: 1 | Q30: transferencia
A31: 0 | B31: 45983 | C31: sai | D31: mireya lopez | E31: San Miguel | F31: 2 | G31: =_xlfn.XLOOKUP(Tabla3[[#This Row],[ID]],Tabla2[ID],Tabla2[Corregimiento],"NA") -> Borrero Ayerbe | H31: =_xlfn.XLOOKUP(Tabla3[[#This Row],[LUGAR ENVÍO]],Tabla9[[Nombre ]],Tabla9[Distancia],"NA") -> 2.269 | I31: =Tabla3[[#This Row],[Valor Tran]]/(Tabla3[[#This Row],[DISTANCIA (km)]]*2) -> 15425.297 | K31: 1 | L31: 70000 | M31: =Tabla3[[#This Row],[VLR. TRANSPORTE]]/Tabla3[[#This Row],[Numero de Transportes]] -> 70000 | N31: 541100 | O31: =Tabla3[[#This Row],[VLR. TOTAL FACT.]]-Tabla3[[#This Row],[VLR. TRANSPORTE]] -> 471100 | P31: 1 | Q31: NA
A32: 57498 | B32: 2025-11-29 | C32: sai | D32: Sandra Palomino | E32: San miguel | F32: 2 | G32: =_xlfn.XLOOKUP(Tabla3[[#This Row],[ID]],Tabla2[ID],Tabla2[Corregimiento],"NA") -> Borrero Ayerbe | H32: =_xlfn.XLOOKUP(Tabla3[[#This Row],[LUGAR ENVÍO]],Tabla9[[Nombre ]],Tabla9[Distancia],"NA") -> 2.269 | I32: =Tabla3[[#This Row],[Valor Tran]]/(Tabla3[[#This Row],[DISTANCIA (km)]]*2) -> 15425.297 | K32: 1 | L32: 70000 | M32: 70000 | N32: 558600 | O32: =Tabla3[[#This Row],[VLR. TOTAL FACT.]]-Tabla3[[#This Row],[VLR. TRANSPORTE]] -> 488600 | P32: 1 | Q32: efectivo
A33: 47307 | B33: 2025-11-25 | C33: sai | D33: Luis Fernando | E33: San miguel | F33: 2 | G33: =_xlfn.XLOOKUP(Tabla3[[#This Row],[ID]],Tabla2[ID],Tabla2[Corregimiento],"NA") -> Borrero Ayerbe | H33: =_xlfn.XLOOKUP(Tabla3[[#This Row],[LUGAR ENVÍO]],Tabla9[[Nombre ]],Tabla9[Distancia],"NA") -> 2.269 | I33: =Tabla3[[#This Row],[Valor Tran]]/(Tabla3[[#This Row],[DISTANCIA (km)]]*2) -> 15425.297 | K33: 1 | L33: 70000 | M33: 70000 | N33: 626400 | O33: =Tabla3[[#This Row],[VLR. TOTAL FACT.]]-Tabla3[[#This Row],[VLR. TRANSPORTE]] -> 556400 | P33: 1 | Q33: efectivo
A34: 58146 | B34: 2025-11-10 | C34: sai | D34: Monica Pastrana | E34: San miguel | F34: 2 | G34: =_xlfn.XLOOKUP(Tabla3[[#This Row],[ID]],Tabla2[ID],Tabla2[Corregimiento],"NA") -> Borrero Ayerbe | H34: =_xlfn.XLOOKUP(Tabla3[[#This Row],[LUGAR ENVÍO]],Tabla9[[Nombre ]],Tabla9[Distancia],"NA") -> 2.269 | I34: =Tabla3[[#This Row],[Valor Tran]]/(Tabla3[[#This Row],[DISTANCIA (km)]]*2) -> 15425.297 | K34: 1 | L34: 70000 | M34: 70000 | N34: 648300 | O34: =Tabla3[[#This Row],[VLR. TOTAL FACT.]]-Tabla3[[#This Row],[VLR. TRANSPORTE]] -> 578300 | P34: 1 | Q34: efectivo
A35: 58837 | B35: 45995 | C35: sai | D35: jhon cruz | E35: San Miguel | F35: 2 | G35: =_xlfn.XLOOKUP(Tabla3[[#This Row],[ID]],Tabla2[ID],Tabla2[Corregimiento],"NA") -> Borrero Ayerbe | H35: =_xlfn.XLOOKUP(Tabla3[[#This Row],[LUGAR ENVÍO]],Tabla9[[Nombre ]],Tabla9[Distancia],"NA") -> 2.269 | I35: =Tabla3[[#This Row],[Valor Tran]]/(Tabla3[[#This Row],[DISTANCIA (km)]]*2) -> 6610.8418 | K35: 1 | L35: 30000 | M35: =Tabla3[[#This Row],[VLR. TRANSPORTE]]/Tabla3[[#This Row],[Numero de Transportes]] -> 30000 | N35: 2391000 | O35: =Tabla3[[#This Row],[VLR. TOTAL FACT.]]-Tabla3[[#This Row],[VLR. TRANSPORTE]] -> 2361000 | P35: 1 | Q35: transferencia
A36: 47219 | B36: 45971 | C36: sai | D36: juan barado | E36: San Jose del Salado | F36: 12 | G36: =_xlfn.XLOOKUP(Tabla3[[#This Row],[ID]],Tabla2[ID],Tabla2[Corregimiento],"NA") -> El Salado | H36: =_xlfn.XLOOKUP(Tabla3[[#This Row],[LUGAR ENVÍO]],Tabla9[[Nombre ]],Tabla9[Distancia],"NA") -> 13.07 | I36: =Tabla3[[#This Row],[Valor Tran]]/(Tabla3[[#This Row],[DISTANCIA (km)]]*2) -> 1530.2219 | K36: 1 | L36: 40000 | M36: =Tabla3[[#This Row],[VLR. TRANSPORTE]]/Tabla3[[#This Row],[Numero de Transportes]] -> 40000 | N36: 401900 | O36: =Tabla3[[#This Row],[VLR. TOTAL FACT.]]-Tabla3[[#This Row],[VLR. TRANSPORTE]] -> 361900 | P36: 1 | Q36: transferenica
A37: 48298 | B37: 45982 | C37: sai | D37: monica pastrana | E37: San Jose del Salado | F37: 12 | G37: =_xlfn.XLOOKUP(Tabla3[[#This Row],[ID]],Tabla2[ID],Tabla2[Corregimiento],"NA") -> El Salado | H37: =_xlfn.XLOOKUP(Tabla3[[#This Row],[LUGAR ENVÍO]],Tabla9[[Nombre ]],Tabla9[Distancia],"NA") -> 13.07 | I37: =Tabla3[[#This Row],[Valor Tran]]/(Tabla3[[#This Row],[DISTANCIA (km)]]*2) -> 2677.8883 | K37: 1 | L37: 70000 | M37: =Tabla3[[#This Row],[VLR. TRANSPORTE]]/Tabla3[[#This Row],[Numero de Transportes]] -> 70000 | N37: 542500 | O37: =Tabla3[[#This Row],[VLR. TOTAL FACT.]]-Tabla3[[#This Row],[VLR. TRANSPORTE]] -> 472500 | P37: 1 | Q37: efectivo
A38: 50256 | B38: 2025-11-22 | C38: sai | D38: Antonio Jimenez | E38: San Jose del Salado | F38: 12 | G38: =_xlfn.XLOOKUP(Tabla3[[#This Row],[ID]],Tabla2[ID],Tabla2[Corregimiento],"NA") -> El Salado | H38: =_xlfn.XLOOKUP(Tabla3[[#This Row],[LUGAR ENVÍO]],Tabla9[[Nombre ]],Tabla9[Distancia],"NA") -> 13.07 | I38: =Tabla3[[#This Row],[Valor Tran]]/(Tabla3[[#This Row],[DISTANCIA (km)]]*2) -> 1530.2219 | K38: 2 | L38: 80000 | M38: 40000 | N38: 633400 | O38: =Tabla3[[#This Row],[VLR. TOTAL FACT.]]-Tabla3[[#This Row],[VLR. TRANSPORTE]] -> 553400 | P38: 1 | Q38: transferencia
A39: 46985 | B39: 45968 | C39: sai | D39: carlos gawes | E39: San Jose del Salado | F39: 12 | G39: =_xlfn.XLOOKUP(Tabla3[[#This Row],[ID]],Tabla2[ID],Tabla2[Corregimiento],"NA") -> El Salado | H39: =_xlfn.XLOOKUP(Tabla3[[#This Row],[LUGAR ENVÍO]],Tabla9[[Nombre ]],Tabla9[Distancia],"NA") -> 13.07 | I39: =Tabla3[[#This Row],[Valor Tran]]/(Tabla3[[#This Row],[DISTANCIA (km)]]*2) -> 1912.7774 | K39: 1 | L39: 50000 | M39: =Tabla3[[#This Row],[VLR. TRANSPORTE]]/Tabla3[[#This Row],[Numero de Transportes]] -> 50000 | N39: 961900 | O39: =Tabla3[[#This Row],[VLR. TOTAL FACT.]]-Tabla3[[#This Row],[VLR. TRANSPORTE]] -> 911900 | P39: 0 | Q39: transferencia
A40: 46966 | B40: 2025-11-15 | C40: sai | D40: Gustavo Chaux | E40: San Jose del Salado | F40: 12 | G40: =_xlfn.XLOOKUP(Tabla3[[#This Row],[ID]],Tabla2[ID],Tabla2[Corregimiento],"NA") -> El Salado | H40: =_xlfn.XLOOKUP(Tabla3[[#This Row],[LUGAR ENVÍO]],Tabla9[[Nombre ]],Tabla9[Distancia],"NA") -> 13.07 | I40: =Tabla3[[#This Row],[Valor Tran]]/(Tabla3[[#This Row],[DISTANCIA (km)]]*2) -> 2677.8883 | K40: 1 | L40: 70000 | M40: 70000 | N40: 1105700 | O40: =Tabla3[[#This Row],[VLR. TOTAL FACT.]]-Tabla3[[#This Row],[VLR. TRANSPORTE]] -> 1035700 | P40: 1 | Q40: efectivo
A41: 30495 | B41: 45981 | C41: sai | D41: Monica Pastrana | E41: San Jose del Salado | F41: 12 | G41: =_xlfn.XLOOKUP(Tabla3[[#This Row],[ID]],Tabla2[ID],Tabla2[Corregimiento],"NA") -> El Salado | H41: =_xlfn.XLOOKUP(Tabla3[[#This Row],[LUGAR ENVÍO]],Tabla9[[Nombre ]],Tabla9[Distancia],"NA") -> 13.07 | I41: =Tabla3[[#This Row],[Valor Tran]]/(Tabla3[[#This Row],[DISTANCIA (km)]]*2) -> 2677.8883 | K41: 1 | L41: 70000 | M41: =Tabla3[[#This Row],[VLR. TRANSPORTE]]/Tabla3[[#This Row],[Numero de Transportes]] -> 70000 | N41: 1343900 | O41: =Tabla3[[#This Row],[VLR. TOTAL FACT.]]-Tabla3[[#This Row],[VLR. TRANSPORTE]] -> 1273900 | P41: 1 | Q41: Tarjeta
A42: 57099 | B42: 45962 | C42: sai | D42: Fundación Shekina | E42: San Jose del Salado | F42: 12 | G42: =_xlfn.XLOOKUP(Tabla3[[#This Row],[ID]],Tabla2[ID],Tabla2[Corregimiento],"NA") -> El Salado | H42: =_xlfn.XLOOKUP(Tabla3[[#This Row],[LUGAR ENVÍO]],Tabla9[[Nombre ]],Tabla9[Distancia],"NA") -> 13.07 | I42: =Tabla3[[#This Row],[Valor Tran]]/(Tabla3[[#This Row],[DISTANCIA (km)]]*2) -> 2295.3328 | K42: 2 | L42: 120000 | M42: =Tabla3[[#This Row],[VLR. TRANSPORTE]]/Tabla3[[#This Row],[Numero de Transportes]] -> 60000 | N42: 1605000 | O42: =Tabla3[[#This Row],[VLR. TOTAL FACT.]]-Tabla3[[#This Row],[VLR. TRANSPORTE]] -> 1485000 | P42: 0 | Q42: Transferencia
A43: 58976 | B43: 45985 | C43: manual | D43: doris villarriaga | E43: San Fernando | F43: 6 | G43: =_xlfn.XLOOKUP(Tabla3[[#This Row],[ID]],Tabla2[ID],Tabla2[Corregimiento],"NA") -> El Limonar | H43: =_xlfn.XLOOKUP(Tabla3[[#This Row],[LUGAR ENVÍO]],Tabla9[[Nombre ]],Tabla9[Distancia],"NA") -> 7.603318 | I43: =Tabla3[[#This Row],[Valor Tran]]/(Tabla3[[#This Row],[DISTANCIA (km)]]*2) -> 4603.2535 | K43: 1 | L43: 70000 | M43: =Tabla3[[#This Row],[VLR. TRANSPORTE]]/Tabla3[[#This Row],[Numero de Transportes]] -> 70000 | N43: 841000 | O43: =Tabla3[[#This Row],[VLR. TOTAL FACT.]]-Tabla3[[#This Row],[VLR. TRANSPORTE]] -> 771000 | P43: 1 | Q43: efectivo
A44: 46592 | B44: 45964 | C44: sai | D44: jose giraldo | E44: San Fernando | F44: 6 | G44: =_xlfn.XLOOKUP(Tabla3[[#This Row],[ID]],Tabla2[ID],Tabla2[Corregimiento],"NA") -> El Limonar | H44: =_xlfn.XLOOKUP(Tabla3[[#This Row],[LUGAR ENVÍO]],Tabla9[[Nombre ]],Tabla9[Distancia],"NA") -> 7.603318 | I44: =Tabla3[[#This Row],[Valor Tran]]/(Tabla3[[#This Row],[DISTANCIA (km)]]*2) -> 3945.6458 | K44: 1 | L44: 60000 | M44: =Tabla3[[#This Row],[VLR. TRANSPORTE]]/Tabla3[[#This Row],[Numero de Transportes]] -> 60000 | N44: 846000 | O44: =Tabla3[[#This Row],[VLR. TOTAL FACT.]]-Tabla3[[#This Row],[VLR. TRANSPORTE]] -> 786000 | P44: 1 | Q44: transferencia
A45: 55784 | B45: 2025-11-25 | C45: sai | D45: Soraya Vargas | E45: San Fernando | F45: 6 | G45: =_xlfn.XLOOKUP(Tabla3[[#This Row],[ID]],Tabla2[ID],Tabla2[Corregimiento],"NA") -> El Limonar | H45: =_xlfn.XLOOKUP(Tabla3[[#This Row],[LUGAR ENVÍO]],Tabla9[[Nombre ]],Tabla9[Distancia],"NA") -> 7.603318 | I45: =Tabla3[[#This Row],[Valor Tran]]/(Tabla3[[#This Row],[DISTANCIA (km)]]*2) -> 4603.2535 | K45: 1 | L45: 70000 | M45: 70000 | N45: 895600 | O45: =Tabla3[[#This Row],[VLR. TOTAL FACT.]]-Tabla3[[#This Row],[VLR. TRANSPORTE]] -> 825600 | P45: 1 | Q45: efectivo
A46: 58524 | B46: 45976 | C46: manual | D46: elizabeth | E46: Saliendo del carmen | F46: 4 | G46: =_xlfn.XLOOKUP(Tabla3[[#This Row],[ID]],Tabla2[ID],Tabla2[Corregimiento],"NA") -> El Carmen | H46: =_xlfn.XLOOKUP(Tabla3[[#This Row],[LUGAR ENVÍO]],Tabla9[[Nombre ]],Tabla9[Distancia],"NA") -> 4.734 | I46: =Tabla3[[#This Row],[Valor Tran]]/(Tabla3[[#This Row],[DISTANCIA (km)]]*2) -> 4224.7571 | K46: 1 | L46: 40000 | M46: =Tabla3[[#This Row],[VLR. TRANSPORTE]]/Tabla3[[#This Row],[Numero de Transportes]] -> 40000 | N46: 288000 | O46: =Tabla3[[#This Row],[VLR. TOTAL FACT.]]-Tabla3[[#This Row],[VLR. TRANSPORTE]] -> 248000 | P46: 0 | Q46: efectivo
A47: 58868 | B47: 45998 | C47: sai | D47: Samuel Calle | E47: Saliendo del carmen | F47: 4 | G47: =_xlfn.XLOOKUP(Tabla3[[#This Row],[ID]],Tabla2[ID],Tabla2[Corregimiento],"NA") -> El Carmen | H47: =_xlfn.XLOOKUP(Tabla3[[#This Row],[LUGAR ENVÍO]],Tabla9[[Nombre ]],Tabla9[Distancia],"NA") -> 4.734 | I47: =Tabla3[[#This Row],[Valor Tran]]/(Tabla3[[#This Row],[DISTANCIA (km)]]*2) -> 6337.1356 | K47: 1 | L47: 60000 | M47: =Tabla3[[#This Row],[VLR. TRANSPORTE]]/Tabla3[[#This Row],[Numero de Transportes]] -> 60000 | N47: 3389000 | O47: =Tabla3[[#This Row],[VLR. TOTAL FACT.]]-Tabla3[[#This Row],[VLR. TRANSPORTE]] -> 3329000 | P47: 1 | Q47: transferencia
A48: 58704 | B48: 45996 | C48: sai | D48: mireya lopez | E48: Saliendo del carmen | F48: 4 | G48: =_xlfn.XLOOKUP(Tabla3[[#This Row],[ID]],Tabla2[ID],Tabla2[Corregimiento],"NA") -> El Carmen | H48: =_xlfn.XLOOKUP(Tabla3[[#This Row],[LUGAR ENVÍO]],Tabla9[[Nombre ]],Tabla9[Distancia],"NA") -> 4.734 | I48: =Tabla3[[#This Row],[Valor Tran]]/(Tabla3[[#This Row],[DISTANCIA (km)]]*2) -> 1584.2839 | K48: 1 | L48: 15000 | M48: =Tabla3[[#This Row],[VLR. TRANSPORTE]]/Tabla3[[#This Row],[Numero de Transportes]] -> 15000 | N48: 3633000 | O48: =Tabla3[[#This Row],[VLR. TOTAL FACT.]]-Tabla3[[#This Row],[VLR. TRANSPORTE]] -> 3618000 | P48: 0 | Q48: transferencia
A49: 56686 | B49: 2025-11-01 | C49: sai | D49: Elizabeth Perlaza | E49: Salida al carmen | F49: 2 | G49: =_xlfn.XLOOKUP(Tabla3[[#This Row],[ID]],Tabla2[ID],Tabla2[Corregimiento],"NA") -> Borrero Ayerbe | H49: =_xlfn.XLOOKUP(Tabla3[[#This Row],[LUGAR ENVÍO]],Tabla9[[Nombre ]],Tabla9[Distancia],"NA") -> 2.329 | I49: =Tabla3[[#This Row],[Valor Tran]]/(Tabla3[[#This Row],[DISTANCIA (km)]]*2) -> 6440.5324 | K49: 1 | L49: 30000 | M49: 30000 | N49: 592700 | O49: =Tabla3[[#This Row],[VLR. TOTAL FACT.]]-Tabla3[[#This Row],[VLR. TRANSPORTE]] -> 562700 | P49: 1 | Q49: efectivo
A50: 58344 | B50: 2025-11-15 | C50: sai | D50: Edilson Vargas | E50: Salida al carmen | F50: 2 | G50: =_xlfn.XLOOKUP(Tabla3[[#This Row],[ID]],Tabla2[ID],Tabla2[Corregimiento],"NA") -> Borrero Ayerbe | H50: =_xlfn.XLOOKUP(Tabla3[[#This Row],[LUGAR ENVÍO]],Tabla9[[Nombre ]],Tabla9[Distancia],"NA") -> 2.329 | I50: =Tabla3[[#This Row],[Valor Tran]]/(Tabla3[[#This Row],[DISTANCIA (km)]]*2) -> 6440.5324 | K50: 1 | L50: 30000 | M50: 30000 | N50: 612900 | O50: =Tabla3[[#This Row],[VLR. TOTAL FACT.]]-Tabla3[[#This Row],[VLR. TRANSPORTE]] -> 582900 | P50: 1 | Q50: transferencia
A51: 47342 | B51: 2025-11-27 | C51: sai | D51: Sebastian Barragan | E51: Salida al carmen | F51: 2 | G51: =_xlfn.XLOOKUP(Tabla3[[#This Row],[ID]],Tabla2[ID],Tabla2[Corregimiento],"NA") -> Borrero Ayerbe | H51: =_xlfn.XLOOKUP(Tabla3[[#This Row],[LUGAR ENVÍO]],Tabla9[[Nombre ]],Tabla9[Distancia],"NA") -> 2.329 | I51: =Tabla3[[#This Row],[Valor Tran]]/(Tabla3[[#This Row],[DISTANCIA (km)]]*2) -> 6440.5324 | K51: 1 | L51: 30000 | M51: 30000 | N51: 637600 | O51: =Tabla3[[#This Row],[VLR. TOTAL FACT.]]-Tabla3[[#This Row],[VLR. TRANSPORTE]] -> 607600 | P51: 1 | Q51: efectivo
A52: 58270 | B52: 45985 | C52: manual | D52: victor | E52: Salida al carmen | F52: 2 | G52: =_xlfn.XLOOKUP(Tabla3[[#This Row],[ID]],Tabla2[ID],Tabla2[Corregimiento],"NA") -> Borrero Ayerbe | H52: =_xlfn.XLOOKUP(Tabla3[[#This Row],[LUGAR ENVÍO]],Tabla9[[Nombre ]],Tabla9[Distancia],"NA") -> 2.329 | I52: =Tabla3[[#This Row],[Valor Tran]]/(Tabla3[[#This Row],[DISTANCIA (km)]]*2) -> 6440.5324 | K52: 1 | L52: 30000 | M52: =Tabla3[[#This Row],[VLR. TRANSPORTE]]/Tabla3[[#This Row],[Numero de Transportes]] -> 30000 | N52: 656000 | O52: =Tabla3[[#This Row],[VLR. TOTAL FACT.]]-Tabla3[[#This Row],[VLR. TRANSPORTE]] -> 626000 | P52: 1 | Q52: efectivo
A53: 58722 | B53: 45986 | C53: sai | D53: angui rengifo | E53: Salida al carmen | F53: 2 | G53: =_xlfn.XLOOKUP(Tabla3[[#This Row],[ID]],Tabla2[ID],Tabla2[Corregimiento],"NA") -> Borrero Ayerbe | H53: =_xlfn.XLOOKUP(Tabla3[[#This Row],[LUGAR ENVÍO]],Tabla9[[Nombre ]],Tabla9[Distancia],"NA") -> 2.329 | I53: =Tabla3[[#This Row],[Valor Tran]]/(Tabla3[[#This Row],[DISTANCIA (km)]]*2) -> 4293.6883 | K53: 1 | L53: 20000 | M53: =Tabla3[[#This Row],[VLR. TRANSPORTE]]/Tabla3[[#This Row],[Numero de Transportes]] -> 20000 | N53: 4505000 | O53: =Tabla3[[#This Row],[VLR. TOTAL FACT.]]-Tabla3[[#This Row],[VLR. TRANSPORTE]] -> 4485000 | P53: 1 | Q53: efectivo
A54: 47572 | B54: 45974 | C54: sai | D54: maria del carmen | E54: Pirineos | F54: 4 | G54: =_xlfn.XLOOKUP(Tabla3[[#This Row],[ID]],Tabla2[ID],Tabla2[Corregimiento],"NA") -> El Carmen | H54: =_xlfn.XLOOKUP(Tabla3[[#This Row],[LUGAR ENVÍO]],Tabla9[[Nombre ]],Tabla9[Distancia],"NA") -> 2.66665 | I54: =Tabla3[[#This Row],[Valor Tran]]/(Tabla3[[#This Row],[DISTANCIA (km)]]*2) -> 5625.0352 | K54: 1 | L54: 30000 | M54: =Tabla3[[#This Row],[VLR. TRANSPORTE]]/Tabla3[[#This Row],[Numero de Transportes]] -> 30000 | N54: 164000 | O54: =Tabla3[[#This Row],[VLR. TOTAL FACT.]]-Tabla3[[#This Row],[VLR. TRANSPORTE]] -> 134000 | P54: 0 | Q54: transferencia
A55: 30489 | B55: 45981 | C55: sai | D55: Maria Del Carmen Astorquiza | E55: Pirineos | F55: 4 | G55: =_xlfn.XLOOKUP(Tabla3[[#This Row],[ID]],Tabla2[ID],Tabla2[Corregimiento],"NA") -> El Carmen | H55: =_xlfn.XLOOKUP(Tabla3[[#This Row],[LUGAR ENVÍO]],Tabla9[[Nombre ]],Tabla9[Distancia],"NA") -> 2.66665 | I55: =Tabla3[[#This Row],[Valor Tran]]/(Tabla3[[#This Row],[DISTANCIA (km)]]*2) -> 5625.0352 | K55: 1 | L55: 30000 | M55: =Tabla3[[#This Row],[VLR. TRANSPORTE]]/Tabla3[[#This Row],[Numero de Transportes]] -> 30000 | N55: 220000 | O55: =Tabla3[[#This Row],[VLR. TOTAL FACT.]]-Tabla3[[#This Row],[VLR. TRANSPORTE]] -> 190000 | P55: 0 | Q55: tarjeta
A56: 30586 | B56: 45980 | C56: sai | D56: Gustavo Chaux | E56: Pirineos | F56: 4 | G56: =_xlfn.XLOOKUP(Tabla3[[#This Row],[ID]],Tabla2[ID],Tabla2[Corregimiento],"NA") -> El Carmen | H56: =_xlfn.XLOOKUP(Tabla3[[#This Row],[LUGAR ENVÍO]],Tabla9[[Nombre ]],Tabla9[Distancia],"NA") -> 2.66665 | I56: =Tabla3[[#This Row],[Valor Tran]]/(Tabla3[[#This Row],[DISTANCIA (km)]]*2) -> 9375.0586 | K56: 1 | L56: 50000 | M56: =Tabla3[[#This Row],[VLR. TRANSPORTE]]/Tabla3[[#This Row],[Numero de Transportes]] -> 50000 | N56: 303000 | O56: =Tabla3[[#This Row],[VLR. TOTAL FACT.]]-Tabla3[[#This Row],[VLR. TRANSPORTE]] -> 253000 | P56: 0 | Q56: Transferencia
A57: 58813 | B57: 45997 | C57: sai | D57: isabel castaño | E57: Pirineos | F57: 4 | G57: =_xlfn.XLOOKUP(Tabla3[[#This Row],[ID]],Tabla2[ID],Tabla2[Corregimiento],"NA") -> El Carmen | H57: =_xlfn.XLOOKUP(Tabla3[[#This Row],[LUGAR ENVÍO]],Tabla9[[Nombre ]],Tabla9[Distancia],"NA") -> 2.66665 | I57: =Tabla3[[#This Row],[Valor Tran]]/(Tabla3[[#This Row],[DISTANCIA (km)]]*2) -> 13125.082 | K57: 1 | L57: 70000 | M57: =Tabla3[[#This Row],[VLR. TRANSPORTE]]/Tabla3[[#This Row],[Numero de Transportes]] -> 70000 | N57: 621000 | O57: =Tabla3[[#This Row],[VLR. TOTAL FACT.]]-Tabla3[[#This Row],[VLR. TRANSPORTE]] -> 551000 | P57: 1 | Q57: efectivo
A58: 47292 | B58: 45970 | C58: sai | D58: oscar quiñonez | E58: Pirineos | F58: 4 | G58: =_xlfn.XLOOKUP(Tabla3[[#This Row],[ID]],Tabla2[ID],Tabla2[Corregimiento],"NA") -> El Carmen | H58: =_xlfn.XLOOKUP(Tabla3[[#This Row],[LUGAR ENVÍO]],Tabla9[[Nombre ]],Tabla9[Distancia],"NA") -> 2.66665 | I58: =Tabla3[[#This Row],[Valor Tran]]/(Tabla3[[#This Row],[DISTANCIA (km)]]*2) -> 11250.07 | K58: 1 | L58: 60000 | M58: =Tabla3[[#This Row],[VLR. TRANSPORTE]]/Tabla3[[#This Row],[Numero de Transportes]] -> 60000 | N58: 736800 | O58: =Tabla3[[#This Row],[VLR. TOTAL FACT.]]-Tabla3[[#This Row],[VLR. TRANSPORTE]] -> 676800 | P58: 1 | Q58: transferencia
A59: 48527 | B59: 45983 | C59: sai | D59: mario camacho | E59: Pirineos | F59: 4 | G59: =_xlfn.XLOOKUP(Tabla3[[#This Row],[ID]],Tabla2[ID],Tabla2[Corregimiento],"NA") -> El Carmen | H59: =_xlfn.XLOOKUP(Tabla3[[#This Row],[LUGAR ENVÍO]],Tabla9[[Nombre ]],Tabla9[Distancia],"NA") -> 2.66665 | I59: =Tabla3[[#This Row],[Valor Tran]]/(Tabla3[[#This Row],[DISTANCIA (km)]]*2) -> 11250.07 | K59: 1 | L59: 60000 | M59: =Tabla3[[#This Row],[VLR. TRANSPORTE]]/Tabla3[[#This Row],[Numero de Transportes]] -> 60000 | N59: 838000 | O59: =Tabla3[[#This Row],[VLR. TOTAL FACT.]]-Tabla3[[#This Row],[VLR. TRANSPORTE]] -> 778000 | P59: 1 | Q59: transferencia
A60: 36307 | B60: 2025-11-27 | C60: manual | D60: Sebastian Barragan | E60: Pirineos | F60: 4 | G60: =_xlfn.XLOOKUP(Tabla3[[#This Row],[ID]],Tabla2[ID],Tabla2[Corregimiento],"NA") -> El Carmen | H60: =_xlfn.XLOOKUP(Tabla3[[#This Row],[LUGAR ENVÍO]],Tabla9[[Nombre ]],Tabla9[Distancia],"NA") -> 2.66665 | I60: =Tabla3[[#This Row],[Valor Tran]]/(Tabla3[[#This Row],[DISTANCIA (km)]]*2) -> 11250.07 | K60: 2 | L60: 120000 | M60: 60000 | N60: 1301500 | O60: =Tabla3[[#This Row],[VLR. TOTAL FACT.]]-Tabla3[[#This Row],[VLR. TRANSPORTE]] -> 1181500 | P60: 1 | Q60: tarjeta
A61: 58313 | B61: 45972 | C61: sai | D61: Nicolas Caicedo | E61: Pirineos | F61: 4 | G61: =_xlfn.XLOOKUP(Tabla3[[#This Row],[ID]],Tabla2[ID],Tabla2[Corregimiento],"NA") -> El Carmen | H61: =_xlfn.XLOOKUP(Tabla3[[#This Row],[LUGAR ENVÍO]],Tabla9[[Nombre ]],Tabla9[Distancia],"NA") -> 2.66665 | I61: =Tabla3[[#This Row],[Valor Tran]]/(Tabla3[[#This Row],[DISTANCIA (km)]]*2) -> 11250.07 | K61: 1 | L61: 60000 | M61: =Tabla3[[#This Row],[VLR. TRANSPORTE]]/Tabla3[[#This Row],[Numero de Transportes]] -> 60000 | N61: 1630800 | O61: =Tabla3[[#This Row],[VLR. TOTAL FACT.]]-Tabla3[[#This Row],[VLR. TRANSPORTE]] -> 1570800 | P61: 1 | Q61: efectivo
A62: 58802 | B62: 45986 | C62: manual | D62: Oscar Narvaez | E62: Pirineos | F62: 4 | G62: =_xlfn.XLOOKUP(Tabla3[[#This Row],[ID]],Tabla2[ID],Tabla2[Corregimiento],"NA") -> El Carmen | H62: =_xlfn.XLOOKUP(Tabla3[[#This Row],[LUGAR ENVÍO]],Tabla9[[Nombre ]],Tabla9[Distancia],"NA") -> 2.66665 | I62: =Tabla3[[#This Row],[Valor Tran]]/(Tabla3[[#This Row],[DISTANCIA (km)]]*2) -> 2812.5176 | K62: 1 | L62: 15000 | M62: =Tabla3[[#This Row],[VLR. TRANSPORTE]]/Tabla3[[#This Row],[Numero de Transportes]] -> 15000 | N62: 4270000 | O62: =Tabla3[[#This Row],[VLR. TOTAL FACT.]]-Tabla3[[#This Row],[VLR. TRANSPORTE]] -> 4255000 | P62: 1 | Q62: transferencia
A63: 48951 | B63: 2025-11-04 | C63: manual | D63: Mario Duran | E63: Parcelaón las palmas | F63: 4 | G63: =_xlfn.XLOOKUP(Tabla3[[#This Row],[ID]],Tabla2[ID],Tabla2[Corregimiento],"NA") -> El Carmen | H63: =_xlfn.XLOOKUP(Tabla3[[#This Row],[LUGAR ENVÍO]],Tabla9[[Nombre ]],Tabla9[Distancia],"NA") -> 2.641 | I63: =Tabla3[[#This Row],[Valor Tran]]/(Tabla3[[#This Row],[DISTANCIA (km)]]*2) -> 7572.8891 | K63: 1 | L63: 40000 | M63: 40000 | N63: 472500 | O63: =Tabla3[[#This Row],[VLR. TOTAL FACT.]]-Tabla3[[#This Row],[VLR. TRANSPORTE]] -> 432500 | P63: 1 | Q63: transferencia
A64: 52866 | B64: 2025-11-15 | C64: sai | D64: Robinson Muñoz | E64: Parcelaón las palmas | F64: 4 | G64: =_xlfn.XLOOKUP(Tabla3[[#This Row],[ID]],Tabla2[ID],Tabla2[Corregimiento],"NA") -> El Carmen | H64: =_xlfn.XLOOKUP(Tabla3[[#This Row],[LUGAR ENVÍO]],Tabla9[[Nombre ]],Tabla9[Distancia],"NA") -> 2.641 | I64: =Tabla3[[#This Row],[Valor Tran]]/(Tabla3[[#This Row],[DISTANCIA (km)]]*2) -> 7572.8891 | K64: 1 | L64: 40000 | M64: 40000 | N64: 486200 | O64: =Tabla3[[#This Row],[VLR. TOTAL FACT.]]-Tabla3[[#This Row],[VLR. TRANSPORTE]] -> 446200 | P64: 1 | Q64: efectivo
A65: 58352 | B65: 45987 | C65: sai | D65: Carlos Arturo | E65: Parcelaón las palmas | F65: 8 | G65: =_xlfn.XLOOKUP(Tabla3[[#This Row],[ID]],Tabla2[ID],Tabla2[Corregimiento],"NA") -> El Palmar | H65: =_xlfn.XLOOKUP(Tabla3[[#This Row],[LUGAR ENVÍO]],Tabla9[[Nombre ]],Tabla9[Distancia],"NA") -> 2.641 | I65: =Tabla3[[#This Row],[Valor Tran]]/(Tabla3[[#This Row],[DISTANCIA (km)]]*2) -> 7572.8891 | K65: 1 | L65: 40000 | M65: =Tabla3[[#This Row],[VLR. TRANSPORTE]]/Tabla3[[#This Row],[Numero de Transportes]] -> 40000 | N65: 533000 | O65: =Tabla3[[#This Row],[VLR. TOTAL FACT.]]-Tabla3[[#This Row],[VLR. TRANSPORTE]] -> 493000 | P65: 1 | Q65: Transferencia
A66: 51245 | B66: 2025-11-12 | C66: sai | D66: Julio Daza | E66: Parcelaón las palmas | F66: 4 | G66: =_xlfn.XLOOKUP(Tabla3[[#This Row],[ID]],Tabla2[ID],Tabla2[Corregimiento],"NA") -> El Carmen | H66: =_xlfn.XLOOKUP(Tabla3[[#This Row],[LUGAR ENVÍO]],Tabla9[[Nombre ]],Tabla9[Distancia],"NA") -> 2.641 | I66: =Tabla3[[#This Row],[Valor Tran]]/(Tabla3[[#This Row],[DISTANCIA (km)]]*2) -> 7572.8891 | K66: 1 | L66: 40000 | M66: 40000 | N66: 605800 | O66: =Tabla3[[#This Row],[VLR. TOTAL FACT.]]-Tabla3[[#This Row],[VLR. TRANSPORTE]] -> 565800 | P66: 1 | Q66: efectivo
A67: 59128 | B67: 45988 | C67: sai | D67: NA | E67: Parcelaón las palmas | F67: 4 | G67: =_xlfn.XLOOKUP(Tabla3[[#This Row],[ID]],Tabla2[ID],Tabla2[Corregimiento],"NA") -> El Carmen | H67: =_xlfn.XLOOKUP(Tabla3[[#This Row],[LUGAR ENVÍO]],Tabla9[[Nombre ]],Tabla9[Distancia],"NA") -> 2.641 | I67: =Tabla3[[#This Row],[Valor Tran]]/(Tabla3[[#This Row],[DISTANCIA (km)]]*2) -> 7572.8891 | K67: 1 | L67: 40000 | M67: =Tabla3[[#This Row],[VLR. TRANSPORTE]]/Tabla3[[#This Row],[Numero de Transportes]] -> 40000 | N67: 665000 | O67: =Tabla3[[#This Row],[VLR. TOTAL FACT.]]-Tabla3[[#This Row],[VLR. TRANSPORTE]] -> 625000 | P67: 0 | Q67: Transferencia
A68: 46700 | B68: 45965 | C68: sai | D68: ibette | E68: Parcelación Monterico | F68: 4 | G68: =_xlfn.XLOOKUP(Tabla3[[#This Row],[ID]],Tabla2[ID],Tabla2[Corregimiento],"NA") -> El Carmen | H68: =_xlfn.XLOOKUP(Tabla3[[#This Row],[LUGAR ENVÍO]],Tabla9[[Nombre ]],Tabla9[Distancia],"NA") -> 9.826848 | I68: =Tabla3[[#This Row],[Valor Tran]]/(Tabla3[[#This Row],[DISTANCIA (km)]]*2) -> 2544.0507 | K68: 1 | L68: 50000 | M68: =Tabla3[[#This Row],[VLR. TRANSPORTE]]/Tabla3[[#This Row],[Numero de Transportes]] -> 50000 | N68: 138500 | O68: =Tabla3[[#This Row],[VLR. TOTAL FACT.]]-Tabla3[[#This Row],[VLR. TRANSPORTE]] -> 88500 | P68: 0 | Q68: transferencia
A69: 46946 | B69: 45968 | C69: sai | D69: eliana jareamillo | E69: Parcelación Monterico | F69: 4 | G69: =_xlfn.XLOOKUP(Tabla3[[#This Row],[ID]],Tabla2[ID],Tabla2[Corregimiento],"NA") -> El Carmen | H69: =_xlfn.XLOOKUP(Tabla3[[#This Row],[LUGAR ENVÍO]],Tabla9[[Nombre ]],Tabla9[Distancia],"NA") -> 9.826848 | I69: =Tabla3[[#This Row],[Valor Tran]]/(Tabla3[[#This Row],[DISTANCIA (km)]]*2) -> 6614.5319 | K69: 1 | L69: 130000 | M69: =Tabla3[[#This Row],[VLR. TRANSPORTE]]/Tabla3[[#This Row],[Numero de Transportes]] -> 130000 | N69: 1458000 | O69: =Tabla3[[#This Row],[VLR. TOTAL FACT.]]-Tabla3[[#This Row],[VLR. TRANSPORTE]] -> 1328000 | P69: 1 | Q69: trasferencia
A70: 30441 | B70: 45971 | C70: sai | D70: Guillermo Lozada | E70: Parcelacion la Cristalina | F70: 4 | G70: =_xlfn.XLOOKUP(Tabla3[[#This Row],[ID]],Tabla2[ID],Tabla2[Corregimiento],"NA") -> El Carmen | H70: =_xlfn.XLOOKUP(Tabla3[[#This Row],[LUGAR ENVÍO]],Tabla9[[Nombre ]],Tabla9[Distancia],"NA") -> 2.71 | I70: =Tabla3[[#This Row],[Valor Tran]]/(Tabla3[[#This Row],[DISTANCIA (km)]]*2) -> 11070.111 | K70: 1 | L70: 60000 | M70: =Tabla3[[#This Row],[VLR. TRANSPORTE]]/Tabla3[[#This Row],[Numero de Transportes]] -> 60000 | N70: 258000 | O70: =Tabla3[[#This Row],[VLR. TOTAL FACT.]]-Tabla3[[#This Row],[VLR. TRANSPORTE]] -> 198000 | P70: 1 | Q70: Transferencia
A71: 52758 | B71: 2025-11-26 | C71: sai | D71: Luis Fernando | E71: Parcelacion la Cristalina | F71: 4 | G71: =_xlfn.XLOOKUP(Tabla3[[#This Row],[ID]],Tabla2[ID],Tabla2[Corregimiento],"NA") -> El Carmen | H71: =_xlfn.XLOOKUP(Tabla3[[#This Row],[LUGAR ENVÍO]],Tabla9[[Nombre ]],Tabla9[Distancia],"NA") -> 2.71 | I71: =Tabla3[[#This Row],[Valor Tran]]/(Tabla3[[#This Row],[DISTANCIA (km)]]*2) -> 7380.0738 | K71: 1 | L71: 40000 | M71: 40000 | N71: 346100 | O71: =Tabla3[[#This Row],[VLR. TOTAL FACT.]]-Tabla3[[#This Row],[VLR. TRANSPORTE]] -> 306100 | P71: 1 | Q71: transferencia
A72: 57849 | B72: 45972 | C72: sai | D72: Fidel Charria | E72: Parcelacion la Cristalina | F72: 4 | G72: =_xlfn.XLOOKUP(Tabla3[[#This Row],[ID]],Tabla2[ID],Tabla2[Corregimiento],"NA") -> El Carmen | H72: =_xlfn.XLOOKUP(Tabla3[[#This Row],[LUGAR ENVÍO]],Tabla9[[Nombre ]],Tabla9[Distancia],"NA") -> 2.71 | I72: =Tabla3[[#This Row],[Valor Tran]]/(Tabla3[[#This Row],[DISTANCIA (km)]]*2) -> 11070.111 | K72: 1 | L72: 60000 | M72: =Tabla3[[#This Row],[VLR. TRANSPORTE]]/Tabla3[[#This Row],[Numero de Transportes]] -> 60000 | N72: 400000 | O72: =Tabla3[[#This Row],[VLR. TOTAL FACT.]]-Tabla3[[#This Row],[VLR. TRANSPORTE]] -> 340000 | P72: 1 | Q72: Tarjeta
A73: 46605 | B73: 45963 | C73: sai | D73: guillermo | E73: Parcelacion la Cristalina | F73: 4 | G73: =_xlfn.XLOOKUP(Tabla3[[#This Row],[ID]],Tabla2[ID],Tabla2[Corregimiento],"NA") -> El Carmen | H73: =_xlfn.XLOOKUP(Tabla3[[#This Row],[LUGAR ENVÍO]],Tabla9[[Nombre ]],Tabla9[Distancia],"NA") -> 2.71 | I73: =Tabla3[[#This Row],[Valor Tran]]/(Tabla3[[#This Row],[DISTANCIA (km)]]*2) -> 11070.111 | K73: 1 | L73: 60000 | M73: =Tabla3[[#This Row],[VLR. TRANSPORTE]]/Tabla3[[#This Row],[Numero de Transportes]] -> 60000 | N73: 419500 | O73: =Tabla3[[#This Row],[VLR. TOTAL FACT.]]-Tabla3[[#This Row],[VLR. TRANSPORTE]] -> 359500 | P73: 1 | Q73: transferencia
A74: 48324 | B74: 45983 | C74: sai | D74: cesar | E74: Parcelacion la Cristalina | F74: 4 | G74: =_xlfn.XLOOKUP(Tabla3[[#This Row],[ID]],Tabla2[ID],Tabla2[Corregimiento],"NA") -> El Carmen | H74: =_xlfn.XLOOKUP(Tabla3[[#This Row],[LUGAR ENVÍO]],Tabla9[[Nombre ]],Tabla9[Distancia],"NA") -> 2.71 | I74: =Tabla3[[#This Row],[Valor Tran]]/(Tabla3[[#This Row],[DISTANCIA (km)]]*2) -> 9225.0923 | K74: 1 | L74: 50000 | M74: =Tabla3[[#This Row],[VLR. TRANSPORTE]]/Tabla3[[#This Row],[Numero de Transportes]] -> 50000 | N74: 515000 | O74: =Tabla3[[#This Row],[VLR. TOTAL FACT.]]-Tabla3[[#This Row],[VLR. TRANSPORTE]] -> 465000 | P74: 0 | Q74: transferenica
A75: 57737 | B75: 45966 | C75: sai | D75: luis montes | E75: Parcelación El bosque | F75: 4 | G75: =_xlfn.XLOOKUP(Tabla3[[#This Row],[ID]],Tabla2[ID],Tabla2[Corregimiento],"NA") -> El Carmen | H75: =_xlfn.XLOOKUP(Tabla3[[#This Row],[LUGAR ENVÍO]],Tabla9[[Nombre ]],Tabla9[Distancia],"NA") -> 4.800039 | I75: =Tabla3[[#This Row],[Valor Tran]]/(Tabla3[[#This Row],[DISTANCIA (km)]]*2) -> 5208.291 | K75: 1 | L75: 50000 | M75: =Tabla3[[#This Row],[VLR. TRANSPORTE]]/Tabla3[[#This Row],[Numero de Transportes]] -> 50000 | N75: 304500 | O75: =Tabla3[[#This Row],[VLR. TOTAL FACT.]]-Tabla3[[#This Row],[VLR. TRANSPORTE]] -> 254500 | P75: 1 | Q75: efectivo
A76: 47439 | B76: 45972 | C76: sai | D76: Maria Amparo Aula | E76: Parcelación El bosque | F76: 4 | G76: =_xlfn.XLOOKUP(Tabla3[[#This Row],[ID]],Tabla2[ID],Tabla2[Corregimiento],"NA") -> El Carmen | H76: =_xlfn.XLOOKUP(Tabla3[[#This Row],[LUGAR ENVÍO]],Tabla9[[Nombre ]],Tabla9[Distancia],"NA") -> 4.800039 | I76: =Tabla3[[#This Row],[Valor Tran]]/(Tabla3[[#This Row],[DISTANCIA (km)]]*2) -> 7291.6074 | K76: 1 | L76: 70000 | M76: =Tabla3[[#This Row],[VLR. TRANSPORTE]]/Tabla3[[#This Row],[Numero de Transportes]] -> 70000 | N76: 420400 | O76: =Tabla3[[#This Row],[VLR. TOTAL FACT.]]-Tabla3[[#This Row],[VLR. TRANSPORTE]] -> 350400 | P76: 1 | Q76: tarjeta
A77: 53251 | B77: 2025-11-21 | C77: sai | D77: Robinson Muñoz | E77: Parcelación El bosque | F77: 4 | G77: =_xlfn.XLOOKUP(Tabla3[[#This Row],[ID]],Tabla2[ID],Tabla2[Corregimiento],"NA") -> El Carmen | H77: =_xlfn.XLOOKUP(Tabla3[[#This Row],[LUGAR ENVÍO]],Tabla9[[Nombre ]],Tabla9[Distancia],"NA") -> 4.800039 | I77: =Tabla3[[#This Row],[Valor Tran]]/(Tabla3[[#This Row],[DISTANCIA (km)]]*2) -> 6249.9492 | K77: 1 | L77: 60000 | M77: 60000 | N77: 717900 | O77: =Tabla3[[#This Row],[VLR. TOTAL FACT.]]-Tabla3[[#This Row],[VLR. TRANSPORTE]] -> 657900 | P77: 1 | Q77: efectivo
A78: 58415 | B78: 45974 | C78: sai | D78: Ismael Grao | E78: Parcelación El bosque | F78: 4 | G78: =_xlfn.XLOOKUP(Tabla3[[#This Row],[ID]],Tabla2[ID],Tabla2[Corregimiento],"NA") -> El Carmen | H78: =_xlfn.XLOOKUP(Tabla3[[#This Row],[LUGAR ENVÍO]],Tabla9[[Nombre ]],Tabla9[Distancia],"NA") -> 4.800039 | I78: =Tabla3[[#This Row],[Valor Tran]]/(Tabla3[[#This Row],[DISTANCIA (km)]]*2) -> 6249.9492 | K78: 1 | L78: 60000 | M78: =Tabla3[[#This Row],[VLR. TRANSPORTE]]/Tabla3[[#This Row],[Numero de Transportes]] -> 60000 | N78: 956000 | O78: =Tabla3[[#This Row],[VLR. TOTAL FACT.]]-Tabla3[[#This Row],[VLR. TRANSPORTE]] -> 896000 | P78: 1 | Q78: efectivo
A79: 48228 | B79: 45972 | C79: sai | D79: diego sarria | E79: Parcelación Ambichinte | F79: 2 | G79: =_xlfn.XLOOKUP(Tabla3[[#This Row],[ID]],Tabla2[ID],Tabla2[Corregimiento],"NA") -> Borrero Ayerbe | H79: =_xlfn.XLOOKUP(Tabla3[[#This Row],[LUGAR ENVÍO]],Tabla9[[Nombre ]],Tabla9[Distancia],"NA") -> 3.684 | I79: =Tabla3[[#This Row],[Valor Tran]]/(Tabla3[[#This Row],[DISTANCIA (km)]]*2) -> 5428.8817 | K79: 1 | L79: 40000 | M79: =Tabla3[[#This Row],[VLR. TRANSPORTE]]/Tabla3[[#This Row],[Numero de Transportes]] -> 40000 | N79: 181500 | O79: =Tabla3[[#This Row],[VLR. TOTAL FACT.]]-Tabla3[[#This Row],[VLR. TRANSPORTE]] -> 141500 | P79: 0 | Q79: tarjeta
A80: 59040 | B80: 45987 | C80: sai | D80: NA | E80: Panamericano | F80: 2 | G80: =_xlfn.XLOOKUP(Tabla3[[#This Row],[ID]],Tabla2[ID],Tabla2[Corregimiento],"NA") -> Borrero Ayerbe | H80: =_xlfn.XLOOKUP(Tabla3[[#This Row],[LUGAR ENVÍO]],Tabla9[[Nombre ]],Tabla9[Distancia],"NA") -> 1.127 | I80: =Tabla3[[#This Row],[Valor Tran]]/(Tabla3[[#This Row],[DISTANCIA (km)]]*2) -> 4436.5572 | K80: 1 | L80: 10000 | M80: =Tabla3[[#This Row],[VLR. TRANSPORTE]]/Tabla3[[#This Row],[Numero de Transportes]] -> 10000 | N80: 207000 | O80: =Tabla3[[#This Row],[VLR. TOTAL FACT.]]-Tabla3[[#This Row],[VLR. TRANSPORTE]] -> 197000 | P80: 0 | Q80: Transferencia
A81: 58796 | B81: 45987 | C81: manual | D81: angui rengifo | E81: Panamericano | F81: 2 | G81: =_xlfn.XLOOKUP(Tabla3[[#This Row],[ID]],Tabla2[ID],Tabla2[Corregimiento],"NA") -> Borrero Ayerbe | H81: =_xlfn.XLOOKUP(Tabla3[[#This Row],[LUGAR ENVÍO]],Tabla9[[Nombre ]],Tabla9[Distancia],"NA") -> 1.127 | I81: =Tabla3[[#This Row],[Valor Tran]]/(Tabla3[[#This Row],[DISTANCIA (km)]]*2) -> 8873.1145 | K81: 1 | L81: 20000 | M81: =Tabla3[[#This Row],[VLR. TRANSPORTE]]/Tabla3[[#This Row],[Numero de Transportes]] -> 20000 | N81: 2207000 | O81: =Tabla3[[#This Row],[VLR. TOTAL FACT.]]-Tabla3[[#This Row],[VLR. TRANSPORTE]] -> 2187000 | P81: 1 | Q81: transferencia
A82: 41501 | B82: 2025-11-25 | C82: manual | D82: Martha Rosero | E82: palo alto | F82: 6 | G82: =_xlfn.XLOOKUP(Tabla3[[#This Row],[ID]],Tabla2[ID],Tabla2[Corregimiento],"NA") -> El Limonar | H82: =_xlfn.XLOOKUP(Tabla3[[#This Row],[LUGAR ENVÍO]],Tabla9[[Nombre ]],Tabla9[Distancia],"NA") -> 4.476 | I82: =Tabla3[[#This Row],[Valor Tran]]/(Tabla3[[#This Row],[DISTANCIA (km)]]*2) -> 8378.0161 | K82: 3 | L82: 225000 | M82: 75000 | N82: 593900 | O82: =Tabla3[[#This Row],[VLR. TOTAL FACT.]]-Tabla3[[#This Row],[VLR. TRANSPORTE]] -> 368900 | P82: 1 | Q82: transferencia
A83: 48616 | B83: 45986 | C83: sai | D83: gladis jordan | E83: palo alto | F83: 6 | G83: =_xlfn.XLOOKUP(Tabla3[[#This Row],[ID]],Tabla2[ID],Tabla2[Corregimiento],"NA") -> El Limonar | H83: =_xlfn.XLOOKUP(Tabla3[[#This Row],[LUGAR ENVÍO]],Tabla9[[Nombre ]],Tabla9[Distancia],"NA") -> 4.476 | I83: =Tabla3[[#This Row],[Valor Tran]]/(Tabla3[[#This Row],[DISTANCIA (km)]]*2) -> 7819.4817 | K83: 1 | L83: 70000 | M83: =Tabla3[[#This Row],[VLR. TRANSPORTE]]/Tabla3[[#This Row],[Numero de Transportes]] -> 70000 | N83: 480300 | O83: =Tabla3[[#This Row],[VLR. TOTAL FACT.]]-Tabla3[[#This Row],[VLR. TRANSPORTE]] -> 410300 | P83: 1 | Q83: efectivo
A84: 50115 | B84: 2025-11-26 | C84: sai | D84: Sebastian Barragan | E84: palo alto | F84: 6 | G84: =_xlfn.XLOOKUP(Tabla3[[#This Row],[ID]],Tabla2[ID],Tabla2[Corregimiento],"NA") -> El Limonar | H84: =_xlfn.XLOOKUP(Tabla3[[#This Row],[LUGAR ENVÍO]],Tabla9[[Nombre ]],Tabla9[Distancia],"NA") -> 4.476 | I84: =Tabla3[[#This Row],[Valor Tran]]/(Tabla3[[#This Row],[DISTANCIA (km)]]*2) -> 7819.4817 | K84: 1 | L84: 70000 | M84: 70000 | N84: 557500 | O84: =Tabla3[[#This Row],[VLR. TOTAL FACT.]]-Tabla3[[#This Row],[VLR. TRANSPORTE]] -> 487500 | P84: 1 | Q84: transferencia
A85: 58809 | B85: 45993 | C85: sai | D85: Viviana Torres | E85: palo alto | F85: 6 | G85: =_xlfn.XLOOKUP(Tabla3[[#This Row],[ID]],Tabla2[ID],Tabla2[Corregimiento],"NA") -> El Limonar | H85: =_xlfn.XLOOKUP(Tabla3[[#This Row],[LUGAR ENVÍO]],Tabla9[[Nombre ]],Tabla9[Distancia],"NA") -> 4.476 | I85: =Tabla3[[#This Row],[Valor Tran]]/(Tabla3[[#This Row],[DISTANCIA (km)]]*2) -> 3351.2064 | K85: 3 | L85: 90000 | M85: =Tabla3[[#This Row],[VLR. TRANSPORTE]]/Tabla3[[#This Row],[Numero de Transportes]] -> 30000 | N85: 1382000 | O85: =Tabla3[[#This Row],[VLR. TOTAL FACT.]]-Tabla3[[#This Row],[VLR. TRANSPORTE]] -> 1292000 | P85: 1 | Q85: tarjeta
A86: 58609 | B86: 45995 | C86: sai | D86: diego sarria | E86: palo alto | F86: 6 | G86: =_xlfn.XLOOKUP(Tabla3[[#This Row],[ID]],Tabla2[ID],Tabla2[Corregimiento],"NA") -> El Limonar | H86: =_xlfn.XLOOKUP(Tabla3[[#This Row],[LUGAR ENVÍO]],Tabla9[[Nombre ]],Tabla9[Distancia],"NA") -> 4.476 | I86: =Tabla3[[#This Row],[Valor Tran]]/(Tabla3[[#This Row],[DISTANCIA (km)]]*2) -> 2234.1376 | K86: 1 | L86: 20000 | M86: =Tabla3[[#This Row],[VLR. TRANSPORTE]]/Tabla3[[#This Row],[Numero de Transportes]] -> 20000 | N86: 3259000 | O86: =Tabla3[[#This Row],[VLR. TOTAL FACT.]]-Tabla3[[#This Row],[VLR. TRANSPORTE]] -> 3239000 | P86: 1 | Q86: efectivo
A87: 57636 | B87: 45962 | C87: manual | D87: sergio bautista | E87: Pa la chingada | F87: 2 | G87: =_xlfn.XLOOKUP(Tabla3[[#This Row],[ID]],Tabla2[ID],Tabla2[Corregimiento],"NA") -> Borrero Ayerbe | H87: =_xlfn.XLOOKUP(Tabla3[[#This Row],[LUGAR ENVÍO]],Tabla9[[Nombre ]],Tabla9[Distancia],"NA") -> 1.31 | I87: =Tabla3[[#This Row],[Valor Tran]]/(Tabla3[[#This Row],[DISTANCIA (km)]]*2) -> 5725.1908 | K87: 1 | L87: 15000 | M87: =Tabla3[[#This Row],[VLR. TRANSPORTE]]/Tabla3[[#This Row],[Numero de Transportes]] -> 15000 | N87: 526000 | O87: =Tabla3[[#This Row],[VLR. TOTAL FACT.]]-Tabla3[[#This Row],[VLR. TRANSPORTE]] -> 511000 | P87: 0 | Q87: efectivo
A88: 58457 | B88: 45974 | C88: manual | D88: maria victoria | E88: Monteredondo | F88: 2 | G88: =_xlfn.XLOOKUP(Tabla3[[#This Row],[ID]],Tabla2[ID],Tabla2[Corregimiento],"NA") -> Borrero Ayerbe | H88: =_xlfn.XLOOKUP(Tabla3[[#This Row],[LUGAR ENVÍO]],Tabla9[[Nombre ]],Tabla9[Distancia],"NA") -> 0.428 | I88: =Tabla3[[#This Row],[Valor Tran]]/(Tabla3[[#This Row],[DISTANCIA (km)]]*2) -> 35046.729 | K88: 1 | L88: 30000 | M88: =Tabla3[[#This Row],[VLR. TRANSPORTE]]/Tabla3[[#This Row],[Numero de Transportes]] -> 30000 | N88: 210000 | O88: =Tabla3[[#This Row],[VLR. TOTAL FACT.]]-Tabla3[[#This Row],[VLR. TRANSPORTE]] -> 180000 | P88: 1 | Q88: efectivo
A89: 58466 | B89: 45974 | C89: manual | D89: robinson | E89: Monteredondo | F89: 2 | G89: =_xlfn.XLOOKUP(Tabla3[[#This Row],[ID]],Tabla2[ID],Tabla2[Corregimiento],"NA") -> Borrero Ayerbe | H89: =_xlfn.XLOOKUP(Tabla3[[#This Row],[LUGAR ENVÍO]],Tabla9[[Nombre ]],Tabla9[Distancia],"NA") -> 0.428 | I89: =Tabla3[[#This Row],[Valor Tran]]/(Tabla3[[#This Row],[DISTANCIA (km)]]*2) -> 17523.364 | K89: 1 | L89: 15000 | M89: =Tabla3[[#This Row],[VLR. TRANSPORTE]]/Tabla3[[#This Row],[Numero de Transportes]] -> 15000 | N89: 246000 | O89: =Tabla3[[#This Row],[VLR. TOTAL FACT.]]-Tabla3[[#This Row],[VLR. TRANSPORTE]] -> 231000 | P89: 0 | Q89: efectivo
A90: 38790 | B90: 2025-11-13 | C90: manual | D90: Elizabeth Perlaza | E90: Monteredondo | F90: 2 | G90: =_xlfn.XLOOKUP(Tabla3[[#This Row],[ID]],Tabla2[ID],Tabla2[Corregimiento],"NA") -> Borrero Ayerbe | H90: =_xlfn.XLOOKUP(Tabla3[[#This Row],[LUGAR ENVÍO]],Tabla9[[Nombre ]],Tabla9[Distancia],"NA") -> 0.428 | I90: =Tabla3[[#This Row],[Valor Tran]]/(Tabla3[[#This Row],[DISTANCIA (km)]]*2) -> 35046.729 | K90: 2 | L90: 60000 | M90: 30000 | N90: 307800 | O90: =Tabla3[[#This Row],[VLR. TOTAL FACT.]]-Tabla3[[#This Row],[VLR. TRANSPORTE]] -> 247800 | P90: 1 | Q90: efectivo
A91: 57842 | B91: 45971 | C91: manual | D91: alfonso ortega | E91: Monteredondo | F91: 2 | G91: =_xlfn.XLOOKUP(Tabla3[[#This Row],[ID]],Tabla2[ID],Tabla2[Corregimiento],"NA") -> Borrero Ayerbe | H91: =_xlfn.XLOOKUP(Tabla3[[#This Row],[LUGAR ENVÍO]],Tabla9[[Nombre ]],Tabla9[Distancia],"NA") -> 0.428 | I91: =Tabla3[[#This Row],[Valor Tran]]/(Tabla3[[#This Row],[DISTANCIA (km)]]*2) -> 17523.364 | K91: 1 | L91: 15000 | M91: =Tabla3[[#This Row],[VLR. TRANSPORTE]]/Tabla3[[#This Row],[Numero de Transportes]] -> 15000 | N91: 351000 | O91: =Tabla3[[#This Row],[VLR. TOTAL FACT.]]-Tabla3[[#This Row],[VLR. TRANSPORTE]] -> 336000 | P91: 0 | Q91: efectivo
A92: 46430 | B92: 45962 | C92: sai | D92: robinson | E92: Monteredondo | F92: 2 | G92: =_xlfn.XLOOKUP(Tabla3[[#This Row],[ID]],Tabla2[ID],Tabla2[Corregimiento],"NA") -> Borrero Ayerbe | H92: =_xlfn.XLOOKUP(Tabla3[[#This Row],[LUGAR ENVÍO]],Tabla9[[Nombre ]],Tabla9[Distancia],"NA") -> 0.428 | I92: =Tabla3[[#This Row],[Valor Tran]]/(Tabla3[[#This Row],[DISTANCIA (km)]]*2) -> 35046.729 | K92: 1 | L92: 30000 | M92: =Tabla3[[#This Row],[VLR. TRANSPORTE]]/Tabla3[[#This Row],[Numero de Transportes]] -> 30000 | N92: 768000 | O92: =Tabla3[[#This Row],[VLR. TOTAL FACT.]]-Tabla3[[#This Row],[VLR. TRANSPORTE]] -> 738000 | P92: 0 | Q92: transferencia
A93: 0 | B93: 45962 | C93: sai | D93: miriam gomez | E93: Mirador Bellavista | F93: 2 | G93: =_xlfn.XLOOKUP(Tabla3[[#This Row],[ID]],Tabla2[ID],Tabla2[Corregimiento],"NA") -> Borrero Ayerbe | H93: =_xlfn.XLOOKUP(Tabla3[[#This Row],[LUGAR ENVÍO]],Tabla9[[Nombre ]],Tabla9[Distancia],"NA") -> 1.201 | I93: =Tabla3[[#This Row],[Valor Tran]]/(Tabla3[[#This Row],[DISTANCIA (km)]]*2) -> 16652.789 | K93: 1 | L93: 40000 | M93: =Tabla3[[#This Row],[VLR. TRANSPORTE]]/Tabla3[[#This Row],[Numero de Transportes]] -> 40000 | N93: 369000 | O93: =Tabla3[[#This Row],[VLR. TOTAL FACT.]]-Tabla3[[#This Row],[VLR. TRANSPORTE]] -> 329000 | P93: 0 | Q93: efectivo
A94: 58326 | B94: 45986 | C94: sai | D94: Sebastian Barragan | E94: Mirador Bellavista | F94: 2 | G94: =_xlfn.XLOOKUP(Tabla3[[#This Row],[ID]],Tabla2[ID],Tabla2[Corregimiento],"NA") -> Borrero Ayerbe | H94: =_xlfn.XLOOKUP(Tabla3[[#This Row],[LUGAR ENVÍO]],Tabla9[[Nombre ]],Tabla9[Distancia],"NA") -> 1.201 | I94: =Tabla3[[#This Row],[Valor Tran]]/(Tabla3[[#This Row],[DISTANCIA (km)]]*2) -> 16652.789 | K94: 1 | L94: 40000 | M94: =Tabla3[[#This Row],[VLR. TRANSPORTE]]/Tabla3[[#This Row],[Numero de Transportes]] -> 40000 | N94: 436000 | O94: =Tabla3[[#This Row],[VLR. TOTAL FACT.]]-Tabla3[[#This Row],[VLR. TRANSPORTE]] -> 396000 | P94: 1 | Q94: efectivo
A95: 511 | B95: 45966 | C95: sai | D95: jose londoño | E95: Los bomberos | F95: 4 | G95: =_xlfn.XLOOKUP(Tabla3[[#This Row],[ID]],Tabla2[ID],Tabla2[Corregimiento],"NA") -> El Carmen | H95: =_xlfn.XLOOKUP(Tabla3[[#This Row],[LUGAR ENVÍO]],Tabla9[[Nombre ]],Tabla9[Distancia],"NA") -> 2.092 | I95: =Tabla3[[#This Row],[Valor Tran]]/(Tabla3[[#This Row],[DISTANCIA (km)]]*2) -> 3585.086 | K95: 1 | L95: 15000 | M95: =Tabla3[[#This Row],[VLR. TRANSPORTE]]/Tabla3[[#This Row],[Numero de Transportes]] -> 15000 | N95: 189000 | O95: =Tabla3[[#This Row],[VLR. TOTAL FACT.]]-Tabla3[[#This Row],[VLR. TRANSPORTE]] -> 174000 | P95: 0 | Q95: transferencia
A96: 59175 | B96: 45969 | C96: sai | D96: Oscar Osorio | E96: Los bomberos | F96: 4 | G96: =_xlfn.XLOOKUP(Tabla3[[#This Row],[ID]],Tabla2[ID],Tabla2[Corregimiento],"NA") -> El Carmen | H96: =_xlfn.XLOOKUP(Tabla3[[#This Row],[LUGAR ENVÍO]],Tabla9[[Nombre ]],Tabla9[Distancia],"NA") -> 2.092 | I96: =Tabla3[[#This Row],[Valor Tran]]/(Tabla3[[#This Row],[DISTANCIA (km)]]*2) -> 9560.2294 | K96: 1 | L96: 40000 | M96: =Tabla3[[#This Row],[VLR. TRANSPORTE]]/Tabla3[[#This Row],[Numero de Transportes]] -> 40000 | N96: 280000 | O96: =Tabla3[[#This Row],[VLR. TOTAL FACT.]]-Tabla3[[#This Row],[VLR. TRANSPORTE]] -> 240000 | P96: 0 | Q96: efectivo
A97: 58549 | B97: 45978 | C97: sai | D97: Sandra Viviana | E97: Los bomberos | F97: 4 | G97: =_xlfn.XLOOKUP(Tabla3[[#This Row],[ID]],Tabla2[ID],Tabla2[Corregimiento],"NA") -> El Carmen | H97: =_xlfn.XLOOKUP(Tabla3[[#This Row],[LUGAR ENVÍO]],Tabla9[[Nombre ]],Tabla9[Distancia],"NA") -> 2.092 | I97: =Tabla3[[#This Row],[Valor Tran]]/(Tabla3[[#This Row],[DISTANCIA (km)]]*2) -> 11950.287 | K97: 1 | L97: 50000 | M97: =Tabla3[[#This Row],[VLR. TRANSPORTE]]/Tabla3[[#This Row],[Numero de Transportes]] -> 50000 | N97: 1794500 | O97: =Tabla3[[#This Row],[VLR. TOTAL FACT.]]-Tabla3[[#This Row],[VLR. TRANSPORTE]] -> 1744500 | P97: 1 | Q97: tarjeta
A98: 58718 | B98: 46003 | C98: sai | D98: raul castillo | E98: Los bomberos | F98: 4 | G98: =_xlfn.XLOOKUP(Tabla3[[#This Row],[ID]],Tabla2[ID],Tabla2[Corregimiento],"NA") -> El Carmen | H98: =_xlfn.XLOOKUP(Tabla3[[#This Row],[LUGAR ENVÍO]],Tabla9[[Nombre ]],Tabla9[Distancia],"NA") -> 2.092 | I98: =Tabla3[[#This Row],[Valor Tran]]/(Tabla3[[#This Row],[DISTANCIA (km)]]*2) -> 7170.1721 | K98: 2 | L98: 60000 | M98: =Tabla3[[#This Row],[VLR. TRANSPORTE]]/Tabla3[[#This Row],[Numero de Transportes]] -> 30000 | N98: 3563000 | O98: =Tabla3[[#This Row],[VLR. TOTAL FACT.]]-Tabla3[[#This Row],[VLR. TRANSPORTE]] -> 3503000 | P98: 1 | Q98: transferencia
A99: 50413 | B99: 2025-11-21 | C99: sai | D99: Viviana Torres | E99: Los bomberos | F99: 4 | G99: =_xlfn.XLOOKUP(Tabla3[[#This Row],[ID]],Tabla2[ID],Tabla2[Corregimiento],"NA") -> El Carmen | H99: =_xlfn.XLOOKUP(Tabla3[[#This Row],[LUGAR ENVÍO]],Tabla9[[Nombre ]],Tabla9[Distancia],"NA") -> 2.092 | I99: =Tabla3[[#This Row],[Valor Tran]]/(Tabla3[[#This Row],[DISTANCIA (km)]]*2) -> 13145.315 | K99: 1 | L99: 55000 | M99: 55000 | N99: 4103000 | O99: =Tabla3[[#This Row],[VLR. TOTAL FACT.]]-Tabla3[[#This Row],[VLR. TRANSPORTE]] -> 4048000 | P99: 1 | Q99: efectivo
A100: 30710 | B100: 45986 | C100: manual | D100: oscar osorio | E100: Los bomberos | F100: 4 | G100: =_xlfn.XLOOKUP(Tabla3[[#This Row],[ID]],Tabla2[ID],Tabla2[Corregimiento],"NA") -> El Carmen | H100: =_xlfn.XLOOKUP(Tabla3[[#This Row],[LUGAR ENVÍO]],Tabla9[[Nombre ]],Tabla9[Distancia],"NA") -> 2.092 | I100: =Tabla3[[#This Row],[Valor Tran]]/(Tabla3[[#This Row],[DISTANCIA (km)]]*2) -> 4780.1147 | K100: 2 | L100: 40000 | M100: =Tabla3[[#This Row],[VLR. TRANSPORTE]]/Tabla3[[#This Row],[Numero de Transportes]] -> 20000 | N100: 5045600 | O100: =Tabla3[[#This Row],[VLR. TOTAL FACT.]]-Tabla3[[#This Row],[VLR. TRANSPORTE]] -> 5005600 | P100: 1 | Q100: efectivo
...

Sheet Hoja1
A1: Nombre | B1: Numero de envios | C1: Distancia
A2: El Coscorron | B2: =COUNTIF(Tabla3[LUGAR ENVÍO],Tabla9[[#This Row],[Nombre ]]) -> 11 | C2: =Distancias!EA61 -> 2.65
A3: Altos del Carmen | B3: =COUNTIF(Tabla3[LUGAR ENVÍO],Tabla9[[#This Row],[Nombre ]]) -> 9 | C3: =Distancias!DO118 -> 5.464 | F3: Ubicación | G3: Envios | H3: Total valor del transporte | I3: Valor promedio de transporte | J3: Total de venta | K3: G/P promedio Margen
A4: Pirineos | B4: =COUNTIF(Tabla3[LUGAR ENVÍO],Tabla9[[#This Row],[Nombre ]]) -> 9 | C4: =Distancias!DC47 -> 2.66665 | F4: El Diviso | G4: =COUNTIF(Tabla3[LUGAR ENVÍO],Tabla11[[#This Row],[Ubicación]]) -> 6 | H4: =SUMIF(Tabla3[LUGAR ENVÍO],Tabla11[[#This Row],[Ubicación]],Tabla3[VLR. TRANSPORTE]) -> 360000 | I4: =AVERAGEIF(Tabla3[LUGAR ENVÍO],Tabla11[[#This Row],[Ubicación]],Tabla3[VLR. TRANSPORTE]) -> 60000 | J4: =SUMIF(Tabla3[LUGAR ENVÍO],Tabla11[[#This Row],[Ubicación]],Tabla3[VLR. TOTAL FACT.]) -> 16869200 | K4: =AVERAGEIF(Tabla8[Lugar],Tabla11[[#This Row],[Ubicación]],Tabla8[Perdida o ganancia de margen]) -> -0.1100685
A5: KM 34 | B5: =COUNTIF(Tabla3[LUGAR ENVÍO],Tabla9[[#This Row],[Nombre ]]) -> 8 | C5: =Distancias!DG63 -> 4.316 | F5: Tocota | G5: =COUNTIF(Tabla3[LUGAR ENVÍO],Tabla11[[#This Row],[Ubicación]]) -> 5 | H5: =SUMIF(Tabla3[LUGAR ENVÍO],Tabla11[[#This Row],[Ubicación]],Tabla3[VLR. TRANSPORTE]) -> 290000 | I5: =AVERAGEIF(Tabla3[LUGAR ENVÍO],Tabla11[[#This Row],[Ubicación]],Tabla3[VLR. TRANSPORTE]) -> 58000 | J5: =SUMIF(Tabla3[LUGAR ENVÍO],Tabla11[[#This Row],[Ubicación]],Tabla3[VLR. TOTAL FACT.]) -> 4672500 | K5: =AVERAGEIF(Tabla8[Lugar],Tabla11[[#This Row],[Ubicación]],Tabla8[Perdida o ganancia de margen]) -> -0.15768468
A6: San Jose del Salado | B6: =COUNTIF(Tabla3[LUGAR ENVÍO],Tabla9[[#This Row],[Nombre ]]) -> 7 | C6: 13.07
A7: San Miguel | B7: =COUNTIF(Tabla3[LUGAR ENVÍO],Tabla9[[#This Row],[Nombre ]]) -> 7 | C7: =Distancias!CI44 -> 2.269 | F7: Ubicación | G7: Envios | H7: Total valor del transporte | I7: Valor promedio de transporte | J7: Total de venta | K7: G/P promedio Margen
A8: Tortolas | B8: =COUNTIF(Tabla3[LUGAR ENVÍO],Tabla9[[#This Row],[Nombre ]]) -> 7 | C8: =Distancias!BO92 -> 5.757 | F8: San Jose del Salado | G8: =COUNTIF(Tabla3[LUGAR ENVÍO],Tabla1113[[#This Row],[Ubicación]]) -> 7 | H8: =SUMIF(Tabla3[LUGAR ENVÍO],Tabla1113[[#This Row],[Ubicación]],Tabla3[VLR. TRANSPORTE]) -> 500000 | I8: =AVERAGEIF(Tabla3[LUGAR ENVÍO],Tabla1113[[#This Row],[Ubicación]],Tabla3[VLR. TRANSPORTE]) -> 71428.571 | J8: =SUMIF(Tabla3[LUGAR ENVÍO],Tabla1113[[#This Row],[Ubicación]],Tabla3[VLR. TOTAL FACT.]) -> 6594300 | K8: =AVERAGEIF(Tabla8[Lugar],Tabla1113[[#This Row],[Ubicación]],Tabla8[Perdida o ganancia de margen]) -> -0.21904907
A9: Casa verde | B9: =COUNTIF(Tabla3[LUGAR ENVÍO],Tabla9[[#This Row],[Nombre ]]) -> 7 | C9: =Distancias!HG57 -> 4.626 | M9: Ubicación | N9: Envios | O9: Total valor del transporte | P9: Valor promedio de transporte | Q9: Total de venta | R9: G/P promedio Margen
A10: El Carmelo | B10: =COUNTIF(Tabla3[LUGAR ENVÍO],Tabla9[[#This Row],[Nombre ]]) -> 6 | C10: =Distancias!BK97 -> 6.124 | F10: Ubicación | G10: Envios | H10: Total valor del transporte | I10: Valor promedio de transporte | J10: Total de venta | K10: G/P promedio Margen | M10: El palmar | N10: =COUNTIF(Tabla3[LUGAR ENVÍO],Tabla1116[[#This Row],[Ubicación]]) -> 3 | O10: =SUMIF(Tabla3[LUGAR ENVÍO],Tabla1116[[#This Row],[Ubicación]],Tabla3[VLR. TRANSPORTE]) -> 120000 | P10: =AVERAGEIF(Tabla3[LUGAR ENVÍO],Tabla1116[[#This Row],[Ubicación]],Tabla3[VLR. TRANSPORTE]) -> 40000 | Q10: =SUMIF(Tabla3[LUGAR ENVÍO],Tabla1116[[#This Row],[Ubicación]],Tabla3[VLR. TOTAL FACT.]) -> 3082200 | R10: =AVERAGEIF(Tabla8[Lugar],Tabla1116[[#This Row],[Ubicación]],Tabla8[Perdida o ganancia de margen]) -> -0.38011721
A11: El diviso | B11: =COUNTIF(Tabla3[LUGAR ENVÍO],Tabla9[[#This Row],[Nombre ]]) -> 6 | C11: =Distancias!CA111 -> 8.471 | F11: KM 34 | G11: =COUNTIF(Tabla3[LUGAR ENVÍO],Tabla111314[[#This Row],[Ubicación]]) -> 8 | H11: =SUMIF(Tabla3[LUGAR ENVÍO],Tabla111314[[#This Row],[Ubicación]],Tabla3[VLR. TRANSPORTE]) -> 390000 | I11: =AVERAGEIF(Tabla3[LUGAR ENVÍO],Tabla111314[[#This Row],[Ubicación]],Tabla3[VLR. TRANSPORTE]) -> 48750 | J11: =SUMIF(Tabla3[LUGAR ENVÍO],Tabla111314[[#This Row],[Ubicación]],Tabla3[VLR. TOTAL FACT.]) -> 7742400 | K11: =AVERAGEIF(Tabla8[Lugar],Tabla111314[[#This Row],[Ubicación]],Tabla8[Perdida o ganancia de margen]) -> -0.5855157 | M11: Tocota | N11: =COUNTIF(Tabla3[LUGAR ENVÍO],Tabla1116[[#This Row],[Ubicación]]) -> 0 | O11: =SUMIF(Tabla3[LUGAR ENVÍO],Tabla1116[[#This Row],[Ubicación]],Tabla3[VLR. TRANSPORTE]) -> 0 | P11: =AVERAGEIF(Tabla3[LUGAR ENVÍO],Tabla1116[[#This Row],[Ubicación]],Tabla3[VLR. TRANSPORTE]) -> #DIV/0! | Q11: =SUMIF(Tabla3[LUGAR ENVÍO],Tabla1116[[#This Row],[Ubicación]],Tabla3[VLR. TOTAL FACT.]) -> 0 | R11: =AVERAGEIF(Tabla8[Lugar],Tabla1116[[#This Row],[Ubicación]],Tabla8[Perdida o ganancia de margen]) -> #DIV/0!
A12: Los bomberos | B12: =COUNTIF(Tabla3[LUGAR ENVÍO],Tabla9[[#This Row],[Nombre ]]) -> 6 | C12: =Distancias!AY49 -> 2.092 | F12: Palo Alto | G12: =COUNTIF(Tabla3[LUGAR ENVÍO],Tabla111314[[#This Row],[Ubicación]]) -> 5 | H12: =SUMIF(Tabla3[LUGAR ENVÍO],Tabla111314[[#This Row],[Ubicación]],Tabla3[VLR. TRANSPORTE]) -> 475000 | I12: =AVERAGEIF(Tabla3[LUGAR ENVÍO],Tabla111314[[#This Row],[Ubicación]],Tabla3[VLR. TRANSPORTE]) -> 95000 | J12: =SUMIF(Tabla3[LUGAR ENVÍO],Tabla111314[[#This Row],[Ubicación]],Tabla3[VLR. TOTAL FACT.]) -> 6272700 | K12: =AVERAGEIF(Tabla8[Lugar],Tabla111314[[#This Row],[Ubicación]],Tabla8[Perdida o ganancia de margen]) -> 0.18991448
A13: Villa del toro | B13: =COUNTIF(Tabla3[LUGAR ENVÍO],Tabla9[[#This Row],[Nombre ]]) -> 6 | C13: =Distancias!GY32 -> 2.279762 | F13: San Fernando | G13: =COUNTIF(Tabla3[LUGAR ENVÍO],Tabla111314[[#This Row],[Ubicación]]) -> 3 | H13: =SUMIF(Tabla3[LUGAR ENVÍO],Tabla111314[[#This Row],[Ubicación]],Tabla3[VLR. TRANSPORTE]) -> 200000 | I13: =AVERAGEIF(Tabla3[LUGAR ENVÍO],Tabla111314[[#This Row],[Ubicación]],Tabla3[VLR. TRANSPORTE]) -> 66666.667 | J13: =SUMIF(Tabla3[LUGAR ENVÍO],Tabla111314[[#This Row],[Ubicación]],Tabla3[VLR. TOTAL FACT.]) -> 2582600 | K13: =AVERAGEIF(Tabla8[Lugar],Tabla111314[[#This Row],[Ubicación]],Tabla8[Perdida o ganancia de margen]) -> 0.032808392 | M13: Ubicación | N13: Envios | O13: Total valor del transporte | P13: Valor promedio de transporte | Q13: Total de venta | R13: G/P promedio Margen
A14: Carmen | B14: =COUNTIF(Tabla3[LUGAR ENVÍO],Tabla9[[#This Row],[Nombre ]]) -> 5 | C14: =Distancias!DS145 -> 4.201 | F14: Villahermosa | G14: =COUNTIF(Tabla3[LUGAR ENVÍO],Tabla111314[[#This Row],[Ubicación]]) -> 2 | H14: =SUMIF(Tabla3[LUGAR ENVÍO],Tabla111314[[#This Row],[Ubicación]],Tabla3[VLR. TRANSPORTE]) -> 250000 | I14: =AVERAGEIF(Tabla3[LUGAR ENVÍO],Tabla111314[[#This Row],[Ubicación]],Tabla3[VLR. TRANSPORTE]) -> 125000 | J14: =SUMIF(Tabla3[LUGAR ENVÍO],Tabla111314[[#This Row],[Ubicación]],Tabla3[VLR. TOTAL FACT.]) -> 5111500 | K14: =AVERAGEIF(Tabla8[Lugar],Tabla111314[[#This Row],[Ubicación]],Tabla8[Perdida o ganancia de margen]) -> 0.15336298 | M14: El Queremal | N14: =COUNTIF(Tabla3[LUGAR ENVÍO],Tabla111617[[#This Row],[Ubicación]]) -> 4 | O14: =SUMIF(Tabla3[LUGAR ENVÍO],Tabla111617[[#This Row],[Ubicación]],Tabla3[VLR. TRANSPORTE]) -> 221000 | P14: =AVERAGEIF(Tabla3[LUGAR ENVÍO],Tabla111617[[#This Row],[Ubicación]],Tabla3[VLR. TRANSPORTE]) -> 55250 | Q14: =SUMIF(Tabla3[LUGAR ENVÍO],Tabla111617[[#This Row],[Ubicación]],Tabla3[VLR. TOTAL FACT.]) -> 11041800 | R14: =AVERAGEIF(Tabla8[Lugar],Tabla111617[[#This Row],[Ubicación]],Tabla8[Perdida o ganancia de margen]) -> -0.074418547
A15: El parque | B15: =COUNTIF(Tabla3[LUGAR ENVÍO],Tabla9[[#This Row],[Nombre ]]) -> 5 | C15: =Distancias!GM17 -> 0.836 | F15: KM 40 | G15: =COUNTIF(Tabla3[LUGAR ENVÍO],Tabla111314[[#This Row],[Ubicación]]) -> 2 | H15: =SUMIF(Tabla3[LUGAR ENVÍO],Tabla111314[[#This Row],[Ubicación]],Tabla3[VLR. TRANSPORTE]) -> 60000 | I15: =AVERAGEIF(Tabla3[LUGAR ENVÍO],Tabla111314[[#This Row],[Ubicación]],Tabla3[VLR. TRANSPORTE]) -> 30000 | J15: =SUMIF(Tabla3[LUGAR ENVÍO],Tabla111314[[#This Row],[Ubicación]],Tabla3[VLR. TOTAL FACT.]) -> 1765600 | K15: =AVERAGEIF(Tabla8[Lugar],Tabla111314[[#This Row],[Ubicación]],Tabla8[Perdida o ganancia de margen]) -> -0.33721545
A16: La Zulia 2 | B16: =COUNTIF(Tabla3[LUGAR ENVÍO],Tabla9[[#This Row],[Nombre ]]) -> 5 | C16: =Distancias!W24 -> 1.248 | F16: El chilcal | G16: =COUNTIF(Tabla3[LUGAR ENVÍO],Tabla111314[[#This Row],[Ubicación]]) -> 2 | H16: =SUMIF(Tabla3[LUGAR ENVÍO],Tabla111314[[#This Row],[Ubicación]],Tabla3[VLR. TRANSPORTE]) -> 150000 | I16: =AVERAGEIF(Tabla3[LUGAR ENVÍO],Tabla111314[[#This Row],[Ubicación]],Tabla3[VLR. TRANSPORTE]) -> 75000 | J16: =SUMIF(Tabla3[LUGAR ENVÍO],Tabla111314[[#This Row],[Ubicación]],Tabla3[VLR. TOTAL FACT.]) -> 1117000 | K16: =AVERAGEIF(Tabla8[Lugar],Tabla111314[[#This Row],[Ubicación]],Tabla8[Perdida o ganancia de margen]) -> -0.10422192 | M16: Ubicación | N16: Envios | O16: Total valor del transporte | P16: Valor promedio de transporte | Q16: Total de venta | R16: G/P promedio Margen
A17: Las villas del carmen | B17: =COUNTIF(Tabla3[LUGAR ENVÍO],Tabla9[[#This Row],[Nombre ]]) -> 5 | C17: =Distancias!EU51 -> 3.507 | F17: KM 37 | G17: =COUNTIF(Tabla3[LUGAR ENVÍO],Tabla111314[[#This Row],[Ubicación]]) -> 1 | H17: =SUMIF(Tabla3[LUGAR ENVÍO],Tabla111314[[#This Row],[Ubicación]],Tabla3[VLR. TRANSPORTE]) -> 140000 | I17: =AVERAGEIF(Tabla3[LUGAR ENVÍO],Tabla111314[[#This Row],[Ubicación]],Tabla3[VLR. TRANSPORTE]) -> 140000 | J17: =SUMIF(Tabla3[LUGAR ENVÍO],Tabla111314[[#This Row],[Ubicación]],Tabla3[VLR. TOTAL FACT.]) -> 1784000 | K17: =AVERAGEIF(Tabla8[Lugar],Tabla111314[[#This Row],[Ubicación]],Tabla8[Perdida o ganancia de margen]) -> 0.06863241 | M17: san miguel | N17: =COUNTIF(Tabla3[LUGAR ENVÍO],Tabla11161718[[#This Row],[Ubicación]]) -> 7 | O17: =SUMIF(Tabla3[LUGAR ENVÍO],Tabla11161718[[#This Row],[Ubicación]],Tabla3[VLR. TRANSPORTE]) -> 460000 | P17: =AVERAGEIF(Tabla3[LUGAR ENVÍO],Tabla11161718[[#This Row],[Ubicación]],Tabla3[VLR. TRANSPORTE]) -> 65714.286 | Q17: =SUMIF(Tabla3[LUGAR ENVÍO],Tabla11161718[[#This Row],[Ubicación]],Tabla3[VLR. TOTAL FACT.]) -> 5698200 | R17: =AVERAGEIF(Tabla8[Lugar],Tabla11161718[[#This Row],[Ubicación]],Tabla8[Perdida o ganancia de margen]) -> 0.22630925
A18: Monteredondo | B18: =COUNTIF(Tabla3[LUGAR ENVÍO],Tabla9[[#This Row],[Nombre ]]) -> 5 | C18: =Distancias!C13 -> 0.428 | M18: Casa verde | N18: =COUNTIF(Tabla3[LUGAR ENVÍO],Tabla11161718[[#This Row],[Ubicación]]) -> 7 | O18: =SUMIF(Tabla3[LUGAR ENVÍO],Tabla11161718[[#This Row],[Ubicación]],Tabla3[VLR. TRANSPORTE]) -> 470000 | P18: =AVERAGEIF(Tabla3[LUGAR ENVÍO],Tabla11161718[[#This Row],[Ubicación]],Tabla3[VLR. TRANSPORTE]) -> 67142.857 | Q18: =SUMIF(Tabla3[LUGAR ENVÍO],Tabla11161718[[#This Row],[Ubicación]],Tabla3[VLR. TOTAL FACT.]) -> 3215600 | R18: =AVERAGEIF(Tabla8[Lugar],Tabla11161718[[#This Row],[Ubicación]],Tabla8[Perdida o ganancia de margen]) -> 0.17899273
A19: Palo alto | B19: =COUNTIF(Tabla3[LUGAR ENVÍO],Tabla9[[#This Row],[Nombre ]]) -> 5 | C19: =Distancias!EM92 -> 4.476 | F19: Ubicación | G19: Envios | H19: Total valor del transporte | I19: Valor promedio de transporte | J19: Total de venta | K19: G/P promedio Margen | M19: Salida al carmen | N19: =COUNTIF(Tabla3[LUGAR ENVÍO],Tabla11161718[[#This Row],[Ubicación]]) -> 5 | O19: =SUMIF(Tabla3[LUGAR ENVÍO],Tabla11161718[[#This Row],[Ubicación]],Tabla3[VLR. TRANSPORTE]) -> 140000 | P19: =AVERAGEIF(Tabla3[LUGAR ENVÍO],Tabla11161718[[#This Row],[Ubicación]],Tabla3[VLR. TRANSPORTE]) -> 28000 | Q19: =SUMIF(Tabla3[LUGAR ENVÍO],Tabla11161718[[#This Row],[Ubicación]],Tabla3[VLR. TOTAL FACT.]) -> 7004200 | R19: =AVERAGEIF(Tabla8[Lugar],Tabla11161718[[#This Row],[Ubicación]],Tabla8[Perdida o ganancia de margen]) -> -0.12106898
A20: Parcelacion la Cristalina | B20: =COUNTIF(Tabla3[LUGAR ENVÍO],Tabla9[[#This Row],[Nombre ]]) -> 5 | C20: =Distancias!EE79 -> 2.71 | F20: El Coscorron | G20: =COUNTIF(Tabla3[LUGAR ENVÍO],Tabla11131415[[#This Row],[Ubicación]]) -> 11 | H20: =SUMIF(Tabla3[LUGAR ENVÍO],Tabla11131415[[#This Row],[Ubicación]],Tabla3[VLR. TRANSPORTE]) -> 985000 | I20: =AVERAGEIF(Tabla3[LUGAR ENVÍO],Tabla11131415[[#This Row],[Ubicación]],Tabla3[VLR. TRANSPORTE]) -> 89545.455 | J20: =SUMIF(Tabla3[LUGAR ENVÍO],Tabla11131415[[#This Row],[Ubicación]],Tabla3[VLR. TOTAL FACT.]) -> 14554100 | K20: =AVERAGEIF(Tabla8[Lugar],Tabla11131415[[#This Row],[Ubicación]],Tabla8[Perdida o ganancia de margen]) -> 0.16313549 | M20: Monteredondo | N20: =COUNTIF(Tabla3[LUGAR ENVÍO],Tabla11161718[[#This Row],[Ubicación]]) -> 5 | O20: =SUMIF(Tabla3[LUGAR ENVÍO],Tabla11161718[[#This Row],[Ubicación]],Tabla3[VLR. TRANSPORTE]) -> 150000 | P20: =AVERAGEIF(Tabla3[LUGAR ENVÍO],Tabla11161718[[#This Row],[Ubicación]],Tabla3[VLR. TRANSPORTE]) -> 30000 | Q20: =SUMIF(Tabla3[LUGAR ENVÍO],Tabla11161718[[#This Row],[Ubicación]],Tabla3[VLR. TOTAL FACT.]) -> 1882800 | R20: =AVERAGEIF(Tabla8[Lugar],Tabla11161718[[#This Row],[Ubicación]],Tabla8[Perdida o ganancia de margen]) -> -0.37490082
A21: Parcelaón las palmas | B21: =COUNTIF(Tabla3[LUGAR ENVÍO],Tabla9[[#This Row],[Nombre ]]) -> 5 | C21: =Distancias!EY52 -> 2.641 | F21: Pirineos | G21: =COUNTIF(Tabla3[LUGAR ENVÍO],Tabla11131415[[#This Row],[Ubicación]]) -> 9 | H21: =SUMIF(Tabla3[LUGAR ENVÍO],Tabla11131415[[#This Row],[Ubicación]],Tabla3[VLR. TRANSPORTE]) -> 495000 | I21: =AVERAGEIF(Tabla3[LUGAR ENVÍO],Tabla11131415[[#This Row],[Ubicación]],Tabla3[VLR. TRANSPORTE]) -> 55000 | J21: =SUMIF(Tabla3[LUGAR ENVÍO],Tabla11131415[[#This Row],[Ubicación]],Tabla3[VLR. TOTAL FACT.]) -> 10085100 | K21: =AVERAGEIF(Tabla8[Lugar],Tabla11131415[[#This Row],[Ubicación]],Tabla8[Perdida o ganancia de margen]) -> -0.070990936 | M21: La Zulia 2 | N21: =COUNTIF(Tabla3[LUGAR ENVÍO],Tabla11161718[[#This Row],[Ubicación]]) -> 5 | O21: =SUMIF(Tabla3[LUGAR ENVÍO],Tabla11161718[[#This Row],[Ubicación]],Tabla3[VLR. TRANSPORTE]) -> 165000 | P21: =AVERAGEIF(Tabla3[LUGAR ENVÍO],Tabla11161718[[#This Row],[Ubicación]],Tabla3[VLR. TRANSPORTE]) -> 33000 | Q21: =SUMIF(Tabla3[LUGAR ENVÍO],Tabla11161718[[#This Row],[Ubicación]],Tabla3[VLR. TOTAL FACT.]) -> 2401300 | R21: =AVERAGEIF(Tabla8[Lugar],Tabla11161718[[#This Row],[Ubicación]],Tabla8[Perdida o ganancia de margen]) -> -0.15998145
A22: Tocota | B22: =COUNTIF(Tabla3[LUGAR ENVÍO],Tabla9[[#This Row],[Nombre ]]) -> 5 | C22: =Distancias!CE118 -> 9.438 | F22: Altos del Carmen | G22: =COUNTIF(Tabla3[LUGAR ENVÍO],Tabla11131415[[#This Row],[Ubicación]]) -> 9 | H22: =SUMIF(Tabla3[LUGAR ENVÍO],Tabla11131415[[#This Row],[Ubicación]],Tabla3[VLR. TRANSPORTE]) -> 460000 | I22: =AVERAGEIF(Tabla3[LUGAR ENVÍO],Tabla11131415[[#This Row],[Ubicación]],Tabla3[VLR. TRANSPORTE]) -> 51111.111 | J22: =SUMIF(Tabla3[LUGAR ENVÍO],Tabla11131415[[#This Row],[Ubicación]],Tabla3[VLR. TOTAL FACT.]) -> 6078300 | K22: =AVERAGEIF(Tabla8[Lugar],Tabla11131415[[#This Row],[Ubicación]],Tabla8[Perdida o ganancia de margen]) -> -0.074871141 | M22: La florida | N22: =COUNTIF(Tabla3[LUGAR ENVÍO],Tabla11161718[[#This Row],[Ubicación]]) -> 5 | O22: =SUMIF(Tabla3[LUGAR ENVÍO],Tabla11161718[[#This Row],[Ubicación]],Tabla3[VLR. TRANSPORTE]) -> 340000 | P22: =AVERAGEIF(Tabla3[LUGAR ENVÍO],Tabla11161718[[#This Row],[Ubicación]],Tabla3[VLR. TRANSPORTE]) -> 68000 | Q22: =SUMIF(Tabla3[LUGAR ENVÍO],Tabla11161718[[#This Row],[Ubicación]],Tabla3[VLR. TOTAL FACT.]) -> 7209650 | R22: =AVERAGEIF(Tabla8[Lugar],Tabla11161718[[#This Row],[Ubicación]],Tabla8[Perdida o ganancia de margen]) -> -0.11182207
A23: Salida al carmen | B23: =COUNTIF(Tabla3[LUGAR ENVÍO],Tabla9[[#This Row],[Nombre ]]) -> 5 | C23: =Distancias!GQ41 -> 2.329 | F23: Tortolas | G23: =COUNTIF(Tabla3[LUGAR ENVÍO],Tabla11131415[[#This Row],[Ubicación]]) -> 7 | H23: =SUMIF(Tabla3[LUGAR ENVÍO],Tabla11131415[[#This Row],[Ubicación]],Tabla3[VLR. TRANSPORTE]) -> 580000 | I23: =AVERAGEIF(Tabla3[LUGAR ENVÍO],Tabla11131415[[#This Row],[Ubicación]],Tabla3[VLR. TRANSPORTE]) -> 82857.143 | J23: =SUMIF(Tabla3[LUGAR ENVÍO],Tabla11131415[[#This Row],[Ubicación]],Tabla3[VLR. TOTAL FACT.]) -> 6919800 | K23: =AVERAGEIF(Tabla8[Lugar],Tabla11131415[[#This Row],[Ubicación]],Tabla8[Perdida o ganancia de margen]) -> -0.051297386 | M23: El parque | N23: =COUNTIF(Tabla3[LUGAR ENVÍO],Tabla11161718[[#This Row],[Ubicación]]) -> 5 | O23: =SUMIF(Tabla3[LUGAR ENVÍO],Tabla11161718[[#This Row],[Ubicación]],Tabla3[VLR. TRANSPORTE]) -> 180000 | P23: =AVERAGEIF(Tabla3[LUGAR ENVÍO],Tabla11161718[[#This Row],[Ubicación]],Tabla3[VLR. TRANSPORTE]) -> 36000 | Q23: =SUMIF(Tabla3[LUGAR ENVÍO],Tabla11161718[[#This Row],[Ubicación]],Tabla3[VLR. TOTAL FACT.]) -> 1639500 | R23: =AVERAGEIF(Tabla8[Lugar],Tabla11161718[[#This Row],[Ubicación]],Tabla8[Perdida o ganancia de margen]) -> -0.45704625
A24: La florida | B24: =COUNTIF(Tabla3[LUGAR ENVÍO],Tabla9[[#This Row],[Nombre ]]) -> 5 | C24: =Distancias!HC28 -> 1.466927 | F24: El Carmelo | G24: =COUNTIF(Tabla3[LUGAR ENVÍO],Tabla11131415[[#This Row],[Ubicación]]) -> 6 | H24: =SUMIF(Tabla3[LUGAR ENVÍO],Tabla11131415[[#This Row],[Ubicación]],Tabla3[VLR. TRANSPORTE]) -> 270000 | I24: =AVERAGEIF(Tabla3[LUGAR ENVÍO],Tabla11131415[[#This Row],[Ubicación]],Tabla3[VLR. TRANSPORTE]) -> 45000 | J24: =SUMIF(Tabla3[LUGAR ENVÍO],Tabla11131415[[#This Row],[Ubicación]],Tabla3[VLR. TOTAL FACT.]) -> 7374800 | K24: =AVERAGEIF(Tabla8[Lugar],Tabla11131415[[#This Row],[Ubicación]],Tabla8[Perdida o ganancia de margen]) -> -0.049634589 | M24: La Zulia 3 | N24: =COUNTIF(Tabla3[LUGAR ENVÍO],Tabla11161718[[#This Row],[Ubicación]]) -> 4 | O24: =SUMIF(Tabla3[LUGAR ENVÍO],Tabla11161718[[#This Row],[Ubicación]],Tabla3[VLR. TRANSPORTE]) -> 145000 | P24: =AVERAGEIF(Tabla3[LUGAR ENVÍO],Tabla11161718[[#This Row],[Ubicación]],Tabla3[VLR. TRANSPORTE]) -> 36250 | Q24: =SUMIF(Tabla3[LUGAR ENVÍO],Tabla11161718[[#This Row],[Ubicación]],Tabla3[VLR. TOTAL FACT.]) -> 3183400 | R24: =AVERAGEIF(Tabla8[Lugar],Tabla11161718[[#This Row],[Ubicación]],Tabla8[Perdida o ganancia de margen]) -> -0.20243558
A25: Agua Sucia | B25: =COUNTIF(Tabla3[LUGAR ENVÍO],Tabla9[[#This Row],[Nombre ]]) -> 4 | C25: =Distancias!AU32 -> 1.343 | F25: Villa del toro | G25: =COUNTIF(Tabla3[LUGAR ENVÍO],Tabla11131415[[#This Row],[Ubicación]]) -> 6 | H25: =SUMIF(Tabla3[LUGAR ENVÍO],Tabla11131415[[#This Row],[Ubicación]],Tabla3[VLR. TRANSPORTE]) -> 245000 | I25: =AVERAGEIF(Tabla3[LUGAR ENVÍO],Tabla11131415[[#This Row],[Ubicación]],Tabla3[VLR. TRANSPORTE]) -> 40833.333 | J25: =SUMIF(Tabla3[LUGAR ENVÍO],Tabla11131415[[#This Row],[Ubicación]],Tabla3[VLR. TOTAL FACT.]) -> 2634000 | K25: =AVERAGEIF(Tabla8[Lugar],Tabla11131415[[#This Row],[Ubicación]],Tabla8[Perdida o ganancia de margen]) -> -0.07941444 | M25: Km 28 | N25: =COUNTIF(Tabla3[LUGAR ENVÍO],Tabla11161718[[#This Row],[Ubicación]]) -> 4 | O25: =SUMIF(Tabla3[LUGAR ENVÍO],Tabla11161718[[#This Row],[Ubicación]],Tabla3[VLR. TRANSPORTE]) -> 235000 | P25: =AVERAGEIF(Tabla3[LUGAR ENVÍO],Tabla11161718[[#This Row],[Ubicación]],Tabla3[VLR. TRANSPORTE]) -> 58750 | Q25: =SUMIF(Tabla3[LUGAR ENVÍO],Tabla11161718[[#This Row],[Ubicación]],Tabla3[VLR. TOTAL FACT.]) -> 4996600 | R25: =AVERAGEIF(Tabla8[Lugar],Tabla11161718[[#This Row],[Ubicación]],Tabla8[Perdida o ganancia de margen]) -> -0.11504817
A26: Altos de las Tortolas | B26: =COUNTIF(Tabla3[LUGAR ENVÍO],Tabla9[[#This Row],[Nombre ]]) -> 4 | C26: =Distancias!BS118 -> 6.724 | F26: Los bomberos | G26: =COUNTIF(Tabla3[LUGAR ENVÍO],Tabla11131415[[#This Row],[Ubicación]]) -> 6 | H26: =SUMIF(Tabla3[LUGAR ENVÍO],Tabla11131415[[#This Row],[Ubicación]],Tabla3[VLR. TRANSPORTE]) -> 260000 | I26: =AVERAGEIF(Tabla3[LUGAR ENVÍO],Tabla11131415[[#This Row],[Ubicación]],Tabla3[VLR. TRANSPORTE]) -> 43333.333 | J26: =SUMIF(Tabla3[LUGAR ENVÍO],Tabla11131415[[#This Row],[Ubicación]],Tabla3[VLR. TOTAL FACT.]) -> 14975100 | K26: =AVERAGEIF(Tabla8[Lugar],Tabla11131415[[#This Row],[Ubicación]],Tabla8[Perdida o ganancia de margen]) -> -0.16615067 | M26: Km 26 | N26: =COUNTIF(Tabla3[LUGAR ENVÍO],Tabla11161718[[#This Row],[Ubicación]]) -> 4 | O26: =SUMIF(Tabla3[LUGAR ENVÍO],Tabla11161718[[#This Row],[Ubicación]],Tabla3[VLR. TRANSPORTE]) -> 105000 | P26: =AVERAGEIF(Tabla3[LUGAR ENVÍO],Tabla11161718[[#This Row],[Ubicación]],Tabla3[VLR. TRANSPORTE]) -> 26250 | Q26: =SUMIF(Tabla3[LUGAR ENVÍO],Tabla11161718[[#This Row],[Ubicación]],Tabla3[VLR. TOTAL FACT.]) -> 5409900 | R26: =AVERAGEIF(Tabla8[Lugar],Tabla11161718[[#This Row],[Ubicación]],Tabla8[Perdida o ganancia de margen]) -> -0.17279623
A27: El limonar | B27: =COUNTIF(Tabla3[LUGAR ENVÍO],Tabla9[[#This Row],[Nombre ]]) -> 4 | C27: =Distancias!FW71 -> 4.713 | F27: Parcelacion la cristalina | G27: =COUNTIF(Tabla3[LUGAR ENVÍO],Tabla11131415[[#This Row],[Ubicación]]) -> 5 | H27: =SUMIF(Tabla3[LUGAR ENVÍO],Tabla11131415[[#This Row],[Ubicación]],Tabla3[VLR. TRANSPORTE]) -> 270000 | I27: =AVERAGEIF(Tabla3[LUGAR ENVÍO],Tabla11131415[[#This Row],[Ubicación]],Tabla3[VLR. TRANSPORTE]) -> 54000 | J27: =SUMIF(Tabla3[LUGAR ENVÍO],Tabla11131415[[#This Row],[Ubicación]],Tabla3[VLR. TOTAL FACT.]) -> 1938600 | K27: =AVERAGEIF(Tabla8[Lugar],Tabla11131415[[#This Row],[Ubicación]],Tabla8[Perdida o ganancia de margen]) -> 0.10560218 | M27: Agua sucia | N27: =COUNTIF(Tabla3[LUGAR ENVÍO],Tabla11161718[[#This Row],[Ubicación]]) -> 4 | O27: =SUMIF(Tabla3[LUGAR ENVÍO],Tabla11161718[[#This Row],[Ubicación]],Tabla3[VLR. TRANSPORTE]) -> 245000 | P27: =AVERAGEIF(Tabla3[LUGAR ENVÍO],Tabla11161718[[#This Row],[Ubicación]],Tabla3[VLR. TRANSPORTE]) -> 61250 | Q27: =SUMIF(Tabla3[LUGAR ENVÍO],Tabla11161718[[#This Row],[Ubicación]],Tabla3[VLR. TOTAL FACT.]) -> 11237300 | R27: =AVERAGEIF(Tabla8[Lugar],Tabla11161718[[#This Row],[Ubicación]],Tabla8[Perdida o ganancia de margen]) -> -0.031277382
A28: El Queremal | B28: =COUNTIF(Tabla3[LUGAR ENVÍO],Tabla9[[#This Row],[Nombre ]]) -> 4 | C28: =Distancias!EI71 -> 18.542 | F28: Carmen | G28: =COUNTIF(Tabla3[LUGAR ENVÍO],Tabla11131415[[#This Row],[Ubicación]]) -> 5 | H28: =SUMIF(Tabla3[LUGAR ENVÍO],Tabla11131415[[#This Row],[Ubicación]],Tabla3[VLR. TRANSPORTE]) -> 210000 | I28: =AVERAGEIF(Tabla3[LUGAR ENVÍO],Tabla11131415[[#This Row],[Ubicación]],Tabla3[VLR. TRANSPORTE]) -> 42000 | J28: =SUMIF(Tabla3[LUGAR ENVÍO],Tabla11131415[[#This Row],[Ubicación]],Tabla3[VLR. TOTAL FACT.]) -> 3997400 | K28: =AVERAGEIF(Tabla8[Lugar],Tabla11131415[[#This Row],[Ubicación]],Tabla8[Perdida o ganancia de margen]) -> -0.05103861 | M28: Villa Saman | N28: =COUNTIF(Tabla3[LUGAR ENVÍO],Tabla11161718[[#This Row],[Ubicación]]) -> 3 | O28: =SUMIF(Tabla3[LUGAR ENVÍO],Tabla11161718[[#This Row],[Ubicación]],Tabla3[VLR. TRANSPORTE]) -> 80000 | P28: =AVERAGEIF(Tabla3[LUGAR ENVÍO],Tabla11161718[[#This Row],[Ubicación]],Tabla3[VLR. TRANSPORTE]) -> 26666.667 | Q28: =SUMIF(Tabla3[LUGAR ENVÍO],Tabla11161718[[#This Row],[Ubicación]],Tabla3[VLR. TOTAL FACT.]) -> 3516000 | R28: =AVERAGEIF(Tabla8[Lugar],Tabla11161718[[#This Row],[Ubicación]],Tabla8[Perdida o ganancia de margen]) -> -0.50796499
A29: KM 26 | B29: =COUNTIF(Tabla3[LUGAR ENVÍO],Tabla9[[#This Row],[Nombre ]]) -> 4 | C29: =Distancias!GA121 -> 5.378 | F29: Parcelaón las palmas | G29: =COUNTIF(Tabla3[LUGAR ENVÍO],Tabla11131415[[#This Row],[Ubicación]]) -> 5 | H29: =SUMIF(Tabla3[LUGAR ENVÍO],Tabla11131415[[#This Row],[Ubicación]],Tabla3[VLR. TRANSPORTE]) -> 200000 | I29: =AVERAGEIF(Tabla3[LUGAR ENVÍO],Tabla11131415[[#This Row],[Ubicación]],Tabla3[VLR. TRANSPORTE]) -> 40000 | J29: =SUMIF(Tabla3[LUGAR ENVÍO],Tabla11131415[[#This Row],[Ubicación]],Tabla3[VLR. TOTAL FACT.]) -> 2762500 | K29: =AVERAGEIF(Tabla8[Lugar],Tabla11131415[[#This Row],[Ubicación]],Tabla8[Perdida o ganancia de margen]) -> -0.078857759 | M29: Tierras blancas | N29: =COUNTIF(Tabla3[LUGAR ENVÍO],Tabla11161718[[#This Row],[Ubicación]]) -> 3 | O29: =SUMIF(Tabla3[LUGAR ENVÍO],Tabla11161718[[#This Row],[Ubicación]],Tabla3[VLR. TRANSPORTE]) -> 205000 | P29: =AVERAGEIF(Tabla3[LUGAR ENVÍO],Tabla11161718[[#This Row],[Ubicación]],Tabla3[VLR. TRANSPORTE]) -> 68333.333 | Q29: =SUMIF(Tabla3[LUGAR ENVÍO],Tabla11161718[[#This Row],[Ubicación]],Tabla3[VLR. TOTAL FACT.]) -> 2559100 | R29: =AVERAGEIF(Tabla8[Lugar],Tabla11161718[[#This Row],[Ubicación]],Tabla8[Perdida o ganancia de margen]) -> -0.049708889
A30: KM 28 | B30: =COUNTIF(Tabla3[LUGAR ENVÍO],Tabla9[[#This Row],[Nombre ]]) -> 4 | C30: =Distancias!GE64 -> 3.943014 | F30: Las villas del carmen | G30: =COUNTIF(Tabla3[LUGAR ENVÍO],Tabla11131415[[#This Row],[Ubicación]]) -> 5 | H30: =SUMIF(Tabla3[LUGAR ENVÍO],Tabla11131415[[#This Row],[Ubicación]],Tabla3[VLR. TRANSPORTE]) -> 150000 | I30: =AVERAGEIF(Tabla3[LUGAR ENVÍO],Tabla11131415[[#This Row],[Ubicación]],Tabla3[VLR. TRANSPORTE]) -> 30000 | J30: =SUMIF(Tabla3[LUGAR ENVÍO],Tabla11131415[[#This Row],[Ubicación]],Tabla3[VLR. TOTAL FACT.]) -> 2360500 | K30: =AVERAGEIF(Tabla8[Lugar],Tabla11131415[[#This Row],[Ubicación]],Tabla8[Perdida o ganancia de margen]) -> -0.30529454 | M30: La Zulia 1 | N30: =COUNTIF(Tabla3[LUGAR ENVÍO],Tabla11161718[[#This Row],[Ubicación]]) -> 3 | O30: =SUMIF(Tabla3[LUGAR ENVÍO],Tabla11161718[[#This Row],[Ubicación]],Tabla3[VLR. TRANSPORTE]) -> 170000 | P30: =AVERAGEIF(Tabla3[LUGAR ENVÍO],Tabla11161718[[#This Row],[Ubicación]],Tabla3[VLR. TRANSPORTE]) -> 56666.667 | Q30: =SUMIF(Tabla3[LUGAR ENVÍO],Tabla11161718[[#This Row],[Ubicación]],Tabla3[VLR. TOTAL FACT.]) -> 956000 | R30: =AVERAGEIF(Tabla8[Lugar],Tabla11161718[[#This Row],[Ubicación]],Tabla8[Perdida o ganancia de margen]) -> -0.24684299
A31: La clorinda | B31: =COUNTIF(Tabla3[LUGAR ENVÍO],Tabla9[[#This Row],[Nombre ]]) -> 4 | C31: =Distancias!BG91 -> 5.264 | F31: Parcelación El bosque | G31: =COUNTIF(Tabla3[LUGAR ENVÍO],Tabla11131415[[#This Row],[Ubicación]]) -> 4 | H31: =SUMIF(Tabla3[LUGAR ENVÍO],Tabla11131415[[#This Row],[Ubicación]],Tabla3[VLR. TRANSPORTE]) -> 240000 | I31: =AVERAGEIF(Tabla3[LUGAR ENVÍO],Tabla11131415[[#This Row],[Ubicación]],Tabla3[VLR. TRANSPORTE]) -> 60000 | J31: =SUMIF(Tabla3[LUGAR ENVÍO],Tabla11131415[[#This Row],[Ubicación]],Tabla3[VLR. TOTAL FACT.]) -> 2398800 | K31: =AVERAGEIF(Tabla8[Lugar],Tabla11131415[[#This Row],[Ubicación]],Tabla8[Perdida o ganancia de margen]) -> 0.059550714 | M31: La bomba | N31: =COUNTIF(Tabla3[LUGAR ENVÍO],Tabla11161718[[#This Row],[Ubicación]]) -> 3 | O31: =SUMIF(Tabla3[LUGAR ENVÍO],Tabla11161718[[#This Row],[Ubicación]],Tabla3[VLR. TRANSPORTE]) -> 65000 | P31: =AVERAGEIF(Tabla3[LUGAR ENVÍO],Tabla11161718[[#This Row],[Ubicación]],Tabla3[VLR. TRANSPORTE]) -> 21666.667 | Q31: =SUMIF(Tabla3[LUGAR ENVÍO],Tabla11161718[[#This Row],[Ubicación]],Tabla3[VLR. TOTAL FACT.]) -> 8288900 | R31: =AVERAGEIF(Tabla8[Lugar],Tabla11161718[[#This Row],[Ubicación]],Tabla8[Perdida o ganancia de margen]) -> -0.040695946
A32: La Zulia 3 | B32: =COUNTIF(Tabla3[LUGAR ENVÍO],Tabla9[[#This Row],[Nombre ]]) -> 4 | C32: =Distancias!S24 -> 1.087 | F32: Altos de las tortolas | G32: =COUNTIF(Tabla3[LUGAR ENVÍO],Tabla11131415[[#This Row],[Ubicación]]) -> 4 | H32: =SUMIF(Tabla3[LUGAR ENVÍO],Tabla11131415[[#This Row],[Ubicación]],Tabla3[VLR. TRANSPORTE]) -> 240000 | I32: =AVERAGEIF(Tabla3[LUGAR ENVÍO],Tabla11131415[[#This Row],[Ubicación]],Tabla3[VLR. TRANSPORTE]) -> 60000 | J32: =SUMIF(Tabla3[LUGAR ENVÍO],Tabla11131415[[#This Row],[Ubicación]],Tabla3[VLR. TOTAL FACT.]) -> 3755100 | K32: =AVERAGEIF(Tabla8[Lugar],Tabla11131415[[#This Row],[Ubicación]],Tabla8[Perdida o ganancia de margen]) -> 0.054933767 | M32: Km 27 | N32: =COUNTIF(Tabla3[LUGAR ENVÍO],Tabla11161718[[#This Row],[Ubicación]]) -> 3 | O32: =SUMIF(Tabla3[LUGAR ENVÍO],Tabla11161718[[#This Row],[Ubicación]],Tabla3[VLR. TRANSPORTE]) -> 200000 | P32: =AVERAGEIF(Tabla3[LUGAR ENVÍO],Tabla11161718[[#This Row],[Ubicación]],Tabla3[VLR. TRANSPORTE]) -> 66666.667 | Q32: =SUMIF(Tabla3[LUGAR ENVÍO],Tabla11161718[[#This Row],[Ubicación]],Tabla3[VLR. TOTAL FACT.]) -> 8220300 | R32: =AVERAGEIF(Tabla8[Lugar],Tabla11161718[[#This Row],[Ubicación]],Tabla8[Perdida o ganancia de margen]) -> -0.13156178
A33: Parcelación El bosque | B33: =COUNTIF(Tabla3[LUGAR ENVÍO],Tabla9[[#This Row],[Nombre ]]) -> 4 | C33: =Distancias!FS60 -> 4.800039 | F33: La clorinda | G33: =COUNTIF(Tabla3[LUGAR ENVÍO],Tabla11131415[[#This Row],[Ubicación]]) -> 4 | H33: =SUMIF(Tabla3[LUGAR ENVÍO],Tabla11131415[[#This Row],[Ubicación]],Tabla3[VLR. TRANSPORTE]) -> 175000 | I33: =AVERAGEIF(Tabla3[LUGAR ENVÍO],Tabla11131415[[#This Row],[Ubicación]],Tabla3[VLR. TRANSPORTE]) -> 43750 | J33: =SUMIF(Tabla3[LUGAR ENVÍO],Tabla11131415[[#This Row],[Ubicación]],Tabla3[VLR. TOTAL FACT.]) -> 3514000 | K33: =AVERAGEIF(Tabla8[Lugar],Tabla11131415[[#This Row],[Ubicación]],Tabla8[Perdida o ganancia de margen]) -> -0.3142945 | M33: KM 24 | N33: =COUNTIF(Tabla3[LUGAR ENVÍO],Tabla11161718[[#This Row],[Ubicación]]) -> 3 | O33: =SUMIF(Tabla3[LUGAR ENVÍO],Tabla11161718[[#This Row],[Ubicación]],Tabla3[VLR. TRANSPORTE]) -> 180000 | P33: =AVERAGEIF(Tabla3[LUGAR ENVÍO],Tabla11161718[[#This Row],[Ubicación]],Tabla3[VLR. TRANSPORTE]) -> 60000 | Q33: =SUMIF(Tabla3[LUGAR ENVÍO],Tabla11161718[[#This Row],[Ubicación]],Tabla3[VLR. TOTAL FACT.]) -> 4517500 | R33: =AVERAGEIF(Tabla8[Lugar],Tabla11161718[[#This Row],[Ubicación]],Tabla8[Perdida o ganancia de margen]) -> -0.13903506
A34: Bahondo | B34: =COUNTIF(Tabla3[LUGAR ENVÍO],Tabla9[[#This Row],[Nombre ]]) -> 3 | C34: =Distancias!BW79 -> 5.6 | F34: Bahondo | G34: =COUNTIF(Tabla3[LUGAR ENVÍO],Tabla11131415[[#This Row],[Ubicación]]) -> 3 | H34: =SUMIF(Tabla3[LUGAR ENVÍO],Tabla11131415[[#This Row],[Ubicación]],Tabla3[VLR. TRANSPORTE]) -> 150000 | I34: =AVERAGEIF(Tabla3[LUGAR ENVÍO],Tabla11131415[[#This Row],[Ubicación]],Tabla3[VLR. TRANSPORTE]) -> 50000 | J34: =SUMIF(Tabla3[LUGAR ENVÍO],Tabla11131415[[#This Row],[Ubicación]],Tabla3[VLR. TOTAL FACT.]) -> 754200 | K34: =AVERAGEIF(Tabla8[Lugar],Tabla11131415[[#This Row],[Ubicación]],Tabla8[Perdida o ganancia de margen]) -> -0.20720133 | M34: Chipre | N34: =COUNTIF(Tabla3[LUGAR ENVÍO],Tabla11161718[[#This Row],[Ubicación]]) -> 3 | O34: =SUMIF(Tabla3[LUGAR ENVÍO],Tabla11161718[[#This Row],[Ubicación]],Tabla3[VLR. TRANSPORTE]) -> 165000 | P34: =AVERAGEIF(Tabla3[LUGAR ENVÍO],Tabla11161718[[#This Row],[Ubicación]],Tabla3[VLR. TRANSPORTE]) -> 55000 | Q34: =SUMIF(Tabla3[LUGAR ENVÍO],Tabla11161718[[#This Row],[Ubicación]],Tabla3[VLR. TOTAL FACT.]) -> 3471900 | R34: =AVERAGEIF(Tabla8[Lugar],Tabla11161718[[#This Row],[Ubicación]],Tabla8[Perdida o ganancia de margen]) -> -0.15588596
A35: Chipre | B35: =COUNTIF(Tabla3[LUGAR ENVÍO],Tabla9[[#This Row],[Nombre ]]) -> 3 | C35: =Distancias!AQ85 -> 4.781 | F35: Saliendo del carmen | G35: =COUNTIF(Tabla3[LUGAR ENVÍO],Tabla11131415[[#This Row],[Ubicación]]) -> 3 | H35: =SUMIF(Tabla3[LUGAR ENVÍO],Tabla11131415[[#This Row],[Ubicación]],Tabla3[VLR. TRANSPORTE]) -> 115000 | I35: =AVERAGEIF(Tabla3[LUGAR ENVÍO],Tabla11131415[[#This Row],[Ubicación]],Tabla3[VLR. TRANSPORTE]) -> 38333.333 | J35: =SUMIF(Tabla3[LUGAR ENVÍO],Tabla11131415[[#This Row],[Ubicación]],Tabla3[VLR. TOTAL FACT.]) -> 7310000 | K35: =AVERAGEIF(Tabla8[Lugar],Tabla11131415[[#This Row],[Ubicación]],Tabla8[Perdida o ganancia de margen]) -> -0.077205953 | M35: Panamericano | N35: =COUNTIF(Tabla3[LUGAR ENVÍO],Tabla11161718[[#This Row],[Ubicación]]) -> 2 | O35: =SUMIF(Tabla3[LUGAR ENVÍO],Tabla11161718[[#This Row],[Ubicación]],Tabla3[VLR. TRANSPORTE]) -> 30000 | P35: =AVERAGEIF(Tabla3[LUGAR ENVÍO],Tabla11161718[[#This Row],[Ubicación]],Tabla3[VLR. TRANSPORTE]) -> 15000 | Q35: =SUMIF(Tabla3[LUGAR ENVÍO],Tabla11161718[[#This Row],[Ubicación]],Tabla3[VLR. TOTAL FACT.]) -> 2414000 | R35: =AVERAGEIF(Tabla8[Lugar],Tabla11161718[[#This Row],[Ubicación]],Tabla8[Perdida o ganancia de margen]) -> -0.45623426
A36: El palmar | B36: =COUNTIF(Tabla3[LUGAR ENVÍO],Tabla9[[#This Row],[Nombre ]]) -> 3 | C36: =Distancias!CM100 -> 4.93 | F36: Parcelación Monterico | G36: =COUNTIF(Tabla3[LUGAR ENVÍO],Tabla11131415[[#This Row],[Ubicación]]) -> 2 | H36: =SUMIF(Tabla3[LUGAR ENVÍO],Tabla11131415[[#This Row],[Ubicación]],Tabla3[VLR. TRANSPORTE]) -> 180000 | I36: =AVERAGEIF(Tabla3[LUGAR ENVÍO],Tabla11131415[[#This Row],[Ubicación]],Tabla3[VLR. TRANSPORTE]) -> 90000 | J36: =SUMIF(Tabla3[LUGAR ENVÍO],Tabla11131415[[#This Row],[Ubicación]],Tabla3[VLR. TOTAL FACT.]) -> 1596500 | K36: =AVERAGEIF(Tabla8[Lugar],Tabla11131415[[#This Row],[Ubicación]],Tabla8[Perdida o ganancia de margen]) -> -0.37601594 | M36: La recta | N36: =COUNTIF(Tabla3[LUGAR ENVÍO],Tabla11161718[[#This Row],[Ubicación]]) -> 2 | O36: =SUMIF(Tabla3[LUGAR ENVÍO],Tabla11161718[[#This Row],[Ubicación]],Tabla3[VLR. TRANSPORTE]) -> 70000 | P36: =AVERAGEIF(Tabla3[LUGAR ENVÍO],Tabla11161718[[#This Row],[Ubicación]],Tabla3[VLR. TRANSPORTE]) -> 35000 | Q36: =SUMIF(Tabla3[LUGAR ENVÍO],Tabla11161718[[#This Row],[Ubicación]],Tabla3[VLR. TOTAL FACT.]) -> 493800 | R36: =AVERAGEIF(Tabla8[Lugar],Tabla11161718[[#This Row],[Ubicación]],Tabla8[Perdida o ganancia de margen]) -> -0.20015568
A37: KM 24 | B37: =COUNTIF(Tabla3[LUGAR ENVÍO],Tabla9[[#This Row],[Nombre ]]) -> 3 | C37: =Distancias!FC115 -> 6.973 | F37: villa emilia | G37: =COUNTIF(Tabla3[LUGAR ENVÍO],Tabla11131415[[#This Row],[Ubicación]]) -> 1 | H37: =SUMIF(Tabla3[LUGAR ENVÍO],Tabla11131415[[#This Row],[Ubicación]],Tabla3[VLR. TRANSPORTE]) -> 40000 | I37: =AVERAGEIF(Tabla3[LUGAR ENVÍO],Tabla11131415[[#This Row],[Ubicación]],Tabla3[VLR. TRANSPORTE]) -> 40000 | J37: =SUMIF(Tabla3[LUGAR ENVÍO],Tabla11131415[[#This Row],[Ubicación]],Tabla3[VLR. TOTAL FACT.]) -> 233000 | K37: =AVERAGEIF(Tabla8[Lugar],Tabla11131415[[#This Row],[Ubicación]],Tabla8[Perdida o ganancia de margen]) -> -0.26229409 | M37: Km 25 | N37: =COUNTIF(Tabla3[LUGAR ENVÍO],Tabla11161718[[#This Row],[Ubicación]]) -> 2 | O37: =SUMIF(Tabla3[LUGAR ENVÍO],Tabla11161718[[#This Row],[Ubicación]],Tabla3[VLR. TRANSPORTE]) -> 110000 | P37: =AVERAGEIF(Tabla3[LUGAR ENVÍO],Tabla11161718[[#This Row],[Ubicación]],Tabla3[VLR. TRANSPORTE]) -> 55000 | Q37: =SUMIF(Tabla3[LUGAR ENVÍO],Tabla11161718[[#This Row],[Ubicación]],Tabla3[VLR. TOTAL FACT.]) -> 5960000 | R37: =AVERAGEIF(Tabla8[Lugar],Tabla11161718[[#This Row],[Ubicación]],Tabla8[Perdida o ganancia de margen]) -> -0.062397199
A38: KM 27 | B38: =COUNTIF(Tabla3[LUGAR ENVÍO],Tabla9[[#This Row],[Nombre ]]) -> 3 | C38: =Distancias!GI77 -> 4.583943 | F38: El chiringuito | G38: =COUNTIF(Tabla3[LUGAR ENVÍO],Tabla11131415[[#This Row],[Ubicación]]) -> 1 | H38: =SUMIF(Tabla3[LUGAR ENVÍO],Tabla11131415[[#This Row],[Ubicación]],Tabla3[VLR. TRANSPORTE]) -> 40000 | I38: =AVERAGEIF(Tabla3[LUGAR ENVÍO],Tabla11131415[[#This Row],[Ubicación]],Tabla3[VLR. TRANSPORTE]) -> 40000 | J38: =SUMIF(Tabla3[LUGAR ENVÍO],Tabla11131415[[#This Row],[Ubicación]],Tabla3[VLR. TOTAL FACT.]) -> 1480000 | K38: =AVERAGEIF(Tabla8[Lugar],Tabla11131415[[#This Row],[Ubicación]],Tabla8[Perdida o ganancia de margen]) -> -0.017157573 | M38: cositas ricas | N38: =COUNTIF(Tabla3[LUGAR ENVÍO],Tabla11161718[[#This Row],[Ubicación]]) -> 2 | O38: =SUMIF(Tabla3[LUGAR ENVÍO],Tabla11161718[[#This Row],[Ubicación]],Tabla3[VLR. TRANSPORTE]) -> 60000 | P38: =AVERAGEIF(Tabla3[LUGAR ENVÍO],Tabla11161718[[#This Row],[Ubicación]],Tabla3[VLR. TRANSPORTE]) -> 30000 | Q38: =SUMIF(Tabla3[LUGAR ENVÍO],Tabla11161718[[#This Row],[Ubicación]],Tabla3[VLR. TOTAL FACT.]) -> 2085300 | R38: =AVERAGEIF(Tabla8[Lugar],Tabla11161718[[#This Row],[Ubicación]],Tabla8[Perdida o ganancia de margen]) -> -0.2367078
A39: La bomba | B39: =COUNTIF(Tabla3[LUGAR ENVÍO],Tabla9[[#This Row],[Nombre ]]) -> 3 | C39: =Distancias!FK26 -> 1.321207 | F39: Las playas | G39: =COUNTIF(Tabla3[LUGAR ENVÍO],Tabla11131415[[#This Row],[Ubicación]]) -> 1 | H39: =SUMIF(Tabla3[LUGAR ENVÍO],Tabla11131415[[#This Row],[Ubicación]],Tabla3[VLR. TRANSPORTE]) -> 40000 | I39: =AVERAGEIF(Tabla3[LUGAR ENVÍO],Tabla11131415[[#This Row],[Ubicación]],Tabla3[VLR. TRANSPORTE]) -> 40000 | J39: =SUMIF(Tabla3[LUGAR ENVÍO],Tabla11131415[[#This Row],[Ubicación]],Tabla3[VLR. TOTAL FACT.]) -> 1699000 | K39: =AVERAGEIF(Tabla8[Lugar],Tabla11131415[[#This Row],[Ubicación]],Tabla8[Perdida o ganancia de margen]) -> -0.019689763 | M39: Azul y verde | N39: =COUNTIF(Tabla3[LUGAR ENVÍO],Tabla11161718[[#This Row],[Ubicación]]) -> 2 | O39: =SUMIF(Tabla3[LUGAR ENVÍO],Tabla11161718[[#This Row],[Ubicación]],Tabla3[VLR. TRANSPORTE]) -> 90000 | P39: =AVERAGEIF(Tabla3[LUGAR ENVÍO],Tabla11161718[[#This Row],[Ubicación]],Tabla3[VLR. TRANSPORTE]) -> 45000 | Q39: =SUMIF(Tabla3[LUGAR ENVÍO],Tabla11161718[[#This Row],[Ubicación]],Tabla3[VLR. TOTAL FACT.]) -> 965000 | R39: =AVERAGEIF(Tabla8[Lugar],Tabla11161718[[#This Row],[Ubicación]],Tabla8[Perdida o ganancia de margen]) -> -0.42142408
A40: La Zulia 1 | B40: =COUNTIF(Tabla3[LUGAR ENVÍO],Tabla9[[#This Row],[Nombre ]]) -> 3 | C40: =Distancias!G26 -> 0.944 | F40: La cabaña | G40: =COUNTIF(Tabla3[LUGAR ENVÍO],Tabla11131415[[#This Row],[Ubicación]]) -> 1 | H40: =SUMIF(Tabla3[LUGAR ENVÍO],Tabla11131415[[#This Row],[Ubicación]],Tabla3[VLR. TRANSPORTE]) -> 40000 | I40: =AVERAGEIF(Tabla3[LUGAR ENVÍO],Tabla11131415[[#This Row],[Ubicación]],Tabla3[VLR. TRANSPORTE]) -> 40000 | J40: =SUMIF(Tabla3[LUGAR ENVÍO],Tabla11131415[[#This Row],[Ubicación]],Tabla3[VLR. TOTAL FACT.]) -> 396000 | K40: =AVERAGEIF(Tabla8[Lugar],Tabla11131415[[#This Row],[Ubicación]],Tabla8[Perdida o ganancia de margen]) -> -0.090304383 | M40: Parcelación Ambichinte | N40: =COUNTIF(Tabla3[LUGAR ENVÍO],Tabla11161718[[#This Row],[Ubicación]]) -> 1 | O40: =SUMIF(Tabla3[LUGAR ENVÍO],Tabla11161718[[#This Row],[Ubicación]],Tabla3[VLR. TRANSPORTE]) -> 40000 | P40: =AVERAGEIF(Tabla3[LUGAR ENVÍO],Tabla11161718[[#This Row],[Ubicación]],Tabla3[VLR. TRANSPORTE]) -> 40000 | Q40: =SUMIF(Tabla3[LUGAR ENVÍO],Tabla11161718[[#This Row],[Ubicación]],Tabla3[VLR. TOTAL FACT.]) -> 181500 | R40: =AVERAGEIF(Tabla8[Lugar],Tabla11161718[[#This Row],[Ubicación]],Tabla8[Perdida o ganancia de margen]) -> -0.38035144
A41: San Fernando | B41: =COUNTIF(Tabla3[LUGAR ENVÍO],Tabla9[[#This Row],[Nombre ]]) -> 3 | C41: =Distancias!CU114 -> 7.603318 | G41: =SUM(Tabla11131415[Envios]) -> 98
A42: Tierras blancas | B42: =COUNTIF(Tabla3[LUGAR ENVÍO],Tabla9[[#This Row],[Nombre ]]) -> 3 | C42: =Distancias!K19 -> 0.449 | G42: =COUNTIF(Tabla3[LUGAR ENVÍO],Tabla11131415[[#This Row],[Ubicación]]) -> 0 | H42: =SUMIF(Tabla3[LUGAR ENVÍO],Tabla11131415[[#This Row],[Ubicación]],Tabla3[VLR. TRANSPORTE]) -> 0 | I42: =AVERAGEIF(Tabla3[LUGAR ENVÍO],Tabla11131415[[#This Row],[Ubicación]],Tabla3[VLR. TRANSPORTE]) -> #DIV/0! | J42: =SUMIF(Tabla3[LUGAR ENVÍO],Tabla11131415[[#This Row],[Ubicación]],Tabla3[VLR. TOTAL FACT.]) -> 0 | K42: =AVERAGEIF(Tabla8[Lugar],Tabla11131415[[#This Row],[Ubicación]],Tabla8[Perdida o ganancia de margen]) -> #DIV/0!
A43: Villa saman | B43: =COUNTIF(Tabla3[LUGAR ENVÍO],Tabla9[[#This Row],[Nombre ]]) -> 3 | C43: =Distancias!II37 -> 2.059 | G43: =COUNTIF(Tabla3[LUGAR ENVÍO],Tabla11131415[[#This Row],[Ubicación]]) -> 0 | H43: =SUMIF(Tabla3[LUGAR ENVÍO],Tabla11131415[[#This Row],[Ubicación]],Tabla3[VLR. TRANSPORTE]) -> 0 | I43: =AVERAGEIF(Tabla3[LUGAR ENVÍO],Tabla11131415[[#This Row],[Ubicación]],Tabla3[VLR. TRANSPORTE]) -> #DIV/0! | J43: =SUMIF(Tabla3[LUGAR ENVÍO],Tabla11131415[[#This Row],[Ubicación]],Tabla3[VLR. TOTAL FACT.]) -> 0 | K43: =AVERAGEIF(Tabla8[Lugar],Tabla11131415[[#This Row],[Ubicación]],Tabla8[Perdida o ganancia de margen]) -> #DIV/0!
A44: Saliendo del carmen | B44: =COUNTIF(Tabla3[LUGAR ENVÍO],Tabla9[[#This Row],[Nombre ]]) -> 3 | C44: =Distancias!IM58 -> 4.734
A45: Azul y verde | B45: =COUNTIF(Tabla3[LUGAR ENVÍO],Tabla9[[#This Row],[Nombre ]]) -> 2 | C45: =Distancias!EQ34 -> 2.31
A46: Cositas ricas | B46: =COUNTIF(Tabla3[LUGAR ENVÍO],Tabla9[[#This Row],[Nombre ]]) -> 2 | C46: =Distancias!AA19 -> 0.723
A47: KM 25 | B47: =COUNTIF(Tabla3[LUGAR ENVÍO],Tabla9[[#This Row],[Nombre ]]) -> 2 | C47: =Distancias!DK130 -> 6.46658
A48: KM 40 | B48: =COUNTIF(Tabla3[LUGAR ENVÍO],Tabla9[[#This Row],[Nombre ]]) -> 2 | C48: =Distancias!CY130 -> 9.607613
A49: La recta | B49: =COUNTIF(Tabla3[LUGAR ENVÍO],Tabla9[[#This Row],[Nombre ]]) -> 2 | C49: =Distancias!O25 -> 0.935
A50: Mirador Bellavista | B50: =COUNTIF(Tabla3[LUGAR ENVÍO],Tabla9[[#This Row],[Nombre ]]) -> 2 | C50: =Distancias!AI33 -> 1.201
A51: Parcelación Monterico | B51: =COUNTIF(Tabla3[LUGAR ENVÍO],Tabla9[[#This Row],[Nombre ]]) -> 2 | C51: =Distancias!FO150 -> 9.826848
A52: El chilcal | B52: =COUNTIF(Tabla3[LUGAR ENVÍO],Tabla9[[#This Row],[Nombre ]]) -> 2 | C52: =Distancias!IA71 -> 14.314
A53: Panamericano | B53: =COUNTIF(Tabla3[LUGAR ENVÍO],Tabla9[[#This Row],[Nombre ]]) -> 2 | C53: =Distancias!IE21 -> 1.127
A54: Villahermosa | B54: =COUNTIF(Tabla3[LUGAR ENVÍO],Tabla9[[#This Row],[Nombre ]]) -> 2 | C54: =Distancias!IQ83 -> 6.788
A55: KM 37 | B55: =COUNTIF(Tabla3[LUGAR ENVÍO],Tabla9[[#This Row],[Nombre ]]) -> 1 | C55: =Distancias!CQ100 -> 6.606969
A56: Pa la chingada | B56: =COUNTIF(Tabla3[LUGAR ENVÍO],Tabla9[[#This Row],[Nombre ]]) -> 1 | C56: =Distancias!AE33 -> 1.31
A57: Parcelación Ambichinte | B57: =COUNTIF(Tabla3[LUGAR ENVÍO],Tabla9[[#This Row],[Nombre ]]) -> 1 | C57: =Distancias!GU80 -> 3.684
A58: La cabaña | B58: =COUNTIF(Tabla3[LUGAR ENVÍO],Tabla9[[#This Row],[Nombre ]]) -> 1 | C58: =Distancias!HK41 -> 2.091
A59: Villa emilia | B59: =COUNTIF(Tabla3[LUGAR ENVÍO],Tabla9[[#This Row],[Nombre ]]) -> 1 | C59: =Distancias!HO50 -> 3.449
A60: El chiringuito | B60: =COUNTIF(Tabla3[LUGAR ENVÍO],Tabla9[[#This Row],[Nombre ]]) -> 1 | C60: =Distancias!HS37 -> 1.544
A61: Las playas | B61: =COUNTIF(Tabla3[LUGAR ENVÍO],Tabla9[[#This Row],[Nombre ]]) -> 1 | C61: =Distancias!HW40 -> 2.129
A62: Campamento Salomon | B62: =COUNTIF(Tabla3[LUGAR ENVÍO],Tabla9[[#This Row],[Nombre ]]) -> 0 | C62: =Distancias!AM58 -> 3.467
A63: Finca la cristalina | B63: =COUNTIF(Tabla3[LUGAR ENVÍO],Tabla9[[#This Row],[Nombre ]]) -> 0 | C63: =Distancias!FG77 -> 6.071
A64: MK 26 | B64: =COUNTIF(Tabla3[LUGAR ENVÍO],Tabla9[[#This Row],[Nombre ]]) -> 0 | C64: =Distancias!GA121 -> 5.378
C65: =SUBTOTAL(101,Tabla9[Distancia]) -> 4.4106011

Sheet ANALISIS DEL MARGEN
A2: N° FACTURA | B2: Corregimiento | C2: Lugar | D2: DISTANCIA (km) | E2: Numero de Transportes | F2: VLR. TRANSPORTE | G2: VLR. Transporte unitario | H2: VLR. TOTAL FACT. | I2: VLR. PRODUCTOS | J2: Margen de productos | K2: Costo fijo | L2: Costo Variable | M2: Costo Total | N2: Columna1 | O2: Ganancia/Perdida | P2: Margen | Q2: Perdida o ganancia de margen
A3: 47735 | B3: =_xlfn.XLOOKUP(Tabla8[[#This Row],[N° FACTURA]],Tabla3[N° FACTURA],Tabla3[Corregimiento],"NA") -> Borrero Ayerbe | C3: =_xlfn.XLOOKUP(Tabla8[[#This Row],[N° FACTURA]],Tabla3[N° FACTURA],Tabla3[LUGAR ENVÍO],"NA") -> casa verde | D3: =_xlfn.XLOOKUP(Tabla8[[#This Row],[N° FACTURA]],Tabla3[N° FACTURA],Tabla3[DISTANCIA (km)],"NA") -> 4.626 | E3: =_xlfn.XLOOKUP(Tabla8[[#This Row],[N° FACTURA]],Tabla3[N° FACTURA],Tabla3[Numero de Transportes],"NA") -> 2 | F3: =_xlfn.XLOOKUP(Tabla8[[#This Row],[N° FACTURA]],Tabla3[N° FACTURA],Tabla3[VLR. TRANSPORTE],"NA") -> 80000 | G3: =Tabla8[[#This Row],[VLR. TRANSPORTE]]/Tabla8[[#This Row],[Numero de Transportes]] -> 40000 | H3: =_xlfn.XLOOKUP(Tabla8[[#This Row],[N° FACTURA]],Tabla3[N° FACTURA],Tabla3[VLR. TOTAL FACT.],"NA") -> 300000 | I3: =Tabla8[[#This Row],[VLR. TOTAL FACT.]]-Tabla8[[#This Row],[VLR. TRANSPORTE]] -> 220000 | J3: =Tabla8[[#This Row],[VLR. PRODUCTOS]]*0.2 -> 44000 | K3: ='ABC COSTEO'!B$11 -> 40740.428 | L3: =Tabla8[[#This Row],[DISTANCIA (km)]]*2*'ABC COSTEO'!B$21 -> 12586.535 | M3: =Tabla8[[#This Row],[Costo Variable]]+Tabla8[[#This Row],[Costo fijo]] -> 53326.963 | N3: =Tabla8[[#This Row],[Costo Total]]*Tabla8[[#This Row],[Numero de Transportes]] -> 106653.93 | O3: =(Tabla8[[#This Row],[VLR. Transporte unitario]]-Tabla8[[#This Row],[Costo Total]])*Tabla8[[#This Row],[Numero de Transportes]] -> -26653.925 | P3: =Tabla8[[#This Row],[Margen de productos]]+Tabla8[[#This Row],[Ganancia/Perdida]] -> 17346.075 | Q3: =(Tabla8[[#This Row],[Margen ]]/Tabla8[[#This Row],[Margen de productos]])-1 -> -0.60577102
A4: 57979 | B4: =_xlfn.XLOOKUP(Tabla8[[#This Row],[N° FACTURA]],Tabla3[N° FACTURA],Tabla3[Corregimiento],"NA") -> Borrero Ayerbe | C4: =_xlfn.XLOOKUP(Tabla8[[#This Row],[N° FACTURA]],Tabla3[N° FACTURA],Tabla3[LUGAR ENVÍO],"NA") -> La Zulia 2 | D4: =_xlfn.XLOOKUP(Tabla8[[#This Row],[N° FACTURA]],Tabla3[N° FACTURA],Tabla3[DISTANCIA (km)],"NA") -> 1.248 | E4: =_xlfn.XLOOKUP(Tabla8[[#This Row],[N° FACTURA]],Tabla3[N° FACTURA],Tabla3[Numero de Transportes],"NA") -> 1 | F4: =_xlfn.XLOOKUP(Tabla8[[#This Row],[N° FACTURA]],Tabla3[N° FACTURA],Tabla3[VLR. TRANSPORTE],"NA") -> 15000 | G4: =Tabla8[[#This Row],[VLR. TRANSPORTE]]/Tabla8[[#This Row],[Numero de Transportes]] -> 15000 | H4: =_xlfn.XLOOKUP(Tabla8[[#This Row],[N° FACTURA]],Tabla3[N° FACTURA],Tabla3[VLR. TOTAL FACT.],"NA") -> 377800 | I4: =Tabla8[[#This Row],[VLR. TOTAL FACT.]]-Tabla8[[#This Row],[VLR. TRANSPORTE]] -> 362800 | J4: =Tabla8[[#This Row],[VLR. PRODUCTOS]]*0.2 -> 72560 | K4: ='ABC COSTEO'!B$11 -> 40740.428 | L4: =Tabla8[[#This Row],[DISTANCIA (km)]]*2*'ABC COSTEO'!B$21 -> 3395.5891 | M4: =Tabla8[[#This Row],[Costo Variable]]+Tabla8[[#This Row],[Costo fijo]] -> 44136.017 | N4: =Tabla8[[#This Row],[Costo Total]]*Tabla8[[#This Row],[Numero de Transportes]] -> 44136.017 | O4: =(Tabla8[[#This Row],[VLR. Transporte unitario]]-Tabla8[[#This Row],[Costo Total]])*Tabla8[[#This Row],[Numero de Transportes]] -> -29136.017 | P4: =Tabla8[[#This Row],[Margen de productos]]+Tabla8[[#This Row],[Ganancia/Perdida]] -> 43423.983 | Q4: =(Tabla8[[#This Row],[Margen ]]/Tabla8[[#This Row],[Margen de productos]])-1 -> -0.40154378
A5: 58976 | B5: =_xlfn.XLOOKUP(Tabla8[[#This Row],[N° FACTURA]],Tabla3[N° FACTURA],Tabla3[Corregimiento],"NA") -> El Limonar | C5: =_xlfn.XLOOKUP(Tabla8[[#This Row],[N° FACTURA]],Tabla3[N° FACTURA],Tabla3[LUGAR ENVÍO],"NA") -> San Fernando | D5: =_xlfn.XLOOKUP(Tabla8[[#This Row],[N° FACTURA]],Tabla3[N° FACTURA],Tabla3[DISTANCIA (km)],"NA") -> 7.603318 | E5: =_xlfn.XLOOKUP(Tabla8[[#This Row],[N° FACTURA]],Tabla3[N° FACTURA],Tabla3[Numero de Transportes],"NA") -> 1 | F5: =_xlfn.XLOOKUP(Tabla8[[#This Row],[N° FACTURA]],Tabla3[N° FACTURA],Tabla3[VLR. TRANSPORTE],"NA") -> 70000 | G5: =Tabla8[[#This Row],[VLR. TRANSPORTE]]/Tabla8[[#This Row],[Numero de Transportes]] -> 70000 | H5: =_xlfn.XLOOKUP(Tabla8[[#This Row],[N° FACTURA]],Tabla3[N° FACTURA],Tabla3[VLR. TOTAL FACT.],"NA") -> 841000 | I5: =Tabla8[[#This Row],[VLR. TOTAL FACT.]]-Tabla8[[#This Row],[VLR. TRANSPORTE]] -> 771000 | J5: =Tabla8[[#This Row],[VLR. PRODUCTOS]]*0.2 -> 154200 | K5: ='ABC COSTEO'!B$11 -> 40740.428 | L5: =Tabla8[[#This Row],[DISTANCIA (km)]]*2*'ABC COSTEO'!B$21 -> 20687.295 | M5: =Tabla8[[#This Row],[Costo Variable]]+Tabla8[[#This Row],[Costo fijo]] -> 61427.723 | N5: =Tabla8[[#This Row],[Costo Total]]*Tabla8[[#This Row],[Numero de Transportes]] -> 61427.723 | O5: =(Tabla8[[#This Row],[VLR. Transporte unitario]]-Tabla8[[#This Row],[Costo Total]])*Tabla8[[#This Row],[Numero de Transportes]] -> 8572.2773 | P5: =Tabla8[[#This Row],[Margen de productos]]+Tabla8[[#This Row],[Ganancia/Perdida]] -> 162772.28 | Q5: =(Tabla8[[#This Row],[Margen ]]/Tabla8[[#This Row],[Margen de productos]])-1 -> 0.055591941
A6: 58505 | B6: =_xlfn.XLOOKUP(Tabla8[[#This Row],[N° FACTURA]],Tabla3[N° FACTURA],Tabla3[Corregimiento],"NA") -> El Carmen | C6: =_xlfn.XLOOKUP(Tabla8[[#This Row],[N° FACTURA]],Tabla3[N° FACTURA],Tabla3[LUGAR ENVÍO],"NA") -> bahondo | D6: =_xlfn.XLOOKUP(Tabla8[[#This Row],[N° FACTURA]],Tabla3[N° FACTURA],Tabla3[DISTANCIA (km)],"NA") -> 5.6 | E6: =_xlfn.XLOOKUP(Tabla8[[#This Row],[N° FACTURA]],Tabla3[N° FACTURA],Tabla3[Numero de Transportes],"NA") -> 1 | F6: =_xlfn.XLOOKUP(Tabla8[[#This Row],[N° FACTURA]],Tabla3[N° FACTURA],Tabla3[VLR. TRANSPORTE],"NA") -> 50000 | G6: =Tabla8[[#This Row],[VLR. TRANSPORTE]]/Tabla8[[#This Row],[Numero de Transportes]] -> 50000 | H6: =_xlfn.XLOOKUP(Tabla8[[#This Row],[N° FACTURA]],Tabla3[N° FACTURA],Tabla3[VLR. TOTAL FACT.],"NA") -> 133500 | I6: =Tabla8[[#This Row],[VLR. TOTAL FACT.]]-Tabla8[[#This Row],[VLR. TRANSPORTE]] -> 83500 | J6: =Tabla8[[#This Row],[VLR. PRODUCTOS]]*0.2 -> 16700 | K6: ='ABC COSTEO'!B$11 -> 40740.428 | L6: =Tabla8[[#This Row],[DISTANCIA (km)]]*2*'ABC COSTEO'!B$21 -> 15236.618 | M6: =Tabla8[[#This Row],[Costo Variable]]+Tabla8[[#This Row],[Costo fijo]] -> 55977.046 | N6: =Tabla8[[#This Row],[Costo Total]]*Tabla8[[#This Row],[Numero de Transportes]] -> 55977.046 | O6: =(Tabla8[[#This Row],[VLR. Transporte unitario]]-Tabla8[[#This Row],[Costo Total]])*Tabla8[[#This Row],[Numero de Transportes]] -> -5977.0457 | P6: =Tabla8[[#This Row],[Margen de productos]]+Tabla8[[#This Row],[Ganancia/Perdida]] -> 10722.954 | Q6: =(Tabla8[[#This Row],[Margen ]]/Tabla8[[#This Row],[Margen de productos]])-1 -> -0.35790693
A7: 48240 | B7: =_xlfn.XLOOKUP(Tabla8[[#This Row],[N° FACTURA]],Tabla3[N° FACTURA],Tabla3[Corregimiento],"NA") -> El Carmen | C7: =_xlfn.XLOOKUP(Tabla8[[#This Row],[N° FACTURA]],Tabla3[N° FACTURA],Tabla3[LUGAR ENVÍO],"NA") -> villa del toro | D7: =_xlfn.XLOOKUP(Tabla8[[#This Row],[N° FACTURA]],Tabla3[N° FACTURA],Tabla3[DISTANCIA (km)],"NA") -> 2.279762 | E7: =_xlfn.XLOOKUP(Tabla8[[#This Row],[N° FACTURA]],Tabla3[N° FACTURA],Tabla3[Numero de Transportes],"NA") -> 1 | F7: =_xlfn.XLOOKUP(Tabla8[[#This Row],[N° FACTURA]],Tabla3[N° FACTURA],Tabla3[VLR. TRANSPORTE],"NA") -> 40000 | G7: =Tabla8[[#This Row],[VLR. TRANSPORTE]]/Tabla8[[#This Row],[Numero de Transportes]] -> 40000 | H7: =_xlfn.XLOOKUP(Tabla8[[#This Row],[N° FACTURA]],Tabla3[N° FACTURA],Tabla3[VLR. TOTAL FACT.],"NA") -> 410500 | I7: =Tabla8[[#This Row],[VLR. TOTAL FACT.]]-Tabla8[[#This Row],[VLR. TRANSPORTE]] -> 370500 | J7: =Tabla8[[#This Row],[VLR. PRODUCTOS]]*0.2 -> 74100 | K7: ='ABC COSTEO'!B$11 -> 40740.428 | L7: =Tabla8[[#This Row],[DISTANCIA (km)]]*2*'ABC COSTEO'!B$21 -> 6202.8326 | M7: =Tabla8[[#This Row],[Costo Variable]]+Tabla8[[#This Row],[Costo fijo]] -> 46943.26 | N7: =Tabla8[[#This Row],[Costo Total]]*Tabla8[[#This Row],[Numero de Transportes]] -> 46943.26 | O7: =(Tabla8[[#This Row],[VLR. Transporte unitario]]-Tabla8[[#This Row],[Costo Total]])*Tabla8[[#This Row],[Numero de Transportes]] -> -6943.2604 | P7: =Tabla8[[#This Row],[Margen de productos]]+Tabla8[[#This Row],[Ganancia/Perdida]] -> 67156.74 | Q7: =(Tabla8[[#This Row],[Margen ]]/Tabla8[[#This Row],[Margen de productos]])-1 -> -0.09370122
A8: 58809 | B8: =_xlfn.XLOOKUP(Tabla8[[#This Row],[N° FACTURA]],Tabla3[N° FACTURA],Tabla3[Corregimiento],"NA") -> El Limonar | C8: =_xlfn.XLOOKUP(Tabla8[[#This Row],[N° FACTURA]],Tabla3[N° FACTURA],Tabla3[LUGAR ENVÍO],"NA") -> palo alto | D8: =_xlfn.XLOOKUP(Tabla8[[#This Row],[N° FACTURA]],Tabla3[N° FACTURA],Tabla3[DISTANCIA (km)],"NA") -> 4.476 | E8: =_xlfn.XLOOKUP(Tabla8[[#This Row],[N° FACTURA]],Tabla3[N° FACTURA],Tabla3[Numero de Transportes],"NA") -> 3 | F8: =_xlfn.XLOOKUP(Tabla8[[#This Row],[N° FACTURA]],Tabla3[N° FACTURA],Tabla3[VLR. TRANSPORTE],"NA") -> 90000 | G8: =Tabla8[[#This Row],[VLR. TRANSPORTE]]/Tabla8[[#This Row],[Numero de Transportes]] -> 30000 | H8: =_xlfn.XLOOKUP(Tabla8[[#This Row],[N° FACTURA]],Tabla3[N° FACTURA],Tabla3[VLR. TOTAL FACT.],"NA") -> 1382000 | I8: =Tabla8[[#This Row],[VLR. TOTAL FACT.]]-Tabla8[[#This Row],[VLR. TRANSPORTE]] -> 1292000 | J8: =Tabla8[[#This Row],[VLR. PRODUCTOS]]*0.2 -> 258400 | K8: ='ABC COSTEO'!B$11 -> 40740.428 | L8: =Tabla8[[#This Row],[DISTANCIA (km)]]*2*'ABC COSTEO'!B$21 -> 12178.411 | M8: =Tabla8[[#This Row],[Costo Variable]]+Tabla8[[#This Row],[Costo fijo]] -> 52918.839 | N8: =Tabla8[[#This Row],[Costo Total]]*Tabla8[[#This Row],[Numero de Transportes]] -> 158756.52 | O8: =(Tabla8[[#This Row],[VLR. Transporte unitario]]-Tabla8[[#This Row],[Costo Total]])*Tabla8[[#This Row],[Numero de Transportes]] -> -68756.517 | P8: =Tabla8[[#This Row],[Margen de productos]]+Tabla8[[#This Row],[Ganancia/Perdida]] -> 189643.48 | Q8: =(Tabla8[[#This Row],[Margen ]]/Tabla8[[#This Row],[Margen de productos]])-1 -> -0.26608559
A9: 0 | B9: =_xlfn.XLOOKUP(Tabla8[[#This Row],[N° FACTURA]],Tabla3[N° FACTURA],Tabla3[Corregimiento],"NA") -> Borrero Ayerbe | C9: =_xlfn.XLOOKUP(Tabla8[[#This Row],[N° FACTURA]],Tabla3[N° FACTURA],Tabla3[LUGAR ENVÍO],"NA") -> San Miguel | D9: =_xlfn.XLOOKUP(Tabla8[[#This Row],[N° FACTURA]],Tabla3[N° FACTURA],Tabla3[DISTANCIA (km)],"NA") -> 2.269 | E9: =_xlfn.XLOOKUP(Tabla8[[#This Row],[N° FACTURA]],Tabla3[N° FACTURA],Tabla3[Numero de Transportes],"NA") -> 1 | F9: =_xlfn.XLOOKUP(Tabla8[[#This Row],[N° FACTURA]],Tabla3[N° FACTURA],Tabla3[VLR. TRANSPORTE],"NA") -> 70000 | G9: =Tabla8[[#This Row],[VLR. TRANSPORTE]]/Tabla8[[#This Row],[Numero de Transportes]] -> 70000 | H9: =_xlfn.XLOOKUP(Tabla8[[#This Row],[N° FACTURA]],Tabla3[N° FACTURA],Tabla3[VLR. TOTAL FACT.],"NA") -> 541100 | I9: =Tabla8[[#This Row],[VLR. TOTAL FACT.]]-Tabla8[[#This Row],[VLR. TRANSPORTE]] -> 471100 | J9: =Tabla8[[#This Row],[VLR. PRODUCTOS]]*0.2 -> 94220 | K9: ='ABC COSTEO'!B$11 -> 40740.428 | L9: =Tabla8[[#This Row],[DISTANCIA (km)]]*2*'ABC COSTEO'!B$21 -> 6173.5511 | M9: =Tabla8[[#This Row],[Costo Variable]]+Tabla8[[#This Row],[Costo fijo]] -> 46913.979 | N9: =Tabla8[[#This Row],[Costo Total]]*Tabla8[[#This Row],[Numero de Transportes]] -> 46913.979 | O9: =(Tabla8[[#This Row],[VLR. Transporte unitario]]-Tabla8[[#This Row],[Costo Total]])*Tabla8[[#This Row],[Numero de Transportes]] -> 23086.021 | P9: =Tabla8[[#This Row],[Margen de productos]]+Tabla8[[#This Row],[Ganancia/Perdida]] -> 117306.02 | Q9: =(Tabla8[[#This Row],[Margen ]]/Tabla8[[#This Row],[Margen de productos]])-1 -> 0.24502251
A10: 46700 | B10: =_xlfn.XLOOKUP(Tabla8[[#This Row],[N° FACTURA]],Tabla3[N° FACTURA],Tabla3[Corregimiento],"NA") -> El Carmen | C10: =_xlfn.XLOOKUP(Tabla8[[#This Row],[N° FACTURA]],Tabla3[N° FACTURA],Tabla3[LUGAR ENVÍO],"NA") -> Parcelación Monterico | D10: =_xlfn.XLOOKUP(Tabla8[[#This Row],[N° FACTURA]],Tabla3[N° FACTURA],Tabla3[DISTANCIA (km)],"NA") -> 9.826848 | E10: =_xlfn.XLOOKUP(Tabla8[[#This Row],[N° FACTURA]],Tabla3[N° FACTURA],Tabla3[Numero de Transportes],"NA") -> 1 | F10: =_xlfn.XLOOKUP(Tabla8[[#This Row],[N° FACTURA]],Tabla3[N° FACTURA],Tabla3[VLR. TRANSPORTE],"NA") -> 50000 | G10: =Tabla8[[#This Row],[VLR. TRANSPORTE]]/Tabla8[[#This Row],[Numero de Transportes]] -> 50000 | H10: =_xlfn.XLOOKUP(Tabla8[[#This Row],[N° FACTURA]],Tabla3[N° FACTURA],Tabla3[VLR. TOTAL FACT.],"NA") -> 138500 | I10: =Tabla8[[#This Row],[VLR. TOTAL FACT.]]-Tabla8[[#This Row],[VLR. TRANSPORTE]] -> 88500 | J10: =Tabla8[[#This Row],[VLR. PRODUCTOS]]*0.2 -> 17700 | K10: ='ABC COSTEO'!B$11 -> 40740.428 | L10: =Tabla8[[#This Row],[DISTANCIA (km)]]*2*'ABC COSTEO'!B$21 -> 26737.13 | M10: =Tabla8[[#This Row],[Costo Variable]]+Tabla8[[#This Row],[Costo fijo]] -> 67477.558 | N10: =Tabla8[[#This Row],[Costo Total]]*Tabla8[[#This Row],[Numero de Transportes]] -> 67477.558 | O10: =(Tabla8[[#This Row],[VLR. Transporte unitario]]-Tabla8[[#This Row],[Costo Total]])*Tabla8[[#This Row],[Numero de Transportes]] -> -17477.558 | P10: =Tabla8[[#This Row],[Margen de productos]]+Tabla8[[#This Row],[Ganancia/Perdida]] -> 222.4421 | Q10: =(Tabla8[[#This Row],[Margen ]]/Tabla8[[#This Row],[Margen de productos]])-1 -> -0.98743265
A11: 48270 | B11: =_xlfn.XLOOKUP(Tabla8[[#This Row],[N° FACTURA]],Tabla3[N° FACTURA],Tabla3[Corregimiento],"NA") -> El Limonar | C11: =_xlfn.XLOOKUP(Tabla8[[#This Row],[N° FACTURA]],Tabla3[N° FACTURA],Tabla3[LUGAR ENVÍO],"NA") -> KM 34 | D11: =_xlfn.XLOOKUP(Tabla8[[#This Row],[N° FACTURA]],Tabla3[N° FACTURA],Tabla3[DISTANCIA (km)],"NA") -> 4.316 | E11: =_xlfn.XLOOKUP(Tabla8[[#This Row],[N° FACTURA]],Tabla3[N° FACTURA],Tabla3[Numero de Transportes],"NA") -> 1 | F11: =_xlfn.XLOOKUP(Tabla8[[#This Row],[N° FACTURA]],Tabla3[N° FACTURA],Tabla3[VLR. TRANSPORTE],"NA") -> 40000 | G11: =Tabla8[[#This Row],[VLR. TRANSPORTE]]/Tabla8[[#This Row],[Numero de Transportes]] -> 40000 | H11: =_xlfn.XLOOKUP(Tabla8[[#This Row],[N° FACTURA]],Tabla3[N° FACTURA],Tabla3[VLR. TOTAL FACT.],"NA") -> 264500 | I11: =Tabla8[[#This Row],[VLR. TOTAL FACT.]]-Tabla8[[#This Row],[VLR. TRANSPORTE]] -> 224500 | J11: =Tabla8[[#This Row],[VLR. PRODUCTOS]]*0.2 -> 44900 | K11: ='ABC COSTEO'!B$11 -> 40740.428 | L11: =Tabla8[[#This Row],[DISTANCIA (km)]]*2*'ABC COSTEO'!B$21 -> 11743.079 | M11: =Tabla8[[#This Row],[Costo Variable]]+Tabla8[[#This Row],[Costo fijo]] -> 52483.507 | N11: =Tabla8[[#This Row],[Costo Total]]*Tabla8[[#This Row],[Numero de Transportes]] -> 52483.507 | O11: =(Tabla8[[#This Row],[VLR. Transporte unitario]]-Tabla8[[#This Row],[Costo Total]])*Tabla8[[#This Row],[Numero de Transportes]] -> -12483.507 | P11: =Tabla8[[#This Row],[Margen de productos]]+Tabla8[[#This Row],[Ganancia/Perdida]] -> 32416.493 | Q11: =(Tabla8[[#This Row],[Margen ]]/Tabla8[[#This Row],[Margen de productos]])-1 -> -0.27802911
A12: 58753 | B12: =_xlfn.XLOOKUP(Tabla8[[#This Row],[N° FACTURA]],Tabla3[N° FACTURA],Tabla3[Corregimiento],"NA") -> Borrero Ayerbe | C12: =_xlfn.XLOOKUP(Tabla8[[#This Row],[N° FACTURA]],Tabla3[N° FACTURA],Tabla3[LUGAR ENVÍO],"NA") -> Cositas ricas | D12: =_xlfn.XLOOKUP(Tabla8[[#This Row],[N° FACTURA]],Tabla3[N° FACTURA],Tabla3[DISTANCIA (km)],"NA") -> 0.723 | E12: =_xlfn.XLOOKUP(Tabla8[[#This Row],[N° FACTURA]],Tabla3[N° FACTURA],Tabla3[Numero de Transportes],"NA") -> 2 | F12: =_xlfn.XLOOKUP(Tabla8[[#This Row],[N° FACTURA]],Tabla3[N° FACTURA],Tabla3[VLR. TRANSPORTE],"NA") -> 50000 | G12: =Tabla8[[#This Row],[VLR. TRANSPORTE]]/Tabla8[[#This Row],[Numero de Transportes]] -> 25000 | H12: =_xlfn.XLOOKUP(Tabla8[[#This Row],[N° FACTURA]],Tabla3[N° FACTURA],Tabla3[VLR. TOTAL FACT.],"NA") -> 1622000 | I12: =Tabla8[[#This Row],[VLR. TOTAL FACT.]]-Tabla8[[#This Row],[VLR. TRANSPORTE]] -> 1572000 | J12: =Tabla8[[#This Row],[VLR. PRODUCTOS]]*0.2 -> 314400 | K12: ='ABC COSTEO'!B$11 -> 40740.428 | L12: =Tabla8[[#This Row],[DISTANCIA (km)]]*2*'ABC COSTEO'!B$21 -> 1967.1562 | M12: =Tabla8[[#This Row],[Costo Variable]]+Tabla8[[#This Row],[Costo fijo]] -> 42707.584 | N12: =Tabla8[[#This Row],[Costo Total]]*Tabla8[[#This Row],[Numero de Transportes]] -> 85415.168 | O12: =(Tabla8[[#This Row],[VLR. Transporte unitario]]-Tabla8[[#This Row],[Costo Total]])*Tabla8[[#This Row],[Numero de Transportes]] -> -35415.168 | P12: =Tabla8[[#This Row],[Margen de productos]]+Tabla8[[#This Row],[Ganancia/Perdida]] -> 278984.83 | Q12: =(Tabla8[[#This Row],[Margen ]]/Tabla8[[#This Row],[Margen de productos]])-1 -> -0.11264366
A13: 48443 | B13: =_xlfn.XLOOKUP(Tabla8[[#This Row],[N° FACTURA]],Tabla3[N° FACTURA],Tabla3[Corregimiento],"NA") -> El Limonar | C13: =_xlfn.XLOOKUP(Tabla8[[#This Row],[N° FACTURA]],Tabla3[N° FACTURA],Tabla3[LUGAR ENVÍO],"NA") -> El chilcal | D13: =_xlfn.XLOOKUP(Tabla8[[#This Row],[N° FACTURA]],Tabla3[N° FACTURA],Tabla3[DISTANCIA (km)],"NA") -> 14.314 | E13: =_xlfn.XLOOKUP(Tabla8[[#This Row],[N° FACTURA]],Tabla3[N° FACTURA],Tabla3[Numero de Transportes],"NA") -> 1 | F13: =_xlfn.XLOOKUP(Tabla8[[#This Row],[N° FACTURA]],Tabla3[N° FACTURA],Tabla3[VLR. TRANSPORTE],"NA") -> 70000 | G13: =Tabla8[[#This Row],[VLR. TRANSPORTE]]/Tabla8[[#This Row],[Numero de Transportes]] -> 70000 | H13: =_xlfn.XLOOKUP(Tabla8[[#This Row],[N° FACTURA]],Tabla3[N° FACTURA],Tabla3[VLR. TOTAL FACT.],"NA") -> 300000 | I13: =Tabla8[[#This Row],[VLR. TOTAL FACT.]]-Tabla8[[#This Row],[VLR. TRANSPORTE]] -> 230000 | J13: =Tabla8[[#This Row],[VLR. PRODUCTOS]]*0.2 -> 46000 | K13: ='ABC COSTEO'!B$11 -> 40740.428 | L13: =Tabla8[[#This Row],[DISTANCIA (km)]]*2*'ABC COSTEO'!B$21 -> 38945.884 | M13: =Tabla8[[#This Row],[Costo Variable]]+Tabla8[[#This Row],[Costo fijo]] -> 79686.312 | N13: =Tabla8[[#This Row],[Costo Total]]*Tabla8[[#This Row],[Numero de Transportes]] -> 79686.312 | O13: =(Tabla8[[#This Row],[VLR. Transporte unitario]]-Tabla8[[#This Row],[Costo Total]])*Tabla8[[#This Row],[Numero de Transportes]] -> -9686.3116 | P13: =Tabla8[[#This Row],[Margen de productos]]+Tabla8[[#This Row],[Ganancia/Perdida]] -> 36313.688 | Q13: =(Tabla8[[#This Row],[Margen ]]/Tabla8[[#This Row],[Margen de productos]])-1 -> -0.21057199
A14: 58539 | B14: =_xlfn.XLOOKUP(Tabla8[[#This Row],[N° FACTURA]],Tabla3[N° FACTURA],Tabla3[Corregimiento],"NA") -> Borrero Ayerbe | C14: =_xlfn.XLOOKUP(Tabla8[[#This Row],[N° FACTURA]],Tabla3[N° FACTURA],Tabla3[LUGAR ENVÍO],"NA") -> La Zulia 1 | D14: =_xlfn.XLOOKUP(Tabla8[[#This Row],[N° FACTURA]],Tabla3[N° FACTURA],Tabla3[DISTANCIA (km)],"NA") -> 0.944 | E14: =_xlfn.XLOOKUP(Tabla8[[#This Row],[N° FACTURA]],Tabla3[N° FACTURA],Tabla3[Numero de Transportes],"NA") -> 1 | F14: =_xlfn.XLOOKUP(Tabla8[[#This Row],[N° FACTURA]],Tabla3[N° FACTURA],Tabla3[VLR. TRANSPORTE],"NA") -> 40000 | G14: =Tabla8[[#This Row],[VLR. TRANSPORTE]]/Tabla8[[#This Row],[Numero de Transportes]] -> 40000 | H14: =_xlfn.XLOOKUP(Tabla8[[#This Row],[N° FACTURA]],Tabla3[N° FACTURA],Tabla3[VLR. TOTAL FACT.],"NA") -> 162000 | I14: =Tabla8[[#This Row],[VLR. TOTAL FACT.]]-Tabla8[[#This Row],[VLR. TRANSPORTE]] -> 122000 | J14: =Tabla8[[#This Row],[VLR. PRODUCTOS]]*0.2 -> 24400 | K14: ='ABC COSTEO'!B$11 -> 40740.428 | L14: =Tabla8[[#This Row],[DISTANCIA (km)]]*2*'ABC COSTEO'!B$21 -> 2568.4585 | M14: =Tabla8[[#This Row],[Costo Variable]]+Tabla8[[#This Row],[Costo fijo]] -> 43308.886 | N14: =Tabla8[[#This Row],[Costo Total]]*Tabla8[[#This Row],[Numero de Transportes]] -> 43308.886 | O14: =(Tabla8[[#This Row],[VLR. Transporte unitario]]-Tabla8[[#This Row],[Costo Total]])*Tabla8[[#This Row],[Numero de Transportes]] -> -3308.8862 | P14: =Tabla8[[#This Row],[Margen de productos]]+Tabla8[[#This Row],[Ganancia/Perdida]] -> 21091.114 | Q14: =(Tabla8[[#This Row],[Margen ]]/Tabla8[[#This Row],[Margen de productos]])-1 -> -0.13561009
... A241: 48585 | B241: =_xlfn.XLOOKUP(Tabla8[[#This Row],[N° FACTURA]],Tabla3[N° FACTURA],Tabla3[Corregimiento],"NA") -> El Carmen | C241: =_xlfn.XLOOKUP(Tabla8[[#This Row],[N° FACTURA]],Tabla3[N° FACTURA],Tabla3[LUGAR ENVÍO],"NA") -> El diviso | D241: =_xlfn.XLOOKUP(Tabla8[[#This Row],[N° FACTURA]],Tabla3[N° FACTURA],Tabla3[DISTANCIA (km)],"NA") -> 8.471 | E241: =_xlfn.XLOOKUP(Tabla8[[#This Row],[N° FACTURA]],Tabla3[N° FACTURA],Tabla3[Numero de Transportes],"NA") -> 2 | F241: =_xlfn.XLOOKUP(Tabla8[[#This Row],[N° FACTURA]],Tabla3[N° FACTURA],Tabla3[VLR. TRANSPORTE],"NA") -> 80000 | G241: =Tabla8[[#This Row],[VLR. TRANSPORTE]]/Tabla8[[#This Row],[Numero de Transportes]] -> 40000 | H241: =_xlfn.XLOOKUP(Tabla8[[#This Row],[N° FACTURA]],Tabla3[N° FACTURA],Tabla3[VLR. TOTAL FACT.],"NA") -> 5520700 | I241: =Tabla8[[#This Row],[VLR. TOTAL FACT.]]-Tabla8[[#This Row],[VLR. TRANSPORTE]] -> 5440700 | J241: =Tabla8[[#This Row],[VLR. PRODUCTOS]]*0.2 -> 1088140 | K241: ='ABC COSTEO'!B$11 -> 40740.428 | L241: =Tabla8[[#This Row],[DISTANCIA (km)]]*2*'ABC COSTEO'!B$21 -> 23048.105 | M241: =Tabla8[[#This Row],[Costo Variable]]+Tabla8[[#This Row],[Costo fijo]] -> 63788.533 | N241: =Tabla8[[#This Row],[Costo Total]]*Tabla8[[#This Row],[Numero de Transportes]] -> 127577.07 | O241: =(Tabla8[[#This Row],[VLR. Transporte unitario]]-Tabla8[[#This Row],[Costo Total]])*Tabla8[[#This Row],[Numero de Transportes]] -> -47577.067 | P241: =Tabla8[[#This Row],[Margen de productos]]+Tabla8[[#This Row],[Ganancia/Perdida]] -> 1040562.9 | Q241: =(Tabla8[[#This Row],[Margen ]]/Tabla8[[#This Row],[Margen de productos]])-1 -> -0.043723295
A242: 50499 | B242: =_xlfn.XLOOKUP(Tabla8[[#This Row],[N° FACTURA]],Tabla3[N° FACTURA],Tabla3[Corregimiento],"NA") -> Borrero Ayerbe | C242: =_xlfn.XLOOKUP(Tabla8[[#This Row],[N° FACTURA]],Tabla3[N° FACTURA],Tabla3[LUGAR ENVÍO],"NA") -> La recta | D242: =_xlfn.XLOOKUP(Tabla8[[#This Row],[N° FACTURA]],Tabla3[N° FACTURA],Tabla3[DISTANCIA (km)],"NA") -> 0.935 | E242: 1 | F242: =_xlfn.XLOOKUP(Tabla8[[#This Row],[N° FACTURA]],Tabla3[N° FACTURA],Tabla3[VLR. TRANSPORTE],"NA") -> 40000 | G242: =Tabla8[[#This Row],[VLR. TRANSPORTE]]/Tabla8[[#This Row],[Numero de Transportes]] -> 40000 | H242: =_xlfn.XLOOKUP(Tabla8[[#This Row],[N° FACTURA]],Tabla3[N° FACTURA],Tabla3[VLR. TOTAL FACT.],"NA") -> 259800 | I242: =Tabla8[[#This Row],[VLR. TOTAL FACT.]]-Tabla8[[#This Row],[VLR. TRANSPORTE]] -> 219800 | J242: =Tabla8[[#This Row],[VLR. PRODUCTOS]]*0.2 -> 43960 | K242: ='ABC COSTEO'!B$11 -> 40740.428 | L242: =Tabla8[[#This Row],[DISTANCIA (km)]]*2*'ABC COSTEO'!B$21 -> 2543.971 | M242: =Tabla8[[#This Row],[Costo Variable]]+Tabla8[[#This Row],[Costo fijo]] -> 43284.399 | N242: =Tabla8[[#This Row],[Costo Total]]*Tabla8[[#This Row],[Numero de Transportes]] -> 43284.399 | O242: =(Tabla8[[#This Row],[VLR. Transporte unitario]]-Tabla8[[#This Row],[Costo Total]])*Tabla8[[#This Row],[Numero de Transportes]] -> -3284.3988 | P242: =Tabla8[[#This Row],[Margen de productos]]+Tabla8[[#This Row],[Ganancia/Perdida]] -> 40675.601 | Q242: =(Tabla8[[#This Row],[Margen ]]/Tabla8[[#This Row],[Margen de productos]])-1 -> -0.074713349
A243: =SUBTOTAL(102,Tabla8[N° FACTURA]) -> 240 | F243: =SUBTOTAL(109,Tabla8[VLR. TRANSPORTE]) -> 12915000 | G243: =SUBTOTAL(101,Tabla8[VLR. Transporte unitario]) -> 45750 | J243: =SUBTOTAL(109,Tabla8[Margen de productos]) -> 52786770 | M243: =SUBTOTAL(101,Tabla8[Costo Total]) -> 52621.971 | N243: =SUBTOTAL(109,Tabla8[Columna1]) -> 14878099 | O243: =SUM(Tabla8[Ganancia/Perdida]) -> -1963099 | Q243: =SUBTOTAL(101,Tabla8[Perdida o ganancia de margen]) -> -0.10838348
A245: Corregimiento
A246: Borrero Ayerbe | L246: =Tabla8[[#Totals],[Margen de productos]]+N246 -> 50823671 | N246: =Tabla8[[#Totals],[VLR. TRANSPORTE]]-Tabla8[[#Totals],[Columna1]] -> -1963099
A247: El Carmen | L247: =(L246-Tabla8[[#Totals],[Margen de productos]])/Tabla8[[#Totals],[Margen de productos]] -> -0.037189223
A248: El Limonar
A249: San Bernardo | L249: =Tabla8[[#Totals],[Margen de productos]]*(1+L247) -> 50823671
A250: El Queremal
A251: El Palmar
A252: El Salado
A253: VillaHermosa

Sheet Distancias
A1: Monteredondo | E1: La Zulia 1 | I1: Tierras blancas | M1: La recta | Q1: La Zulia 3 | U1: La Zulia 2 | Y1: Cositas ricas | AC1: Pa la chingada | AG1: Mirador Bellavista | AK1: Campamento Salomon | AO1: Chipre | AS1: Agua Sucia | AW1: Los bomberos | BA1: El bosque | BE1: La clorinda | BI1: El Carmelo | BM1: Tortolas | BQ1: Altos de las Tortolas | BU1: Bahondo | BY1: El diviso | CC1: Tocota | CG1: San Miguel | CK1: El palmar | CO1: KM 37 | CS1: San Fernando | CW1: KM 40 | DA1: Pirineos | DE1: KM 34 | DI1: KM 25 | DM1: Altos del Carmen | DQ1: Carmen | DU1: San Jose del Salado | DY1: El Coscorron | EC1: Parcelacion la Cristalina | EG1: El queremal | EK1: Palo alto | EO1: Azul y verde | ES1: Las villas del carmen | EW1: Parcelaón las palmas | FA1: KM 24 | FE1: Finca la cristalina | FI1: La bomba | FM1: Parcelación Monterico | FQ1: Parcelación El bosque | FU1: El limonar | FY1: KM 26 | GC1: KM 28 | GG1: KM 27 | GK1: El parque | GO1: Salida al carmen | GS1: Parcelación Ambichinte | GW1: Villa del toro | HA1: La florida | HE1: Casa verde | HI1: La cabaña | HM1: Villa emilia | HQ1: El chiringuito | HU1: Las playas | HY1: El chilcal | IC1: Panamericano | IG1: Villa saman | IK1: Saliendo del carmen | IO1: Villahermosa
A2: X | B2: Y | C2: Segmentos (KM) | E2: X | F2: Y | G2: Segmentos (KM) | I2: X | J2: Y | K2: Segmentos (KM) | M2: X | N2: Y | O2: Segmentos (KM) | Q2: X | R2: Y | S2: Segmentos (KM) | U2: X | V2: Y | W2: Segmentos (KM) | Y2: X | Z2: Y | AA2: Segmentos (KM) | AC2: X | AD2: Y | AE2: Segmentos (KM) | AG2: X | AH2: Y | AI2: Segmentos (KM) | AK2: X | AL2: Y | AM2: Segmentos (KM) | AO2: X | AP2: Y | AQ2: Segmentos (KM) | AS2: X | AT2: Y | AU2: Segmentos (KM) | AW2: X | AX2: Y | AY2: Segmentos (KM) | BA2: X | BB2: Y | BC2: Segmentos (KM) | BE2: X | BF2: Y | BG2: Segmentos (KM) | BI2: X | BJ2: Y | BK2: Segmentos (KM) | BM2: X | BN2: Y | BO2: Segmentos (KM) | BQ2: X | BR2: Y | BS2: Segmentos (KM) | BU2: X | BV2: Y | BW2: Segmentos (KM) | BY2: X | BZ2: Y | CA2: Segmentos (KM) | CC2: X | CD2: Y | CE2: Segmentos (KM) | CG2: X | CH2: Y | CI2: Segmentos (KM) | CK2: X | CL2: Y | CM2: Segmentos (KM) | CO2: X | CP2: Y | CQ2: Segmentos (KM) | CS2: X | CT2: Y | CU2: Segmentos (KM) | CW2: X | CX2: Y | CY2: Segmentos (KM) | DA2: X | DB2: Y | DC2: Segmentos (KM) | DE2: X | DF2: Y | DG2: Segmentos (KM) | DI2: X | DJ2: Y | DK2: Segmentos (KM) | DM2: X | DN2: Y | DO2: Segmentos (KM) | DQ2: X | DR2: Y | DS2: Segmentos (KM) | DU2: X | DV2: Y | DW2: Segmentos (KM) | DY2: X | DZ2: Y | EA2: Segmentos (KM) | EC2: X | ED2: Y | EE2: Segmentos (KM) | EG2: X | EH2: Y | EI2: Segmentos (KM) | EK2: X | EL2: Y | EM2: Segmentos (KM) | EO2: X | EP2: Y | EQ2: Segmentos (KM) | ES2: X | ET2: Y | EU2: Segmentos (KM) | EW2: X | EX2: Y | EY2: Segmentos (KM) | FA2: X | FB2: Y | FC2: Segmentos (KM) | FE2: X | FF2: Y | FG2: Segmentos (KM) | FI2: X | FJ2: Y | FK2: Segmentos (KM) | FM2: X | FN2: Y | FO2: Segmentos (KM) | FQ2: X | FR2: Y | FS2: Segmentos (KM) | FU2: X | FV2: Y | FW2: Segmentos (KM) | FY2: X | FZ2: Y | GA2: Segmentos (KM) | GC2: X | GD2: Y | GE2: Segmentos (KM) | GG2: X | GH2: Y | GI2: Segmentos (KM) | GK2: X | GL2: Y | GM2: Segmentos (KM) | GO2: X | GP2: Y | GQ2: Segmentos (KM) | GS2: X | GT2: Y | GU2: Segmentos (KM) | GW2: X | GX2: Y | GY2: Segmentos (KM) | HA2: X | HB2: Y | HC2: Segmentos (KM) | HE2: X | HF2: Y | HG2: Segmentos (KM) | HI2: X | HJ2: Y | HK2: Segmentos (KM) | HM2: X | HN2: Y | HO2: Segmentos (KM) | HQ2: X | HR2: Y | HS2: Segmentos (KM) | HU2: X | HV2: Y | HW2: Segmentos (KM) | HY2: X | HZ2: Y | IA2: Segmentos (KM) | IC2: X | ID2: Y | IE2: Segmentos (KM) | IG2: X | IH2: Y | II2: Segmentos (KM) | IK2: X | IL2: Y | IM2: Segmentos (KM) | IO2: X | IP2: Y | IQ2: Segmentos (KM)
A3: -8532840.5 | B3: 398186.22 | E3: -8532842.9 | F3: 398186.52 | I3: -8532840.9 | J3: 398184.21 | M3: -8532839.7 | N3: 398185.41 | Q3: -8532845.9 | R3: 398189.04 | U3: -8532826.1 | V3: 398177.56 | W3: 0.022 | Y3: -8532841.8 | Z3: 398186.17 | AC3: -8532842.4 | AD3: 398188.18 | AG3: -8532847.8 | AH3: 398189.69 | AK3: -8532844.6 | AL3: 398188.28 | AO3: -8532844.6 | AP3: 398188.28 | AS3: -8532841.6 | AT3: 398185.36 | AW3: -8532841.6 | AX3: 398185.36 | BA3: -8532841.6 | BB3: 398185.36 | BE3: -8532841.6 | BF3: 398185.36 | BI3: -8532841.6 | BJ3: 398185.36 | BM3: -8532841.6 | BN3: 398185.36 | BQ3: -8532841.6 | BR3: 398185.36 | BU3: -8532841.6 | BV3: 398185.36 | BY3: -8532841.6 | BZ3: 398185.36 | CC3: -8532841.6 | CD3: 398185.36 | CG3: -8532839.8 | CH3: 398186.52 | CK3: -8532839.8 | CL3: 398186.52 | CO3: -8532841.8 | CP3: 398186.05 | CS3: -8532841.8 | CT3: 398186.05 | CW3: -8532841.8 | CX3: 398186.05 | DA3: -8532838.6 | DB3: 398184.62 | DE3: -8532837.5 | DF3: 398184.78 | DI3: -8532840.7 | DJ3: 398185.68 | DM3: -8532841.6 | DN3: 398185.36 | DQ3: -8532841.6 | DR3: 398185.36 | DU3: -8532841.8 | DV3: 398186.05 | DY3: -8532838.8 | DZ3: 398187.04 | EC3: -8532842.6 | ED3: 398185 | EG3: -8539566.9 | EH3: 396698.21 | EK3: -8534693.9 | EL3: 399977.79 | EO3: -8532441.7 | EP3: 398824.48 | ES3: -8532579.8 | ET3: 396785.15 | EW3: -8532409.9 | EX3: 396945.14 | FA3: -8528797.3 | FB3: 395465.6 | FE3: -8533441.7 | FF3: 394620.16 | FI3: -8532271.2 | FJ3: 397709.6 | FM3: -8529458.2 | FN3: 393636.11 | FQ3: -8534145.7 | FR3: 396070.82 | FU3: -8534380.5 | FV3: 400423.85 | FY3: -8528985 | FZ3: 396421.96 | GC3: -8530126 | GD3: 396518.51 | GG3: -8529618.3 | GH3: 396449.05 | GK3: -8532288.9 | GL3: 397974.12 | GO3: -8532254.9 | GP3: 396672.85 | GS3: -8530843.1 | GT3: 397255.77 | GW3: -8531197.2 | GX3: 398390.65 | HA3: -8532455.3 | HB3: 397489.33 | HE3: -8534245.6 | HF3: 396674.22 | HI3: -8531398.8 | HJ3: 398277.02 | HM3: -8533028.8 | HN3: 396618.39 | HQ3: -8531683.3 | HR3: 397886.87 | HU3: -8532222.3 | HV3: 396866.84 | HY3: -8539634.2 | HZ3: 398738.08 | IC3: -8532200.6 | ID3: 398014.63 | IG3: -8531426.9 | IH3: 397365.6 | IK3: -8532655.5 | IL3: 395062.66 | IO3: -8535057.9 | IP3: 402022.94
A4: -8532824.8 | B4: 398176.56 | C4: 0.018 | E4: -8532825.6 | F4: 398177.66 | G4: 0.019 | I4: -8532870.3 | J4: 398199.11 | K4: 0.033 | M4: -8532871.1 | N4: 398199.91 | O4: 0.035 | Q4: -8532825 | R4: 398177.56 | S4: 0.024 | U4: -8532714.4 | V4: 398153.81 | W4: 0.114 | Y4: -8532825.7 | Z4: 398176.91 | AA4: 0.019 | AC4: -8532826.7 | AD4: 398177.72 | AE4: 0.019 | AG4: -8532824.1 | AH4: 398177.21 | AI4: 0.027 | AK4: -8532824.3 | AL4: 398176.21 | AM4: 0.024 | AO4: -8532824.3 | AP4: 398176.21 | AQ4: 0.024 | AS4: -8532825.9 | AT4: 398177.72 | AU4: 0.017 | AW4: -8532825.9 | AX4: 398177.72 | AY4: 0.017 | BA4: -8532825.9 | BB4: 398177.72 | BC4: 0.017 | BE4: -8532825.9 | BF4: 398177.72 | BG4: 0.017 | BI4: -8532825.9 | BJ4: 398177.72 | BK4: 0.017 | BM4: -8532825.9 | BN4: 398177.72 | BO4: 0.017 | BQ4: -8532825.9 | BR4: 398177.72 | BS4: 0.017 | BU4: -8532825.9 | BV4: 398177.72 | BW4: 0.017 | BY4: -8532825.9 | BZ4: 398177.72 | CA4: 0.017 | CC4: -8532825.9 | CD4: 398177.72 | CE4: 0.017 | CG4: -8532825.7 | CH4: 398177.16 | CI4: 0.017 | CK4: -8532825.7 | CL4: 398177.16 | CM4: 0.017 | CO4: -8532873.2 | CP4: 398202.1 | CQ4: 35.213 | CS4: -8532873.2 | CT4: 398202.1 | CU4: 35.213 | CW4: -8532873.2 | CX4: 398202.1 | CY4: 35.213 | DA4: -8532860.4 | DB4: 398194.94 | DC4: 24.106 | DE4: -8532862.9 | DF4: 398197.02 | DG4: 0.028 | DI4: -8532872 | DJ4: 398199.29 | DK4: 34.121 | DM4: -8532825.9 | DN4: 398177.72 | DO4: 0.017 | DQ4: -8532825.9 | DR4: 398177.72 | DS4: 0.017 | DU4: -8532873.2 | DV4: 398202.1 | DW4: 35.213 | DY4: -8532873.2 | DZ4: 398198.38 | EA4: 0.036 | EC4: -8532875.1 | ED4: 398199.97 | EE4: 0.036 | EG4: -8539589.6 | EH4: 396659.21 | EI4: 0.045 | EK4: -8534667.5 | EL4: 399954.85 | EM4: 0.035 | EO4: -8532429 | EP4: 398842.09 | EQ4: 0.022 | ES4: -8532485.8 | ET4: 396730.91 | EU4: 0.108 | EW4: -8532433.7 | EX4: 396919.34 | EY4: 0.035 | FA4: -8528819.1 | FB4: 395510.25 | FE4: -8533470.3 | FF4: 394604.82 | FG4: 0.032 | FI4: -8532271.2 | FJ4: 397800.88 | FK4: 90.498 | FM4: -8529436.4 | FN4: 393675.3 | FO4: 44.548 | FQ4: -8534118.2 | FR4: 396111 | FS4: 48.398 | FU4: -8534402.8 | FV4: 400446.18 | FW4: 0.031 | FY4: -8529028.5 | FZ4: 396432 | GA4: 0.045 | GC4: -8530207 | GD4: 396519.45 | GE4: 80.845 | GG4: -8529631.7 | GH4: 396465.3 | GI4: 20.949 | GK4: -8532337.9 | GL4: 397992.49 | GM4: 0.052 | GO4: -8532240.1 | GP4: 396704.63 | GQ4: 0.035 | GS4: -8530849.5 | GT4: 397229.98 | GU4: 0.026 | GW4: -8531261.6 | GX4: 398365.22 | GY4: 69.011 | HA4: -8532391.5 | HB4: 397535.61 | HC4: 78.466 | HE4: -8534200.4 | HF4: 396726.66 | HG4: 0.069 | HI4: -8531389.9 | HJ4: 398253.18 | HK4: 0.025 | HM4: -8532913.2 | HN4: 396421.72 | HO4: 0.227 | HQ4: -8531711.9 | HR4: 397865.86 | HS4: 0.035 | HU4: -8532222.3 | HV4: 396866.84 | HY4: -8539650.3 | HZ4: 398650.91 | IA4: 0.088 | IC4: -8532204.6 | ID4: 397991.83 | IE4: 0.023 | IG4: -8531448.3 | IH4: 397394.43 | II4: 0.036 | IK4: -8532691.7 | IL4: 395122.33 | IM4: 0.069 | IO4: -8535120.9 | IP4: 401935.78 | IQ4: 0.107
A5: -8532713.7 | B5: 398154.41 | C5: 0.113 | E5: -8532710 | F5: 398153.91 | G5: 0.118 | I5: -8532896.5 | J5: 398206.35 | K5: 0.027 | M5: -8532898.1 | N5: 398207.16 | O5: 0.028 | Q5: -8532716.5 | R5: 398154.21 | S5: 0.111 | U5: -8532671.3 | V5: 398157.03 | W5: 0.043 | Y5: -8532740.3 | Z5: 398158.39 | AA5: 0.087 | AC5: -8532797.5 | AD5: 398168.86 | AE5: 0.031 | AG5: -8532713.2 | AH5: 398154.46 | AI5: 0.113 | AK5: -8532714.6 | AL5: 398155.07 | AM5: 0.112 | AO5: -8532714.6 | AP5: 398155.07 | AQ5: 0.112 | AS5: -8532714 | AT5: 398152.35 | AU5: 0.115 | AW5: -8532714 | AX5: 398152.35 | AY5: 0.115 | BA5: -8532714 | BB5: 398152.35 | BC5: 0.115 | BE5: -8532714 | BF5: 398152.35 | BG5: 0.115 | BI5: -8532714 | BJ5: 398152.35 | BK5: 0.115 | BM5: -8532714 | BN5: 398152.35 | BO5: 0.115 | BQ5: -8532714 | BR5: 398152.35 | BS5: 0.115 | BU5: -8532714 | BV5: 398152.35 | BW5: 0.115 | BY5: -8532714 | BZ5: 398152.35 | CA5: 0.115 | CC5: -8532714 | CD5: 398152.35 | CE5: 0.115 | CG5: -8532739.3 | CH5: 398159.34 | CI5: 0.088 | CK5: -8532739.3 | CL5: 398159.34 | CM5: 0.088 | CO5: -8532894.6 | CP5: 398202.87 | CQ5: 21.417 | CS5: -8532894.6 | CT5: 398202.87 | CU5: 21.417 | CW5: -8532894.6 | CX5: 398202.87 | CY5: 21.417 | DA5: -8532898.2 | DB5: 398204.11 | DC5: 38.935 | DE5: -8532895.1 | DF5: 398205.18 | DG5: 0.033 | DI5: -8532897.8 | DJ5: 398204.73 | DK5: 26.416 | DM5: -8532714 | DN5: 398152.35 | DO5: 0.115 | DQ5: -8532714 | DR5: 398152.35 | DS5: 0.115 | DU5: -8532894.6 | DV5: 398202.87 | DW5: 21.417 | DY5: -8532895 | DZ5: 398205.64 | EA5: 0.023 | EC5: -8532904.8 | ED5: 398209.72 | EE5: 0.031 | EG5: -8539611.3 | EH5: 396658.3 | EI5: 0.022 | EK5: -8534652.5 | EL5: 399917.81 | EM5: 0.04 | EO5: -8532426.5 | EP5: 398839.03 | EQ5: 0.004 | ES5: -8532471.3 | ET5: 396741.49 | EU5: 0.018 | EW5: -8532425.8 | EX5: 396863.78 | EY5: 0.056 | FA5: -8528812.7 | FB5: 395536.54 | FC5: 0.027 | FE5: -8533526.8 | FF5: 394600.35 | FG5: 0.057 | FI5: -8532201.7 | FJ5: 397886.21 | FK5: 109.369 | FM5: -8529406.3 | FN5: 393680.51 | FO5: 30.399 | FQ5: -8534075.8 | FR5: 396132.58 | FS5: 47.434 | FU5: -8534469.8 | FV5: 400387.02 | FW5: 0.089 | FY5: -8529074.9 | FZ5: 396443.17 | GA5: 0.048 | GC5: -8530244.7 | GD5: 396501.56 | GE5: 41.575 | GG5: -8529667 | GH5: 396477.07 | GI5: 37.132 | GK5: -8532393.4 | GL5: 397990.37 | GM5: 0.055 | GO5: -8532254.9 | GP5: 396734.83 | GQ5: 0.033 | GS5: -8530833.9 | GT5: 397170.65 | GU5: 0.061 | GW5: -8531309.2 | GX5: 398336.62 | GY5: 55.397 | HA5: -8532365.7 | HB5: 397551.51 | HC5: 30.211 | HE5: -8534150.3 | HF5: 396771.16 | HG5: 0.067 | HI5: -8531454.8 | HJ5: 398195.37 | HK5: 0.087 | HM5: -8532887 | HN5: 396450.33 | HO5: 0.039 | HQ5: -8531731.5 | HR5: 397836.81 | HS5: 0.035 | HU5: -8532242.7 | HV5: 396914.45 | HW5: 0.051 | HY5: -8539721.4 | HZ5: 398587.89 | IA5: 0.095 | IC5: -8532248.9 | ID5: 397962.33 | IE5: 0.053 | IG5: -8531474.5 | IH5: 397468.18 | II5: 0.078 | IK5: -8532725.9 | IL5: 395210.84 | IM5: 0.094 | IO5: -8535107.5 | IP5: 401883.48 | IQ5: 0.054
A6: -8532629.5 | B6: 398158.44 | C6: 0.084 | E6: -8532626.9 | F6: 398157.93 | G6: 0.083 | I6: -8532906.9 | J6: 398132.27 | K6: 0.075 | M6: -8532907.3 | N6: 398134.28 | O6: 0.073 | Q6: -8532656.3 | R6: 398157.43 | S6: 0.06 | U6: -8532631.8 | V6: 398158.24 | W6: 0.039 | Y6: -8532713 | Z6: 398153.96 | AA6: 0.028 | AC6: -8532715.2 | AD6: 398155.17 | AE6: 0.083 | AG6: -8532633.2 | AH6: 398158.29 | AI6: 0.08 | AK6: -8532631.2 | AL6: 398158.69 | AM6: 0.083 | AO6: -8532631.2 | AP6: 398158.69 | AQ6: 0.083 | AS6: -8532666.5 | AT6: 398157.18 | AU6: 0.048 | AW6: -8532666.5 | AX6: 398157.18 | AY6: 0.048 | BA6: -8532666.5 | BB6: 398157.18 | BC6: 0.048 | BE6: -8532666.5 | BF6: 398157.18 | BG6: 0.048 | BI6: -8532666.5 | BJ6: 398157.18 | BK6: 0.048 | BM6: -8532666.5 | BN6: 398157.18 | BO6: 0.048 | BQ6: -8532666.5 | BR6: 398157.18 | BS6: 0.048 | BU6: -8532666.5 | BV6: 398157.18 | BW6: 0.048 | BY6: -8532666.5 | BZ6: 398157.18 | CA6: 0.048 | CC6: -8532666.5 | CD6: 398157.18 | CE6: 0.048 | CG6: -8532713 | CH6: 398153.91 | CI6: 0.027 | CK6: -8532713 | CL6: 398153.91 | CM6: 0.027 | CO6: -8532907.6 | CP6: 398133.31 | CQ6: 70.765 | CS6: -8532907.6 | CT6: 398133.31 | CU6: 70.765 | CW6: -8532907.6 | CX6: 398133.31 | CY6: 70.765 | DA6: -8532910.8 | DB6: 398124.42 | DC6: 80.682 | DE6: -8532907.8 | DF6: 398133.53 | DG6: 0.073 | DI6: -8532907.8 | DJ6: 398127.64 | DK6: 77.738 | DM6: -8532666.5 | DN6: 398157.18 | DO6: 0.048 | DQ6: -8532666.5 | DR6: 398157.18 | DS6: 0.048 | DU6: -8532907.6 | DV6: 398133.31 | DW6: 70.765 | DY6: -8532907.7 | DZ6: 398129.45 | EA6: 0.077 | EC6: -8532906.1 | ED6: 398133.53 | EE6: 0.076 | EG6: -8539676.6 | EH6: 396699.12 | EI6: 0.077 | EK6: -8534637.5 | EL6: 399886.95 | EM6: 0.034 | EO6: -8532388.3 | EP6: 398817.53 | EQ6: 0.044 | ES6: -8532455.4 | ET6: 396771.92 | EU6: 0.034 | EW6: -8532449.6 | EX6: 396855.84 | EY6: 0.025 | FA6: -8528785.4 | FB6: 395583.67 | FC6: 0.054 | FE6: -8533590.8 | FF6: 394646.49 | FG6: 0.079 | FI6: -8532342.6 | FJ6: 397991.38 | FK6: 175.059 | FM6: -8529356 | FN6: 393675.55 | FO6: 50.498 | FQ6: -8533900.2 | FR6: 396188.39 | FS6: 183.807 | FU6: -8534479.8 | FV6: 400366.93 | FW6: 0.022 | FY6: -8529124.5 | FZ6: 396432.56 | GA6: 0.051 | GC6: -8530285.2 | GD6: 396496.38 | GE6: 40.745 | GG6: -8529698.5 | GH6: 396475.19 | GI6: 31.545 | GK6: -8532472.9 | GL6: 397959.29 | GM6: 0.085 | GO6: -8532270.3 | GP6: 396765.56 | GQ6: 0.034 | GS6: -8530815.6 | GT6: 397119.79 | GU6: 0.054 | GW6: -8531368.8 | GX6: 398274.63 | GY6: 85.524 | HA6: -8532331.3 | HB6: 397554.88 | HC6: 34.465 | HE6: -8534085.9 | HF6: 396802.16 | HG6: 0.071 | HI6: -8531476.3 | HJ6: 398179.28 | HK6: 0.027 | HM6: -8532859.6 | HN6: 396545.68 | HO6: 0.098 | HQ6: -8531746.7 | HR6: 397829.66 | HS6: 0.017 | HU6: -8532251.2 | HV6: 396974.12 | HW6: 0.06 | HY6: -8539701.3 | HZ6: 398504.75 | IA6: 0.085 | IC6: -8532268.3 | ID6: 397940.87 | IE6: 0.029 | IG6: -8531507.3 | IH6: 397501.04 | II6: 0.046 | IK6: -8532762.1 | IL6: 395280.57 | IM6: 0.078 | IO6: -8535036.4 | IP6: 401794.98 | IQ6: 0.113
A7: -8532576.8 | B7: 398174.14 | C7: 0.055 | E7: -8532575.4 | F7: 398173.23 | G7: 0.054 | I7: -8532911.4 | J7: 398096.83 | K7: 0.036 | M7: -8532911.8 | N7: 398097.64 | O7: 0.037 | Q7: -8532627.5 | R7: 398158.24 | S7: 0.029 | U7: -8532575.8 | V7: 398173.64 | W7: 0.058 | Y7: -8532626.4 | Z7: 398158.39 | AA7: 0.087 | AC7: -8532649.5 | AD7: 398158.39 | AE7: 0.066 | AG7: -8532612.9 | AH7: 398161.31 | AI7: 0.021 | AK7: -8532614.1 | AL7: 398161.1 | AM7: 0.017 | AO7: -8532614.1 | AP7: 398161.1 | AQ7: 0.017 | AS7: -8532621.4 | AT7: 398159.19 | AU7: 0.045 | AW7: -8532621.4 | AX7: 398159.19 | AY7: 0.045 | BA7: -8532621.4 | BB7: 398159.19 | BC7: 0.045 | BE7: -8532621.4 | BF7: 398159.19 | BG7: 0.045 | BI7: -8532621.4 | BJ7: 398159.19 | BK7: 0.045 | BM7: -8532621.4 | BN7: 398159.19 | BO7: 0.045 | BQ7: -8532621.4 | BR7: 398159.19 | BS7: 0.045 | BU7: -8532621.4 | BV7: 398159.19 | BW7: 0.045 | BY7: -8532621.4 | BZ7: 398159.19 | CA7: 0.045 | CC7: -8532621.4 | CD7: 398159.19 | CE7: 0.045 | CG7: -8532666.5 | CH7: 398158.14 | CI7: 0.047 | CK7: -8532666.5 | CL7: 398158.14 | CM7: 0.047 | CO7: -8532912.9 | CP7: 398095.09 | CQ7: 38.594 | CS7: -8532912.9 | CT7: 398095.09 | CU7: 38.594 | CW7: -8532912.9 | CX7: 398095.09 | CY7: 38.594 | DA7: -8532912 | DB7: 398093.46 | DC7: 30.98 | DE7: -8532911.9 | DF7: 398095.44 | DG7: 0.038 | DI7: -8532912.8 | DJ7: 398095.44 | DK7: 32.583 | DM7: -8532621.4 | DN7: 398159.19 | DO7: 0.045 | DQ7: -8532621.4 | DR7: 398159.19 | DS7: 0.045 | DU7: -8532912.9 | DV7: 398095.09 | DW7: 38.594 | DY7: -8532912.2 | DZ7: 398094.98 | EA7: 0.035 | EC7: -8532909.1 | ED7: 398112.67 | EE7: 0.021 | EG7: -8539818.1 | EH7: 396686.42 | EI7: 0.142 | EK7: -8534613.7 | EL7: 399875.48 | EM7: 0.026 | EO7: -8532237.9 | EP7: 398719.14 | EQ7: 0.179 | ES7: -8532257 | ET7: 396666.09 | EU7: 0.224 | EW7: -8532499.2 | EX7: 396901.48 | EY7: 0.067 | FA7: -8528810.2 | FB7: 395654.12 | FC7: 0.074 | FE7: -8533671.2 | FF7: 394661.37 | FG7: 0.082 | FI7: -8532414 | FJ7: 397991.38 | FK7: 71.3 | FM7: -8529327.5 | FN7: 393695.4 | FO7: 34.608 | FQ7: -8533740.2 | FR7: 396253.13 | FS7: 172.101 | FU7: -8534439.7 | FV7: 400264.23 | FW7: 0.109 | FY7: -8529169.2 | FZ7: 396450.42 | GA7: 0.048 | GC7: -8530302.6 | GD7: 396455.88 | GE7: 43.755 | GG7: -8529721.6 | GH7: 396453.29 | GI7: 31.649 | GK7: -8532512.4 | GL7: 397933.86 | GM7: 0.047 | GO7: -8532252.8 | GP7: 396796.81 | GQ7: 0.036 | GS7: -8530786.6 | GT7: 397094.36 | GU7: 0.038 | GW7: -8531471.3 | GX7: 398180.87 | GY7: 138.238 | HA7: -8532294 | HB7: 397575.74 | HC7: 42.629 | HE7: -8534033.5 | HF7: 396818.84 | HG7: 0.055 | HI7: -8531507.9 | HJ7: 398169.15 | HK7: 0.033 | HM7: -8532858.4 | HN7: 396633.89 | HO7: 0.087 | HQ7: -8531768.2 | HR7: 397833.68 | HS7: 0.022 | HU7: -8532268.1 | HV7: 397043.85 | HW7: 0.071 | HY7: -8539708 | HZ7: 398410.88 | IA7: 0.093 | IC7: -8532327.3 | ID7: 397985.8 | IE7: 0.074 | IG7: -8531591.1 | IH7: 397544.62 | II7: 0.094 | IK7: -8532843.3 | IL7: 395454.89 | IM7: 0.191 | IO7: -8534978.7 | IP7: 401699.77 | IQ7: 0.111
A8: -8532561.9 | B8: 398175.35 | C8: 0.015 | E8: -8532561.9 | F8: 398175.25 | G8: 0.014 | I8: -8532909.8 | J8: 398085.96 | K8: 0.011 | M8: -8532909.4 | N8: 398087.57 | O8: 0.01 | Q8: -8532613.8 | R8: 398161.86 | S8: 0.014 | U8: -8532562.3 | V8: 398175.95 | W8: 0.014 | Y8: -8532575.7 | Z8: 398173.28 | AA8: 0.053 | AC8: -8532619.3 | AD8: 398159.59 | AE8: 0.03 | AG8: -8532576.1 | AH8: 398173.79 | AI8: 0.039 | AK8: -8532576.1 | AL8: 398173.39 | AM8: 0.04 | AO8: -8532576.1 | AP8: 398173.39 | AQ8: 0.04 | AS8: -8532577.9 | AT8: 398171.67 | AU8: 0.045 | AW8: -8532577.9 | AX8: 398171.67 | AY8: 0.045 | BA8: -8532577.9 | BB8: 398171.67 | BC8: 0.045 | BE8: -8532577.9 | BF8: 398171.67 | BG8: 0.045 | BI8: -8532577.9 | BJ8: 398171.67 | BK8: 0.045 | BM8: -8532577.9 | BN8: 398171.67 | BO8: 0.045 | BQ8: -8532577.9 | BR8: 398171.67 | BS8: 0.045 | BU8: -8532577.9 | BV8: 398171.67 | BW8: 0.045 | BY8: -8532577.9 | BZ8: 398171.67 | CA8: 0.045 | CC8: -8532577.9 | CD8: 398171.67 | CE8: 0.045 | CG8: -8532627.5 | CH8: 398157.83 | CI8: 0.039 | CK8: -8532627.5 | CL8: 398157.83 | CM8: 0.039 | CO8: -8532908.3 | CP8: 398084.38 | CQ8: 11.643 | CS8: -8532908.3 | CT8: 398084.38 | CU8: 11.643 | CW8: -8532908.3 | CX8: 398084.38 | CY8: 11.643 | DA8: -8532907.4 | DB8: 398085.43 | DC8: 9.244 | DE8: -8532909.6 | DF8: 398088.64 | DG8: 0.007 | DI8: -8532909.2 | DJ8: 398086.37 | DK8: 9.769 | DM8: -8532577.9 | DN8: 398171.67 | DO8: 0.045 | DQ8: -8532577.9 | DR8: 398171.67 | DS8: 0.045 | DU8: -8532908.3 | DV8: 398084.38 | DW8: 11.643 | DY8: -8532909.1 | DZ8: 398085.01 | EA8: 0.01 | EC8: -8532912 | ED8: 398093.17 | EE8: 0.02 | EG8: -8539887 | EH8: 396649.23 | EI8: 0.078 | EK8: -8534579.3 | EL8: 399867.54 | EM8: 0.035 | EO8: -8532207.5 | EP8: 398664.9 | EQ8: 0.062 | ES8: -8532241.1 | ET8: 396712.39 | EU8: 0.049 | EW8: -8532562.7 | EX8: 396955.06 | EY8: 0.083 | FA8: -8528790.8 | FB8: 395672.97 | FC8: 0.027 | FE8: -8533631 | FF8: 394743.23 | FG8: 0.091 | FI8: -8532487.5 | FJ8: 397949.71 | FK8: 84.124 | FM8: -8529322.8 | FN8: 393710.03 | FO8: 15.253 | FQ8: -8533672.4 | FR8: 396260.57 | FS8: 67.989 | FU8: -8534434.1 | FV8: 400145.92 | FW8: 0.117 | FY8: -8529213.8 | FZ8: 396487.26 | GA8: 0.058 | GC8: -8530311.6 | GD8: 396439.87 | GE8: 18.213 | GG8: -8529724.4 | GH8: 396419.86 | GI8: 33.267 | GK8: -8532561.9 | GL8: 397916.21 | GM8: 0.052 | GO8: -8532222.6 | GP8: 396818 | GQ8: 0.037 | GS8: -8530753.4 | GT8: 397085.18 | GU8: 0.034 | GW8: -8531515.8 | GX8: 398161.79 | GY8: 48.271 | HA8: -8532279.7 | HB8: 397603.95 | HC8: 31.401 | HE8: -8533981 | HF8: 396818.05 | HG8: 0.052 | HI8: -8531522.8 | HJ8: 398143.52 | HK8: 0.029 | HM8: -8532895.3 | HN8: 396688.72 | HO8: 0.066 | HQ8: -8531791.9 | HR8: 397842.17 | HS8: 0.025 | HU8: -8532283.3 | HV8: 397105.54 | HW8: 0.063 | HY8: -8539677.1 | HZ8: 398334.45 | IA8: 0.082 | IC8: -8532434.6 | ID8: 397982.44 | IE8: 0.107 | IG8: -8531640.7 | IH8: 397560.71 | II8: 0.052 | IK8: -8532864.7 | IL8: 395489.76 | IM8: 0.041 | IO8: -8534935.8 | IP8: 401621.99 | IQ8: 0.088
A9: -8532542.1 | B9: 398154.81 | C9: 0.028 | E9: -8532590.7 | F9: 398229.51 | G9: 0.061 | I9: -8532887.2 | J9: 398076.7 | K9: 0.024 | M9: -8532900.1 | N9: 398081.93 | O9: 0.011 | Q9: -8532576.6 | R9: 398172.73 | S9: 0.039 | U9: -8532571.7 | V9: 398190.5 | W9: 0.017 | Y9: -8532561.2 | Z9: 398174.09 | AA9: 0.015 | AC9: -8532576.7 | AD9: 398174.49 | AE9: 0.045 | AG9: -8532563.2 | AH9: 398175 | AI9: 0.013 | AK9: -8532562 | AL9: 398175 | AM9: 0.014 | AO9: -8532562 | AP9: 398175 | AQ9: 0.014 | AS9: -8532561.4 | AT9: 398174.09 | AU9: 0.017 | AW9: -8532561.4 | AX9: 398174.09 | AY9: 0.017 | BA9: -8532561.4 | BB9: 398174.09 | BC9: 0.017 | BE9: -8532561.4 | BF9: 398174.09 | BG9: 0.017 | BI9: -8532561.4 | BJ9: 398174.09 | BK9: 0.017 | BM9: -8532561.4 | BN9: 398174.09 | BO9: 0.017 | BQ9: -8532561.4 | BR9: 398174.09 | BS9: 0.017 | BU9: -8532561.4 | BV9: 398174.09 | BW9: 0.017 | BY9: -8532561.4 | BZ9: 398174.09 | CA9: 0.017 | CC9: -8532561.4 | CD9: 398174.09 | CE9: 0.017 | CG9: -8532575.6 | CH9: 398174.14 | CI9: 0.054 | CK9: -8532575.6 | CL9: 398174.14 | CM9: 0.054 | CO9: -8532748.6 | CP9: 398049.98 | CQ9: 163.424 | CS9: -8532748.6 | CT9: 398049.98 | CU9: 163.424 | CW9: -8532748.6 | CX9: 398049.98 | CY9: 163.424 | DA9: -8532755.4 | DB9: 398049.89 | DC9: 156.03 | DE9: -8532895.6 | DF9: 398081.83 | DG9: 0.016 | DI9: -8532788.6 | DJ9: 398054.62 | DK9: 124.738 | DM9: -8532561.4 | DN9: 398174.09 | DO9: 0.017 | DQ9: -8532561.4 | DR9: 398174.09 | DS9: 0.017 | DU9: -8532748.6 | DV9: 398049.98 | DW9: 163.424 | DY9: -8532755.8 | DZ9: 398048.27 | EA9: 0.158 | EC9: -8532908.8 | ED9: 398084.78 | EE9: 0.009 | EG9: -8539908.8 | EH9: 396645.6 | EI9: 0.022 | EK9: -8534535.2 | EL9: 399863.13 | EM9: 0.044 | EO9: -8532178.4 | EP9: 398611.98 | EQ9: 0.06 | ES9: -8532268.9 | ET9: 396762.66 | EU9: 0.057 | EW9: -8532570.7 | EX9: 397072.14 | EY9: 0.116 | FA9: -8528747.5 | FB9: 395701.49 | FC9: 0.052 | FE9: -8533564.1 | FF9: 394859.31 | FG9: 0.133 | FI9: -8532543 | FJ9: 397919.94 | FK9: 62.818 | FM9: -8529353.5 | FN9: 393771.05 | FO9: 67.842 | FQ9: -8533580.2 | FR9: 396373.68 | FS9: 145.111 | FU9: -8534430.7 | FV9: 400066.67 | FW9: 0.079 | FY9: -8529231.7 | FZ9: 396539.16 | GA9: 0.054 | GC9: -8530330.4 | GD9: 396445.99 | GE9: 19.755 | GG9: -8529736.4 | GH9: 396397.25 | GI9: 25.413 | GK9: -8532749.7 | GL9: 397914.09 | GM9: 0.188 | GO9: -8532220.5 | GP9: 396845.02 | GQ9: 0.027 | GS9: -8530689.8 | GT9: 397098.6 | GU9: 0.065 | GW9: -8531536.5 | GX9: 398127.62 | GY9: 39.659 | HA9: -8532282.9 | HB9: 397655.21 | HC9: 50.914 | HE9: -8533942.9 | HF9: 396856.98 | HG9: 0.054 | HI9: -8531532.3 | HJ9: 398131.6 | HK9: 0.015 | HM9: -8533008.6 | HN9: 396790.04 | HO9: 0.151 | HQ9: -8531810.2 | HR9: 397835.02 | HS9: 0.02 | HU9: -8532262.8 | HV9: 397161.86 | HW9: 0.059 | HY9: -8539752.2 | HZ9: 398290.2 | IA9: 0.087 | IC9: -8532519.7 | ID9: 397932.16 | IE9: 0.099 | IG9: -8531662.2 | IH9: 397591.55 | II9: 0.037 | IK9: -8532884.8 | IL9: 395556.8 | IM9: 0.069 | IO9: -8534803.1 | IP9: 401545.56 | IQ9: 0.153
A10: -8532480.5 | B10: 398194.27 | C10: 0.073 | E10: -8532659.5 | F10: 398321.71 | G10: 0.115 | I10: -8532759.6 | J10: 398050.12 | K10: 0.13 | M10: -8532756.7 | N10: 398048.51 | O10: 0.147 | Q10: -8532562.3 | R10: 398175.55 | S10: 0.015 | U10: -8532589.6 | V10: 398230.97 | W10: 0.044 | Y10: -8532509.6 | Z10: 398121.74 | AA10: 0.073 | AC10: -8532560.6 | AD10: 398176.1 | AE10: 0.016 | AG10: -8532503.4 | AH10: 398116.21 | AI10: 0.084 | AK10: -8532541.6 | AL10: 398154.06 | AM10: 0.029 | AO10: -8532541.6 | AP10: 398154.06 | AQ10: 0.029 | AS10: -8532541.6 | AT10: 398153.76 | AU10: 0.028 | AW10: -8532541.6 | AX10: 398153.76 | AY10: 0.028 | BA10: -8532541.6 | BB10: 398153.76 | BC10: 0.028 | BE10: -8532541.6 | BF10: 398153.76 | BG10: 0.028 | BI10: -8532541.6 | BJ10: 398153.76 | BK10: 0.028 | BM10: -8532541.6 | BN10: 398153.76 | BO10: 0.028 | BQ10: -8532541.6 | BR10: 398153.76 | BS10: 0.028 | BU10: -8532541.6 | BV10: 398153.76 | BW10: 0.028 | BY10: -8532541.6 | BZ10: 398153.76 | CA10: 0.028 | CC10: -8532541.6 | CD10: 398153.76 | CE10: 0.028 | CG10: -8532561.4 | CH10: 398174.14 | CI10: 0.014 | CK10: -8532561.4 | CL10: 398174.14 | CM10: 0.014 | CO10: -8532727.9 | CP10: 398049.22 | CQ10: 20.653 | CS10: -8532727.9 | CT10: 398049.22 | CU10: 20.653 | CW10: -8532727.9 | CX10: 398049.22 | CY10: 20.653 | DA10: -8532727.3 | DB10: 398046.45 | DC10: 28.302 | DE10: -8532755.9 | DF10: 398048.27 | DG10: 0.144 | DI10: -8532750 | DJ10: 398048.27 | DK10: 39.067 | DM10: -8532541.6 | DN10: 398153.76 | DO10: 0.028 | DQ10: -8532541.6 | DR10: 398153.76 | DS10: 0.028 | DU10: -8532727.9 | DV10: 398049.22 | DW10: 20.653 | DY10: -8532726.8 | DZ10: 398049.64 | EA10: 0.029 | EC10: -8532896.8 | ED10: 398080.93 | EE10: 0.013 | EG10: -8539927.9 | EH10: 396665.56 | EI10: 0.028 | EK10: -8534504.3 | EL10: 399849.9 | EM10: 0.033 | EO10: -8532153.3 | EP10: 398576.27 | EQ10: 0.043 | ES10: -8532258.3 | ET10: 396789.12 | EU10: 0.028 | EW10: -8532656 | EX10: 397191.2 | EY10: 0.146 | FA10: -8528709.3 | FB10: 395710.42 | FC10: 0.039 | FE10: -8533543.2 | FF10: 394914.38 | FG10: 0.058 | FI10: -8532662.1 | FJ10: 397912.01 | FK10: 119.093 | FM10: -8529383.3 | FN10: 393798.83 | FO10: 40.513 | FQ10: -8533288.5 | FR10: 396378.15 | FS10: 291.178 | FU10: -8534411.7 | FV10: 399897 | FW10: 0.169 | FY10: -8529271.3 | FZ10: 396546.97 | GA10: 0.04 | GC10: -8530358.7 | GD10: 396489.31 | GE10: 51.382 | GG10: -8529759.8 | GH10: 396391.6 | GI10: 23.93 | GK10: -8532730 | GL10: 397987.55 | GM10: 0.075 | GO10: -8532243.8 | GP10: 396909.12 | GQ10: 0.068 | GS10: -8530646.1 | GT10: 397105.66 | GU10: 0.044 | GW10: -8531582.6 | GX10: 398122.86 | GY10: 46.243 | HA10: -8532261.4 | HB10: 397696.53 | HC10: 46.226 | HE10: -8533941.3 | HF10: 396895.92 | HG10: 0.039 | HI10: -8531584.2 | HJ10: 398119.68 | HK10: 0.053 | HM10: -8533018.1 | HN10: 396819.84 | HO10: 0.031 | HQ10: -8531836.1 | HR10: 397818.03 | HS10: 0.031 | HU10: -8532259.2 | HV10: 397243.21 | HW10: 0.081 | HY10: -8539754.9 | HZ10: 398243.26 | IA10: 0.047 | IC10: -8532570.7 | ID10: 397918.08 | IE10: 0.053 | IG10: -8531650.1 | IH10: 397621.05 | II10: 0.032 | IK10: -8532879.5 | IL10: 395669.45 | IM10: 0.112 | IO10: -8534777.6 | IP10: 401541.53 | IQ10: 0.026
A11: -8532455.6 | B11: 398160.85 | C11: 0.042 | E11: -8532672.8 | F11: 398371.44 | G11: 0.051 | I11: -8532729.8 | J11: 398049.72 | K11: 0.03 | M11: -8532730.2 | N11: 398050.93 | O11: 0.027 | Q11: -8532590.4 | R11: 398231.32 | S11: 0.062 | U11: -8532659.3 | V11: 398321.16 | W11: 0.114 | Y11: -8532462.1 | Z11: 398066.58 | AA11: 0.073 | AC11: -8532482.8 | AD11: 398092.35 | AE11: 0.114 | AG11: -8532481.2 | AH11: 398092.25 | AI11: 0.033 | AK11: -8532482.4 | AL11: 398093.46 | AM11: 0.085 | AO11: -8532482.4 | AP11: 398093.46 | AQ11: 0.085 | AS11: -8532507.2 | AT11: 398120.34 | AU11: 0.048 | AW11: -8532507.2 | AX11: 398120.34 | AY11: 0.048 | BA11: -8532507.2 | BB11: 398120.34 | BC11: 0.048 | BE11: -8532507.2 | BF11: 398120.34 | BG11: 0.048 | BI11: -8532507.2 | BJ11: 398120.34 | BK11: 0.048 | BM11: -8532507.2 | BN11: 398120.34 | BO11: 0.048 | BQ11: -8532507.2 | BR11: 398120.34 | BS11: 0.048 | BU11: -8532507.2 | BV11: 398120.34 | BW11: 0.048 | BY11: -8532507.2 | BZ11: 398120.34 | CA11: 0.048 | CC11: -8532507.2 | CD11: 398120.34 | CE11: 0.048 | CG11: -8532483.2 | CH11: 398093.51 | CI11: 0.112 | CK11: -8532483.2 | CL11: 398093.51 | CM11: 0.112 | CO11: -8532733.3 | CP11: 398037.75 | CQ11: 12.653 | CS11: -8532733.3 | CT11: 398037.75 | CU11: 12.653 | CW11: -8532733.3 | CX11: 398037.75 | CY11: 12.653 | DA11: -8532730.8 | DB11: 398040.14 | DC11: 7.184 | DE11: -8532727.3 | DF11: 398049.18 | DG11: 0.029 | DI11: -8532724.6 | DJ11: 398048.27 | DK11: 25.396 | DM11: -8532507.2 | DN11: 398120.34 | DO11: 0.048 | DQ11: -8532507.2 | DR11: 398120.34 | DS11: 0.048 | DU11: -8532733.3 | DV11: 398037.75 | DW11: 12.653 | DY11: -8532731.7 | DZ11: 398040.57 | EA11: 0.01 | EC11: -8532780.3 | ED11: 398052.81 | EE11: 0.12 | EG11: -8539920.6 | EH11: 396683.7 | EI11: 0.02 | EK11: -8534440.8 | EL11: 399745.83 | EM11: 0.121 | EO11: -8532104.3 | EP11: 398539.22 | EQ11: 0.061 | ES11: -8532219.9 | ET11: 396823.51 | EU11: 0.051 | EW11: -8532711.6 | EX11: 397230.89 | EY11: 0.068 | FA11: -8528681 | FB11: 395708.44 | FC11: 0.028 | FE11: -8533543.2 | FF11: 394938.19 | FG11: 0.024 | FI11: -8532749.4 | FJ11: 397913.99 | FK11: 87.166 | FM11: -8529365.4 | FN11: 393814.71 | FO11: 23.78 | FQ11: -8533230.4 | FR11: 396381.12 | FS11: 58.007 | FU11: -8534402.8 | FV11: 399798.78 | FW11: 0.098 | FY11: -8529301.5 | FZ11: 396510.14 | GA11: 0.047 | GC11: -8530386 | GD11: 396517.57 | GE11: 39.087 | GG11: -8529797.4 | GH11: 396409.5 | GI11: 41.575 | GK11: -8532708.8 | GL11: 398029.22 | GM11: 0.046 | GO11: -8532251.8 | GP11: 396992.3 | GQ11: 0.083 | GS11: -8530619.2 | GT11: 397081.65 | GU11: 0.036 | GW11: -8531603.2 | GX11: 398070.41 | GY11: 55.936 | HA11: -8532272.5 | HB11: 397759.31 | HC11: 63.221 | HE11: -8533901.6 | HF11: 396914.99 | HG11: 0.044 | HI11: -8531606.2 | HJ11: 398057.7 | HK11: 0.065 | HM11: -8532977.6 | HN11: 396880.63 | HO11: 0.073 | HQ11: -8531858 | HR11: 397802.84 | HS11: 0.027 | HU11: -8532207.4 | HV11: 397264.22 | HW11: 0.056 | HY11: -8539726.8 | HZ11: 398174.87 | IA11: 0.073 | IC11: -8532719.5 | ID11: 397903.33 | IE11: 0.149 | IG11: -8531666.2 | IH11: 397662.62 | II11: 0.044 | IK11: -8532880.8 | IL11: 395775.38 | IM11: 0.105 | IO11: -8534762.8 | IP11: 401499.96 | IQ11: 0.044
A12: -8532411.7 | B12: 398173.74 | E12: -8532700.6 | F12: 398414.12 | G12: 0.051 | I12: -8532727.4 | J12: 398045.69 | K12: 0.005 | M12: -8532727.8 | N12: 398044.89 | O12: 0.007 | Q12: -8532659.2 | R12: 398322.52 | S12: 0.114 | U12: -8532674.4 | V12: 398373.91 | W12: 0.055 | Y12: -8532450.4 | Z12: 398030.34 | AA12: 0.038 | AC12: -8532462.3 | AD12: 398067.39 | AE12: 0.032 | AG12: -8532462.5 | AH12: 398066.48 | AI12: 0.032 | AK12: -8532462.3 | AL12: 398066.08 | AM12: 0.034 | AO12: -8532462.3 | AP12: 398066.08 | AQ12: 0.034 | AS12: -8532461.7 | AT12: 398067.59 | AU12: 0.07 | AW12: -8532461.7 | AX12: 398067.59 | AY12: 0.07 | BA12: -8532461.7 | BB12: 398067.59 | BC12: 0.07 | BE12: -8532461.7 | BF12: 398067.59 | BG12: 0.07 | BI12: -8532461.7 | BJ12: 398067.59 | BK12: 0.07 | BM12: -8532461.7 | BN12: 398067.59 | BO12: 0.07 | BQ12: -8532461.7 | BR12: 398067.59 | BS12: 0.07 | BU12: -8532461.7 | BV12: 398067.59 | BW12: 0.07 | BY12: -8532461.7 | BZ12: 398067.59 | CA12: 0.07 | CC12: -8532461.7 | CD12: 398067.59 | CE12: 0.07 | CG12: -8532460.2 | CH12: 398064.52 | CI12: 0.037 | CK12: -8532460.2 | CL12: 398064.52 | CM12: 0.037 | CO12: -8532731.7 | CP12: 398026.29 | CQ12: 11.568 | CS12: -8532731.7 | CT12: 398026.29 | CU12: 11.568 | CW12: -8532731.7 | CX12: 398026.29 | CY12: 11.568 | DA12: -8532733.1 | DB12: 398025.24 | DC12: 15.081 | DE12: -8532731.9 | DF12: 398040.11 | DG12: 0.01 | DI12: -8532731.4 | DJ12: 398039.66 | DK12: 10.978 | DM12: -8532461.7 | DN12: 398067.59 | DO12: 0.07 | DQ12: -8532461.7 | DR12: 398067.59 | DS12: 0.07 | DU12: -8532731.7 | DV12: 398026.29 | DW12: 11.568 | DY12: -8532733.6 | DZ12: 398027.87 | EA12: 0.013 | EC12: -8532753.1 | ED12: 398048.73 | EE12: 0.028 | EG12: -8539881.6 | EH12: 396725.42 | EI12: 0.057 | EK12: -8534404.7 | EL12: 399684.98 | EM12: 0.07 | EO12: -8532101.7 | EP12: 398458.53 | EQ12: 0.08 | ES12: -8532247.7 | ET12: 396953.16 | EU12: 0.131 | EW12: -8532710.6 | EX12: 397266.61 | EY12: 0.035 | FA12: -8528662.7 | FB12: 395717.24 | FC12: 0.02 | FE12: -8533595.3 | FF12: 395003.68 | FG12: 0.083 | FI12: -8532747.9 | FJ12: 397927.39 | FK12: 13.362 | FM12: -8529296 | FN12: 393814.71 | FO12: 69.322 | FQ12: -8533167.9 | FR12: 396349.87 | FS12: 69.659 | FU12: -8534426.3 | FV12: 399716.17 | FW12: 0.085 | FY12: -8529319.9 | FZ12: 396481.67 | GA12: 0.034 | GC12: -8530396.8 | GD12: 396591.03 | GE12: 73.629 | GG12: -8529815.3 | GH12: 396418.44 | GI12: 19.942 | GK12: -8532684.8 | GL12: 398026.4 | GM12: 0.024 | GO12: -8532281.4 | GP12: 397072.82 | GQ12: 0.085 | GS12: -8530619.2 | GT12: 397052.69 | GU12: 0.029 | GW12: -8531627.1 | GX12: 397955.98 | GY12: 115.915 | HA12: -8532264.6 | HB12: 397830.03 | HC12: 70.564 | HE12: -8533847.5 | HF12: 396907.84 | HG12: 0.054 | HI12: -8531614.6 | HJ12: 398010.61 | HK12: 0.047 | HM12: -8532976.4 | HN12: 396935.46 | HO12: 0.054 | HQ12: -8531924.2 | HR12: 397814.46 | HS12: 0.067 | HU12: -8532198.4 | HV12: 397274.05 | HW12: 0.013 | HY12: -8539801.9 | HZ12: 397987.14 | IA12: 0.201 | IC12: -8532747.7 | ID12: 397912.71 | IE12: 0.03 | IG12: -8531689 | IH12: 397677.37 | II12: 0.027 | IK12: -8532896.9 | IL12: 395870.59 | IM12: 0.096 | IO12: -8534722.6 | IP12: 401459.73 | IQ12: 0.057
C13: =SUM(C3:C12) -> 0.428 | E13: -8532713.9 | F13: 398421.37 | G13: 0.015 | I13: -8532733 | J13: 398040.06 | K13: 0.008 | M13: -8532731.8 | N13: 398041.67 | O13: 0.005 | Q13: -8532672.1 | R13: 398373.25 | S13: 0.052 | U13: -8532701.3 | V13: 398416.89 | W13: 0.051 | Y13: -8532431.5 | Z13: 397979.61 | AA13: 0.054 | AC13: -8532451 | AD13: 398031.15 | AE13: 0.038 | AG13: -8532451.2 | AH13: 398031.25 | AI13: 0.037 | AK13: -8532443.2 | AL13: 398008.7 | AM13: 0.06 | AO13: -8532443.2 | AP13: 398008.7 | AQ13: 0.06 | AS13: -8532448.8 | AT13: 398030.54 | AU13: 0.039 | AW13: -8532448.8 | AX13: 398030.54 | AY13: 0.039 | BA13: -8532448.8 | BB13: 398030.54 | BC13: 0.039 | BE13: -8532448.8 | BF13: 398030.54 | BG13: 0.039 | BI13: -8532448.8 | BJ13: 398030.54 | BK13: 0.039 | BM13: -8532448.8 | BN13: 398030.54 | BO13: 0.039 | BQ13: -8532448.8 | BR13: 398030.54 | BS13: 0.039 | BU13: -8532448.8 | BV13: 398030.54 | BW13: 0.039 | BY13: -8532448.8 | BZ13: 398030.54 | CA13: 0.039 | CC13: -8532448.8 | CD13: 398030.54 | CE13: 0.039 | CG13: -8532449.4 | CH13: 398032.51 | CI13: 0.034 | CK13: -8532449.4 | CL13: 398032.51 | CM13: 0.034 | CO13: -8532753.9 | CP13: 398012.53 | CQ13: 26.091 | CS13: -8532753.9 | CT13: 398012.53 | CU13: 26.091 | CW13: -8532753.9 | CX13: 398012.53 | CY13: 26.091 | DA13: -8532752 | DB13: 398017.21 | DC13: 20.551 | DE13: -8532733.7 | DF13: 398027.87 | DG13: 0.012 | DI13: -8532732.3 | DJ13: 398028.32 | DK13: 11.374 | DM13: -8532448.8 | DN13: 398030.54 | DO13: 0.039 | DQ13: -8532448.8 | DR13: 398030.54 | DS13: 0.039 | DU13: -8532753.9 | DV13: 398012.53 | DW13: 26.091 | DY13: -8532752.6 | DZ13: 398009.73 | EA13: 0.026 | EC13: -8532726.8 | ED13: 398050.09 | EE13: 0.026 | EG13: -8539886.1 | EH13: 396751.72 | EI13: 0.027 | EK13: -8534358.8 | EL13: 399612.66 | EM13: 0.085 | EO13: -8532090.4 | EP13: 398417.52 | EQ13: 0.042 | ES13: -8532409.1 | ET13: 396951.84 | EU13: 0.161 | EW13: -8532687.7 | EX13: 397294.39 | EY13: 0.036 | FA13: -8528662.9 | FB13: 395753.21 | FC13: 0.036 | FE13: -8533686.1 | FF13: 394997.72 | FG13: 0.091 | FI13: -8532734.5 | FJ13: 397952.19 | FK13: 27.991 | FM13: -8529282.1 | FN13: 393842.49 | FO13: 30.836 | FQ13: -8533135.2 | FR13: 396348.38 | FS13: 32.713 | FU13: -8534390 | FV13: 399649.2 | FW13: 0.076 | FY13: -8529360.1 | FZ13: 396485.02 | GA13: 0.04 | GC13: -8530431.6 | GD13: 396627.76 | GE13: 50.356 | GG13: -8529852.1 | GH13: 396407.61 | GI13: 38.2 | GK13: -8532727.8 | GL13: 398080.08 | GM13: 0.068 | GO13: -8532277.2 | GP13: 397117.32 | GQ13: 0.044 | GS13: -8530618.5 | GT13: 397039.27 | GU13: 0.013 | GW13: -8531743.1 | GX13: 397827.25 | GY13: 172.329 | HA13: -8532225.7 | HB13: 397907.91 | HC13: 86.436 | HE13: -8533797.5 | HF13: 396930.09 | HG13: 0.055 | HI13: -8531631.9 | HJ13: 397940.29 | HK13: 0.072 | HM13: -8532952.6 | HN13: 396948.57 | HO13: 0.027 | HQ13: -8531946.5 | HR13: 397852.01 | HS13: 0.043 | HU13: -8532216.3 | HV13: 397316.07 | HW13: 0.045 | HY13: -8539847.4 | HZ13: 397984.46 | IA13: 0.046 | IC13: -8532730.3 | ID13: 397977.08 | IE13: 0.066 | IG13: -8531734.6 | IH13: 397653.24 | II13: 0.051 | IK13: -8532958.6 | IL13: 396051.62 | IM13: 0.19 | IO13: -8534715.9 | IP13: 401426.21 | IQ13: 0.034
